Workbook

Sheet README
A1: README - Governed Multi-Brand Agentic System Project Workbook
A3: Project Window: Friday, September 11, 2026 through Wednesday, October 14, 2026 (34 calendar days)
A4: Source of Truth: Project_Plan_Essentials-Governed_Multi-Brand_Agentic_System.md + Final-Level_Full_Architecture.md
A6: 1. Where to update tasks:
A7: - Go to Tracker sheet. Editable columns are highlighted in light yellow: Start Date, End Date, Predecessor, Dependency Type, Resource/Owner, Status, Progress %, Milestone YES/NO, Milestone ID, Priority, Notes.
A8: - Duration, Conflict/Validation, Current State, Latest Pred End are calculated (light blue) and update automatically.
A9: - All dates use YYYY-MM-DD format. Duration = End-Start+1 inclusive calendar days.
A11: 2. How to change dates and dependencies:
A12: - Edit Start Date / End Date directly in Tracker (cols E,F). Gantt bars recalculate via formulas =IF(AND(date>=Start,date<=End),...)
A13: - Predecessor format: comma-separated Task IDs e.g. 'T01, T02' or 'None'. Use exact IDs from column A.
A14: - Latest Predecessor End (col S) = MAX(XLOOKUP(TEXTSPLIT(Predecessor),TaskID,EndDate)). Conflict column Q flags '⚠ Pred conflict' if Start <= Latest Pred End.
A15: - Dependency Type defaults to FS (Finish-to-Start) per architecture spec. Editable via dropdown FS/SS/FF/SF.
... A56: - Missing: Platform API credentials, exact budget figures - noted in Milestones/Notes and assumed injected via vault during T25.

Sheet Tracker
A1: Task ID | B1: Phase / Workstream | C1: Task Name | D1: Task Description | E1: Start Date | F1: End Date | G1: Duration | H1: Predecessor / Dependency | I1: Dependency Type | J1: Assigned Resource / Owner | K1: Status | L1: Progress % | M1: Milestone (YES/NO) | N1: Milestone ID | O1: Priority | P1: Notes | Q1: Conflict / Validation | R1: Current State | S1: Latest Pred End
A2: T01 | B2: Phase 1: Governance, Policy & Canonical State | C2: Define enterprise objectives, tenant scopes, and budget boundaries | D2: Define strategic objectives, tenant scopes, budgets, risk appetite. Input from Brand Stakeholder/Portfolio Owner. Output: approved scope envelope and budget boundaries per brand. Governed by Model A. | E2: 46276 | F2: 46277 | G2: =IF(AND(E2<>"",F2<>""),F2-E2+1,"") | H2: None | I2: FS | J2: Brand Stakeholder / Portfolio Owner | K2: Completed | L2: 1 | M2: NO | N2: M1 | O2: Critical | P2: Architectural scope, objectives, and budget envelopes established in source blueprint. [INFERRED: 100%] | Q2: =IF(F2<E2,"⚠ End < Start",IF(OR(E2<DATE(2026,9,11),F2>DATE(2026,10,14)),"⚠ Outside 09/11-10/14",IF(AND(H2<>"None",H2<>"",S2<>"",S2<>0,E2<=S2),"⚠ Pred conflict","✓ OK"))) | R2: =IF(L2=1,"Completed",IF(F2<Dashboard!$B$2,"Overdue",IF(AND(E2<=Dashboard!$B$2,F2>=Dashboard!$B$2),IF(L2>0,"Active","At Risk"),IF(E2>Dashboard!$B$2,"Upcoming","At Risk")))) | S2: =IF(OR(H2="",H2="None"),"",LET(ids,TEXTSPLIT(H2,", ",,TRUE),MAX(XLOOKUP(ids,$A$2:$A$35,$F$2:$F$35,0))))
A3: T02 | B3: Phase 1: Governance, Policy & Canonical State | C3: Configure machine-readable policy rules, autonomy tiers, and claim limits | D3: Configure machine-readable policy rules, autonomy tiers, claim limits, legal constraints in Enterprise Policy Engine. Versioned policy envelopes with tenant isolation. | E3: 46276 | F3: 46277 | G3: =IF(AND(E3<>"",F3<>""),F3-E3+1,"") | H3: None | I3: FS | J3: Enterprise Policy Engine | K3: Completed | L3: 1 | M3: NO | N3: M1 | O3: Critical | P3: Compliance rules, autonomy tiers, and brand constraints defined in policy engine specification. [INFERRED: 100%] | Q3: =IF(F3<E3,"⚠ End < Start",IF(OR(E3<DATE(2026,9,11),F3>DATE(2026,10,14)),"⚠ Outside 09/11-10/14",IF(AND(H3<>"None",H3<>"",S3<>"",S3<>0,E3<=S3),"⚠ Pred conflict","✓ OK"))) | R3: =IF(L3=1,"Completed",IF(F3<Dashboard!$B$2,"Overdue",IF(AND(E3<=Dashboard!$B$2,F3>=Dashboard!$B$2),IF(L3>0,"Active","At Risk"),IF(E3>Dashboard!$B$2,"Upcoming","At Risk")))) | S3: =IF(OR(H3="",H3="None"),"",LET(ids,TEXTSPLIT(H3,", ",,TRUE),MAX(XLOOKUP(ids,$A$2:$A$35,$F$2:$F$35,0))))
A4: T03 | B4: Phase 1: Governance, Policy & Canonical State | C4: Establish Policy & Authorization Boundary (PAB) evaluation rules | D4: Establish Policy & Authorization Boundary evaluation: caller ID, delegation chain, tenant scope, risk tier, monotonic attenuation, tool allowlisting. Security gate for all downstream. | E4: 46277 | F4: 46279 | G4: =IF(AND(E4<>"",F4<>""),F4-E4+1,"") | H4: T01, T02 | I4: FS | J4: Policy & Authorization Boundary (PAB) | K4: Completed | L4: 1 | M4: YES | N4: M1 | O4: Critical | P4: PAB monotonic attenuation logic and verification formulas validated in control plane. [INFERRED: 100%] | Q4: =IF(F4<E4,"⚠ End < Start",IF(OR(E4<DATE(2026,9,11),F4>DATE(2026,10,14)),"⚠ Outside 09/11-10/14",IF(AND(H4<>"None",H4<>"",S4<>"",S4<>0,E4<=S4),"⚠ Pred conflict","✓ OK"))) | R4: =IF(L4=1,"Completed",IF(F4<Dashboard!$B$2,"Overdue",IF(AND(E4<=Dashboard!$B$2,F4>=Dashboard!$B$2),IF(L4>0,"Active","At Risk"),IF(E4>Dashboard!$B$2,"Upcoming","At Risk")))) | S4: =IF(OR(H4="",H4="None"),"",LET(ids,TEXTSPLIT(H4,", ",,TRUE),MAX(XLOOKUP(ids,$A$2:$A$35,$F$2:$F$35,0))))
A5: T04 | B5: Phase 1: Governance, Policy & Canonical State | C5: Initialize Canonical Task State Machine (CTS) and DAG execution schema | D5: Initialize Canonical Task State Machine and DAG execution schema: lifecycle states CREATED→COMPLETED, checkpoints, holds, dependency locks, state ledger. | E5: 46277 | F5: 46279 | G5: =IF(AND(E5<>"",F5<>""),F5-E5+1,"") | H5: T01 | I5: FS | J5: Canonical Task State Machine (CTS) | K5: Completed | L5: 1 | M5: YES | N5: M1 | O5: Critical | P5: Canonical Task State Machine lifecycle states (CREATED to COMPLETED) configured. [INFERRED: 100%] | Q5: =IF(F5<E5,"⚠ End < Start",IF(OR(E5<DATE(2026,9,11),F5>DATE(2026,10,14)),"⚠ Outside 09/11-10/14",IF(AND(H5<>"None",H5<>"",S5<>"",S5<>0,E5<=S5),"⚠ Pred conflict","✓ OK"))) | R5: =IF(L5=1,"Completed",IF(F5<Dashboard!$B$2,"Overdue",IF(AND(E5<=Dashboard!$B$2,F5>=Dashboard!$B$2),IF(L5>0,"Active","At Risk"),IF(E5>Dashboard!$B$2,"Upcoming","At Risk")))) | S5: =IF(OR(H5="",H5="None"),"",LET(ids,TEXTSPLIT(H5,", ",,TRUE),MAX(XLOOKUP(ids,$A$2:$A$35,$F$2:$F$35,0))))
A6: T05 | B6: Phase 2: Governed Data Plane & Central Storage | C6: Provision Central Enterprise Database (CDB) relational tables & vector stores | D6: Provision Central Enterprise Database: relational tables, JSONB docs, vector namespaces, embeddings, state ledgers, telemetry time-series. System of record. | E6: 46279 | F6: 46281 | G6: =IF(AND(E6<>"",F6<>""),F6-E6+1,"") | H6: T04 | I6: FS | J6: Central Enterprise Database (CDB) | K6: Completed | L6: 1 | M6: NO | N6: M2 | O6: High | P6: Relational tables, JSONB schemas, and pgvector stores defined in Central DB model. [INFERRED: 100%] | Q6: =IF(F6<E6,"⚠ End < Start",IF(OR(E6<DATE(2026,9,11),F6>DATE(2026,10,14)),"⚠ Outside 09/11-10/14",IF(AND(H6<>"None",H6<>"",S6<>"",S6<>0,E6<=S6),"⚠ Pred conflict","✓ OK"))) | R6: =IF(L6=1,"Completed",IF(F6<Dashboard!$B$2,"Overdue",IF(AND(E6<=Dashboard!$B$2,F6>=Dashboard!$B$2),IF(L6>0,"Active","At Risk"),IF(E6>Dashboard!$B$2,"Upcoming","At Risk")))) | S6: =IF(OR(H6="",H6="None"),"",LET(ids,TEXTSPLIT(H6,", ",,TRUE),MAX(XLOOKUP(ids,$A$2:$A$35,$F$2:$F$35,0))))
A7: T06 | B7: Phase 2: Governed Data Plane & Central Storage | C7: Connect Headless CMS content models and staging layout schemas | D7: Connect Headless CMS content models and staging layout schemas: page models, catalog diffs, digital assets, staged schemas for W_DEV consumption. | E7: 46279 | F7: 46281 | G7: =IF(AND(E7<>"",F7<>""),F7-E7+1,"") | H7: T04 | I7: FS | J7: Headless CMS & Web Store (CMS) | K7: Completed | L7: 1 | M7: NO | N7: M2 | O7: High | P7: Headless CMS content schemas and staging layout diffs integrated. [INFERRED: 100%] | Q7: =IF(F7<E7,"⚠ End < Start",IF(OR(E7<DATE(2026,9,11),F7>DATE(2026,10,14)),"⚠ Outside 09/11-10/14",IF(AND(H7<>"None",H7<>"",S7<>"",S7<>0,E7<=S7),"⚠ Pred conflict","✓ OK"))) | R7: =IF(L7=1,"Completed",IF(F7<Dashboard!$B$2,"Overdue",IF(AND(E7<=Dashboard!$B$2,F7>=Dashboard!$B$2),IF(L7>0,"Active","At Risk"),IF(E7>Dashboard!$B$2,"Upcoming","At Risk")))) | S7: =IF(OR(H7="",H7="None"),"",LET(ids,TEXTSPLIT(H7,", ",,TRUE),MAX(XLOOKUP(ids,$A$2:$A$35,$F$2:$F$35,0))))
A8: T07 | B8: Phase 2: Governed Data Plane & Central Storage | C8: Instantiate Institutional Memory Store (MEM) for brand heuristics & rules | D8: Instantiate Institutional Memory Store for brand heuristics, voice rules, learned heuristics, long-term knowledge promotion from W_LEARN. | E8: 46279 | F8: 46281 | G8: =IF(AND(E8<>"",F8<>""),F8-E8+1,"") | H8: T04 | I8: FS | J8: Institutional Memory Store (MEM) | K8: Completed | L8: 1 | M8: NO | N8: M2 | O8: High | P8: Long-term institutional memory schemas and brand book namespaces established. [INFERRED: 100%] | Q8: =IF(F8<E8,"⚠ End < Start",IF(OR(E8<DATE(2026,9,11),F8>DATE(2026,10,14)),"⚠ Outside 09/11-10/14",IF(AND(H8<>"None",H8<>"",S8<>"",S8<>0,E8<=S8),"⚠ Pred conflict","✓ OK"))) | R8: =IF(L8=1,"Completed",IF(F8<Dashboard!$B$2,"Overdue",IF(AND(E8<=Dashboard!$B$2,F8>=Dashboard!$B$2),IF(L8>0,"Active","At Risk"),IF(E8>Dashboard!$B$2,"Upcoming","At Risk")))) | S8: =IF(OR(H8="",H8="None"),"",LET(ids,TEXTSPLIT(H8,", ",,TRUE),MAX(XLOOKUP(ids,$A$2:$A$35,$F$2:$F$35,0))))
A9: T08 | B9: Phase 2: Governed Data Plane & Central Storage | C9: Configure Artifact & Evidence Registry (ART) for UUID/hash deliverables | D9: Configure Artifact & Evidence Registry for UUID/hash deliverables: content-addressable storage, SHA-256 validation, copy packs, code diffs, dossiers. | E9: 46281 | F9: 46283 | G9: =IF(AND(E9<>"",F9<>""),F9-E9+1,"") | H9: T05 | I9: FS | J9: Artifact & Evidence Registry (ART) | K9: Completed | L9: 1 | M9: NO | N9: M2 | O9: Medium | P9: Content-addressable artifact storage with UUID and SHA-256 hash validation defined. [INFERRED: 100%] | Q9: =IF(F9<E9,"⚠ End < Start",IF(OR(E9<DATE(2026,9,11),F9>DATE(2026,10,14)),"⚠ Outside 09/11-10/14",IF(AND(H9<>"None",H9<>"",S9<>"",S9<>0,E9<=S9),"⚠ Pred conflict","✓ OK"))) | R9: =IF(L9=1,"Completed",IF(F9<Dashboard!$B$2,"Overdue",IF(AND(E9<=Dashboard!$B$2,F9>=Dashboard!$B$2),IF(L9>0,"Active","At Risk"),IF(E9>Dashboard!$B$2,"Upcoming","At Risk")))) | S9: =IF(OR(H9="",H9="None"),"",LET(ids,TEXTSPLIT(H9,", ",,TRUE),MAX(XLOOKUP(ids,$A$2:$A$35,$F$2:$F$35,0))))
A10: T09 | B10: Phase 2: Governed Data Plane & Central Storage | C10: Deploy Governed MCP Data Boundary CRUD gateways & connection pools | D10: Deploy Governed MCP Data Boundary CRUD gateways & connection pools: schema-validated read/write facades over CDB, CMS, MEM, ART. | E10: 46281 | F10: 46283 | G10: =IF(AND(E10<>"",F10<>""),F10-E10+1,"") | H10: T05, T06, T07 | I10: FS | J10: Governed MCP Data Boundary | K10: Completed | L10: 1 | M10: NO | N10: M2 | O10: Critical | P10: MCP Data Boundary read/write CRUD capability facades verified against storage layer. [INFERRED: 100%] | Q10: =IF(F10<E10,"⚠ End < Start",IF(OR(E10<DATE(2026,9,11),F10>DATE(2026,10,14)),"⚠ Outside 09/11-10/14",IF(AND(H10<>"None",H10<>"",S10<>"",S10<>0,E10<=S10),"⚠ Pred conflict","✓ OK"))) | R10: =IF(L10=1,"Completed",IF(F10<Dashboard!$B$2,"Overdue",IF(AND(E10<=Dashboard!$B$2,F10>=Dashboard!$B$2),IF(L10>0,"Active","At Risk"),IF(E10>Dashboard!$B$2,"Upcoming","At Risk")))) | S10: =IF(OR(H10="",H10="None"),"",LET(ids,TEXTSPLIT(H10,", ",,TRUE),MAX(XLOOKUP(ids,$A$2:$A$35,$F$2:$F$35,0))))
A11: T10 | B11: Phase 2: Governed Data Plane & Central Storage | C11: Configure Agentic RAG Controller with tenant isolation & freshness gates | D11: Configure Agentic RAG Controller with tenant isolation, freshness gates, provenance attestation, vector indexing. Exclusive broker under Model A. | E11: 46283 | F11: 46284 | G11: =IF(AND(E11<>"",F11<>""),F11-E11+1,"") | H11: T03, T09 | I11: FS | J11: Agentic RAG Controller | K11: Completed | L11: 1 | M11: YES | N11: M2 | O11: Critical | P11: Model A Agentic RAG Controller deployed with tenant-scoped filtering and provenance tagging. [INFERRED: 100%] | Q11: =IF(F11<E11,"⚠ End < Start",IF(OR(E11<DATE(2026,9,11),F11>DATE(2026,10,14)),"⚠ Outside 09/11-10/14",IF(AND(H11<>"None",H11<>"",S11<>"",S11<>0,E11<=S11),"⚠ Pred conflict","✓ OK"))) | R11: =IF(L11=1,"Completed",IF(F11<Dashboard!$B$2,"Overdue",IF(AND(E11<=Dashboard!$B$2,F11>=Dashboard!$B$2),IF(L11>0,"Active","At Risk"),IF(E11>Dashboard!$B$2,"Upcoming","At Risk")))) | S11: =IF(OR(H11="",H11="None"),"",LET(ids,TEXTSPLIT(H11,", ",,TRUE),MAX(XLOOKUP(ids,$A$2:$A$35,$F$2:$F$35,0))))
A12: T11 | B12: Phase 3: Sandbox Isolation & Sub-Agent Readiness | C12: Deploy agent_sandbox with cgroups, seccomp, and tmpfs isolation | D12: Deploy agent_sandbox with cgroups, seccomp, tmpfs isolation: micro-VM/container layer for all ephemeral sub-agents and micro-tools. | E12: 46283 | F12: 46285 | G12: =IF(AND(E12<>"",F12<>""),F12-E12+1,"") | H12: T03 | I12: FS | J12: Sandbox Controller (agent_sandbox) | K12: Completed | L12: 1 | M12: NO | N12: M3 | O12: Critical | P12: agent_sandbox (AIO Sandbox) virtualized container environment instantiated. [INFERRED: 100%] | Q12: =IF(F12<E12,"⚠ End < Start",IF(OR(E12<DATE(2026,9,11),F12>DATE(2026,10,14)),"⚠ Outside 09/11-10/14",IF(AND(H12<>"None",H12<>"",S12<>"",S12<>0,E12<=S12),"⚠ Pred conflict","✓ OK"))) | R12: =IF(L12=1,"Completed",IF(F12<Dashboard!$B$2,"Overdue",IF(AND(E12<=Dashboard!$B$2,F12>=Dashboard!$B$2),IF(L12>0,"Active","At Risk"),IF(E12>Dashboard!$B$2,"Upcoming","At Risk")))) | S12: =IF(OR(H12="",H12="None"),"",LET(ids,TEXTSPLIT(H12,", ",,TRUE),MAX(XLOOKUP(ids,$A$2:$A$35,$F$2:$F$35,0))))
A13: T12 | B13: Phase 3: Sandbox Isolation & Sub-Agent Readiness | C13: Configure sandbox network proxy with strict egress allowlisting (DENY_ALL) | D13: Configure sandbox network proxy with strict egress allowlisting (DENY_ALL): default deny, domain-whitelisted proxy for S_SCRAPE, block metadata endpoints. | E13: 46285 | F13: 46286 | G13: =IF(AND(E13<>"",F13<>""),F13-E13+1,"") | H13: T11 | I13: FS | J13: Sandbox Controller (agent_sandbox) | K13: Completed | L13: 1 | M13: NO | N13: M3 | O13: High | P13: Network egress firewall configured with default DENY_ALL policy and domain whitelist proxy. [INFERRED: 100%] | Q13: =IF(F13<E13,"⚠ End < Start",IF(OR(E13<DATE(2026,9,11),F13>DATE(2026,10,14)),"⚠ Outside 09/11-10/14",IF(AND(H13<>"None",H13<>"",S13<>"",S13<>0,E13<=S13),"⚠ Pred conflict","✓ OK"))) | R13: =IF(L13=1,"Completed",IF(F13<Dashboard!$B$2,"Overdue",IF(AND(E13<=Dashboard!$B$2,F13>=Dashboard!$B$2),IF(L13>0,"Active","At Risk"),IF(E13>Dashboard!$B$2,"Upcoming","At Risk")))) | S13: =IF(OR(H13="",H13="None"),"",LET(ids,TEXTSPLIT(H13,", ",,TRUE),MAX(XLOOKUP(ids,$A$2:$A$35,$F$2:$F$35,0))))
... A35: T34 | B35: Phase 7: Telemetry Optimization & Closeout | C35: Perform final project verification against acceptance criteria & close | D35: Perform final project verification against acceptance criteria & close: final verification, acceptance, contract closure on 2026-10-14. | E35: 46309 | F35: 46309 | G35: =IF(AND(E35<>"",F35<>""),F35-E35+1,"") | H35: T32, T33 | I35: FS | J35: Intelligence Engine & Brand Owner | K35: Not Started | L35: 0 | M35: YES | N35: M7 | O35: Critical | P35: Final project sign-off and contract closure scheduled for 2026-10-14. [INFERRED: 0% - Milestone M7] | Q35: =IF(F35<E35,"⚠ End < Start",IF(OR(E35<DATE(2026,9,11),F35>DATE(2026,10,14)),"⚠ Outside 09/11-10/14",IF(AND(H35<>"None",H35<>"",S35<>"",S35<>0,E35<=S35),"⚠ Pred conflict","✓ OK"))) | R35: =IF(L35=1,"Completed",IF(F35<Dashboard!$B$2,"Overdue",IF(AND(E35<=Dashboard!$B$2,F35>=Dashboard!$B$2),IF(L35>0,"Active","At Risk"),IF(E35>Dashboard!$B$2,"Upcoming","At Risk")))) | S35: =IF(OR(H35="",H35="None"),"",LET(ids,TEXTSPLIT(H35,", ",,TRUE),MAX(XLOOKUP(ids,$A$2:$A$35,$F$2:$F$35,0))))

Sheet Gantt
A1: Governed Multi-Brand Agentic System - Gantt Timeline (Sep 11 - Oct 14, 2026)
A2: Task ID | B2: Phase / Workstream | C2: Task Name | D2: Resource | E2: Status | F2: Progress % | G2: Start Date | H2: End Date | I2: Milestone? | J2: 46276 | K2: 46277 | L2: 46278 | M2: 46279 | N2: 46280 | O2: 46281 | P2: 46282 | Q2: 46283 | R2: 46284 | S2: 46285 | T2: 46286 | U2: 46287 | V2: 46288 | W2: 46289 | X2: 46290 | Y2: 46291 | Z2: 46292 | AA2: 46293 | AB2: 46294 | AC2: 46295 | AD2: 46296 | AE2: 46297 | AF2: 46298 | AG2: 46299 | AH2: 46300 | AI2: 46301 | AJ2: 46302 | AK2: 46303 | AL2: 46304 | AM2: 46305 | AN2: 46306 | AO2: 46307 | AP2: 46308 | AQ2: 46309
J3: Fri | K3: Sat | L3: Sun | M3: Mon | N3: Tue | O3: Wed | P3: Thu | Q3: Fri | R3: Sat | S3: Sun | T3: Mon | U3: Tue | V3: Wed | W3: Thu | X3: Fri | Y3: Sat | Z3: Sun | AA3: Mon | AB3: Tue | AC3: Wed | AD3: Thu | AE3: Fri | AF3: Sat | AG3: Sun | AH3: Mon | AI3: Tue | AJ3: Wed | AK3: Thu | AL3: Fri | AM3: Sat | AN3: Sun | AO3: Mon | AP3: Tue | AQ3: Wed
J4: 09/11 | K4: 09/12 | L4: 09/13 | M4: 09/14 | N4: 09/15 | O4: 09/16 | P4: 09/17 | Q4: 09/18 | R4: 09/19 | S4: 09/20 | T4: 09/21 | U4: 09/22 | V4: 09/23 | W4: 09/24 | X4: 09/25 | Y4: 09/26 | Z4: 09/27 | AA4: 09/28 | AB4: 09/29 | AC4: 09/30 | AD4: 10/01 | AE4: 10/02 | AF4: 10/03 | AG4: 10/04 | AH4: 10/05 | AI4: 10/06 | AJ4: 10/07 | AK4: 10/08 | AL4: 10/09 | AM4: 10/10 | AN4: 10/11 | AO4: 10/12 | AP4: 10/13 | AQ4: 10/14
A5: =Tracker!A2 | B5: =Tracker!B2 | C5: =Tracker!C2 | D5: =Tracker!J2 | E5: =Tracker!K2 | F5: =Tracker!L2 | G5: =Tracker!E2 | H5: =Tracker!F2 | I5: =Tracker!M2 | J5: =IF(AND(J$2>=$G5,J$2<=$H5),IF(AND($I5="YES",J$2=$H5),3,IF($F5=1,4,IF(J$2<=$G5+($H5-$G5+1)*$F5-1,1,2))),"") | K5: =IF(AND(K$2>=$G5,K$2<=$H5),IF(AND($I5="YES",K$2=$H5),3,IF($F5=1,4,IF(K$2<=$G5+($H5-$G5+1)*$F5-1,1,2))),"") | L5: =IF(AND(L$2>=$G5,L$2<=$H5),IF(AND($I5="YES",L$2=$H5),3,IF($F5=1,4,IF(L$2<=$G5+($H5-$G5+1)*$F5-1,1,2))),"") | M5: =IF(AND(M$2>=$G5,M$2<=$H5),IF(AND($I5="YES",M$2=$H5),3,IF($F5=1,4,IF(M$2<=$G5+($H5-$G5+1)*$F5-1,1,2))),"") | N5: =IF(AND(N$2>=$G5,N$2<=$H5),IF(AND($I5="YES",N$2=$H5),3,IF($F5=1,4,IF(N$2<=$G5+($H5-$G5+1)*$F5-1,1,2))),"") | O5: =IF(AND(O$2>=$G5,O$2<=$H5),IF(AND($I5="YES",O$2=$H5),3,IF($F5=1,4,IF(O$2<=$G5+($H5-$G5+1)*$F5-1,1,2))),"") | P5: =IF(AND(P$2>=$G5,P$2<=$H5),IF(AND($I5="YES",P$2=$H5),3,IF($F5=1,4,IF(P$2<=$G5+($H5-$G5+1)*$F5-1,1,2))),"") | Q5: =IF(AND(Q$2>=$G5,Q$2<=$H5),IF(AND($I5="YES",Q$2=$H5),3,IF($F5=1,4,IF(Q$2<=$G5+($H5-$G5+1)*$F5-1,1,2))),"") | ... AQ5: =IF(AND(AQ$2>=$G5,AQ$2<=$H5),IF(AND($I5="YES",AQ$2=$H5),3,IF($F5=1,4,IF(AQ$2<=$G5+($H5-$G5+1)*$F5-1,1,2))),"")
A6: =Tracker!A3 | B6: =Tracker!B3 | C6: =Tracker!C3 | D6: =Tracker!J3 | E6: =Tracker!K3 | F6: =Tracker!L3 | G6: =Tracker!E3 | H6: =Tracker!F3 | I6: =Tracker!M3 | J6: =IF(AND(J$2>=$G6,J$2<=$H6),IF(AND($I6="YES",J$2=$H6),3,IF($F6=1,4,IF(J$2<=$G6+($H6-$G6+1)*$F6-1,1,2))),"") | K6: =IF(AND(K$2>=$G6,K$2<=$H6),IF(AND($I6="YES",K$2=$H6),3,IF($F6=1,4,IF(K$2<=$G6+($H6-$G6+1)*$F6-1,1,2))),"") | L6: =IF(AND(L$2>=$G6,L$2<=$H6),IF(AND($I6="YES",L$2=$H6),3,IF($F6=1,4,IF(L$2<=$G6+($H6-$G6+1)*$F6-1,1,2))),"") | M6: =IF(AND(M$2>=$G6,M$2<=$H6),IF(AND($I6="YES",M$2=$H6),3,IF($F6=1,4,IF(M$2<=$G6+($H6-$G6+1)*$F6-1,1,2))),"") | N6: =IF(AND(N$2>=$G6,N$2<=$H6),IF(AND($I6="YES",N$2=$H6),3,IF($F6=1,4,IF(N$2<=$G6+($H6-$G6+1)*$F6-1,1,2))),"") | O6: =IF(AND(O$2>=$G6,O$2<=$H6),IF(AND($I6="YES",O$2=$H6),3,IF($F6=1,4,IF(O$2<=$G6+($H6-$G6+1)*$F6-1,1,2))),"") | P6: =IF(AND(P$2>=$G6,P$2<=$H6),IF(AND($I6="YES",P$2=$H6),3,IF($F6=1,4,IF(P$2<=$G6+($H6-$G6+1)*$F6-1,1,2))),"") | Q6: =IF(AND(Q$2>=$G6,Q$2<=$H6),IF(AND($I6="YES",Q$2=$H6),3,IF($F6=1,4,IF(Q$2<=$G6+($H6-$G6+1)*$F6-1,1,2))),"") | ... AQ6: =IF(AND(AQ$2>=$G6,AQ$2<=$H6),IF(AND($I6="YES",AQ$2=$H6),3,IF($F6=1,4,IF(AQ$2<=$G6+($H6-$G6+1)*$F6-1,1,2))),"")
A7: =Tracker!A4 | B7: =Tracker!B4 | C7: =Tracker!C4 | D7: =Tracker!J4 | E7: =Tracker!K4 | F7: =Tracker!L4 | G7: =Tracker!E4 | H7: =Tracker!F4 | I7: =Tracker!M4 | J7: =IF(AND(J$2>=$G7,J$2<=$H7),IF(AND($I7="YES",J$2=$H7),3,IF($F7=1,4,IF(J$2<=$G7+($H7-$G7+1)*$F7-1,1,2))),"") | K7: =IF(AND(K$2>=$G7,K$2<=$H7),IF(AND($I7="YES",K$2=$H7),3,IF($F7=1,4,IF(K$2<=$G7+($H7-$G7+1)*$F7-1,1,2))),"") | L7: =IF(AND(L$2>=$G7,L$2<=$H7),IF(AND($I7="YES",L$2=$H7),3,IF($F7=1,4,IF(L$2<=$G7+($H7-$G7+1)*$F7-1,1,2))),"") | M7: =IF(AND(M$2>=$G7,M$2<=$H7),IF(AND($I7="YES",M$2=$H7),3,IF($F7=1,4,IF(M$2<=$G7+($H7-$G7+1)*$F7-1,1,2))),"") | N7: =IF(AND(N$2>=$G7,N$2<=$H7),IF(AND($I7="YES",N$2=$H7),3,IF($F7=1,4,IF(N$2<=$G7+($H7-$G7+1)*$F7-1,1,2))),"") | O7: =IF(AND(O$2>=$G7,O$2<=$H7),IF(AND($I7="YES",O$2=$H7),3,IF($F7=1,4,IF(O$2<=$G7+($H7-$G7+1)*$F7-1,1,2))),"") | P7: =IF(AND(P$2>=$G7,P$2<=$H7),IF(AND($I7="YES",P$2=$H7),3,IF($F7=1,4,IF(P$2<=$G7+($H7-$G7+1)*$F7-1,1,2))),"") | Q7: =IF(AND(Q$2>=$G7,Q$2<=$H7),IF(AND($I7="YES",Q$2=$H7),3,IF($F7=1,4,IF(Q$2<=$G7+($H7-$G7+1)*$F7-1,1,2))),"") | ... AQ7: =IF(AND(AQ$2>=$G7,AQ$2<=$H7),IF(AND($I7="YES",AQ$2=$H7),3,IF($F7=1,4,IF(AQ$2<=$G7+($H7-$G7+1)*$F7-1,1,2))),"")
A8: =Tracker!A5 | B8: =Tracker!B5 | C8: =Tracker!C5 | D8: =Tracker!J5 | E8: =Tracker!K5 | F8: =Tracker!L5 | G8: =Tracker!E5 | H8: =Tracker!F5 | I8: =Tracker!M5 | J8: =IF(AND(J$2>=$G8,J$2<=$H8),IF(AND($I8="YES",J$2=$H8),3,IF($F8=1,4,IF(J$2<=$G8+($H8-$G8+1)*$F8-1,1,2))),"") | K8: =IF(AND(K$2>=$G8,K$2<=$H8),IF(AND($I8="YES",K$2=$H8),3,IF($F8=1,4,IF(K$2<=$G8+($H8-$G8+1)*$F8-1,1,2))),"") | L8: =IF(AND(L$2>=$G8,L$2<=$H8),IF(AND($I8="YES",L$2=$H8),3,IF($F8=1,4,IF(L$2<=$G8+($H8-$G8+1)*$F8-1,1,2))),"") | M8: =IF(AND(M$2>=$G8,M$2<=$H8),IF(AND($I8="YES",M$2=$H8),3,IF($F8=1,4,IF(M$2<=$G8+($H8-$G8+1)*$F8-1,1,2))),"") | N8: =IF(AND(N$2>=$G8,N$2<=$H8),IF(AND($I8="YES",N$2=$H8),3,IF($F8=1,4,IF(N$2<=$G8+($H8-$G8+1)*$F8-1,1,2))),"") | O8: =IF(AND(O$2>=$G8,O$2<=$H8),IF(AND($I8="YES",O$2=$H8),3,IF($F8=1,4,IF(O$2<=$G8+($H8-$G8+1)*$F8-1,1,2))),"") | P8: =IF(AND(P$2>=$G8,P$2<=$H8),IF(AND($I8="YES",P$2=$H8),3,IF($F8=1,4,IF(P$2<=$G8+($H8-$G8+1)*$F8-1,1,2))),"") | Q8: =IF(AND(Q$2>=$G8,Q$2<=$H8),IF(AND($I8="YES",Q$2=$H8),3,IF($F8=1,4,IF(Q$2<=$G8+($H8-$G8+1)*$F8-1,1,2))),"") | ... AQ8: =IF(AND(AQ$2>=$G8,AQ$2<=$H8),IF(AND($I8="YES",AQ$2=$H8),3,IF($F8=1,4,IF(AQ$2<=$G8+($H8-$G8+1)*$F8-1,1,2))),"")
A9: =Tracker!A6 | B9: =Tracker!B6 | C9: =Tracker!C6 | D9: =Tracker!J6 | E9: =Tracker!K6 | F9: =Tracker!L6 | G9: =Tracker!E6 | H9: =Tracker!F6 | I9: =Tracker!M6 | J9: =IF(AND(J$2>=$G9,J$2<=$H9),IF(AND($I9="YES",J$2=$H9),3,IF($F9=1,4,IF(J$2<=$G9+($H9-$G9+1)*$F9-1,1,2))),"") | K9: =IF(AND(K$2>=$G9,K$2<=$H9),IF(AND($I9="YES",K$2=$H9),3,IF($F9=1,4,IF(K$2<=$G9+($H9-$G9+1)*$F9-1,1,2))),"") | L9: =IF(AND(L$2>=$G9,L$2<=$H9),IF(AND($I9="YES",L$2=$H9),3,IF($F9=1,4,IF(L$2<=$G9+($H9-$G9+1)*$F9-1,1,2))),"") | M9: =IF(AND(M$2>=$G9,M$2<=$H9),IF(AND($I9="YES",M$2=$H9),3,IF($F9=1,4,IF(M$2<=$G9+($H9-$G9+1)*$F9-1,1,2))),"") | N9: =IF(AND(N$2>=$G9,N$2<=$H9),IF(AND($I9="YES",N$2=$H9),3,IF($F9=1,4,IF(N$2<=$G9+($H9-$G9+1)*$F9-1,1,2))),"") | O9: =IF(AND(O$2>=$G9,O$2<=$H9),IF(AND($I9="YES",O$2=$H9),3,IF($F9=1,4,IF(O$2<=$G9+($H9-$G9+1)*$F9-1,1,2))),"") | P9: =IF(AND(P$2>=$G9,P$2<=$H9),IF(AND($I9="YES",P$2=$H9),3,IF($F9=1,4,IF(P$2<=$G9+($H9-$G9+1)*$F9-1,1,2))),"") | Q9: =IF(AND(Q$2>=$G9,Q$2<=$H9),IF(AND($I9="YES",Q$2=$H9),3,IF($F9=1,4,IF(Q$2<=$G9+($H9-$G9+1)*$F9-1,1,2))),"") | ... AQ9: =IF(AND(AQ$2>=$G9,AQ$2<=$H9),IF(AND($I9="YES",AQ$2=$H9),3,IF($F9=1,4,IF(AQ$2<=$G9+($H9-$G9+1)*$F9-1,1,2))),"")
A10: =Tracker!A7 | B10: =Tracker!B7 | C10: =Tracker!C7 | D10: =Tracker!J7 | E10: =Tracker!K7 | F10: =Tracker!L7 | G10: =Tracker!E7 | H10: =Tracker!F7 | I10: =Tracker!M7 | J10: =IF(AND(J$2>=$G10,J$2<=$H10),IF(AND($I10="YES",J$2=$H10),3,IF($F10=1,4,IF(J$2<=$G10+($H10-$G10+1)*$F10-1,1,2))),"") | K10: =IF(AND(K$2>=$G10,K$2<=$H10),IF(AND($I10="YES",K$2=$H10),3,IF($F10=1,4,IF(K$2<=$G10+($H10-$G10+1)*$F10-1,1,2))),"") | L10: =IF(AND(L$2>=$G10,L$2<=$H10),IF(AND($I10="YES",L$2=$H10),3,IF($F10=1,4,IF(L$2<=$G10+($H10-$G10+1)*$F10-1,1,2))),"") | M10: =IF(AND(M$2>=$G10,M$2<=$H10),IF(AND($I10="YES",M$2=$H10),3,IF($F10=1,4,IF(M$2<=$G10+($H10-$G10+1)*$F10-1,1,2))),"") | N10: =IF(AND(N$2>=$G10,N$2<=$H10),IF(AND($I10="YES",N$2=$H10),3,IF($F10=1,4,IF(N$2<=$G10+($H10-$G10+1)*$F10-1,1,2))),"") | O10: =IF(AND(O$2>=$G10,O$2<=$H10),IF(AND($I10="YES",O$2=$H10),3,IF($F10=1,4,IF(O$2<=$G10+($H10-$G10+1)*$F10-1,1,2))),"") | P10: =IF(AND(P$2>=$G10,P$2<=$H10),IF(AND($I10="YES",P$2=$H10),3,IF($F10=1,4,IF(P$2<=$G10+($H10-$G10+1)*$F10-1,1,2))),"") | Q10: =IF(AND(Q$2>=$G10,Q$2<=$H10),IF(AND($I10="YES",Q$2=$H10),3,IF($F10=1,4,IF(Q$2<=$G10+($H10-$G10+1)*$F10-1,1,2))),"") | ... AQ10: =IF(AND(AQ$2>=$G10,AQ$2<=$H10),IF(AND($I10="YES",AQ$2=$H10),3,IF($F10=1,4,IF(AQ$2<=$G10+($H10-$G10+1)*$F10-1,1,2))),"")
A11: =Tracker!A8 | B11: =Tracker!B8 | C11: =Tracker!C8 | D11: =Tracker!J8 | E11: =Tracker!K8 | F11: =Tracker!L8 | G11: =Tracker!E8 | H11: =Tracker!F8 | I11: =Tracker!M8 | J11: =IF(AND(J$2>=$G11,J$2<=$H11),IF(AND($I11="YES",J$2=$H11),3,IF($F11=1,4,IF(J$2<=$G11+($H11-$G11+1)*$F11-1,1,2))),"") | K11: =IF(AND(K$2>=$G11,K$2<=$H11),IF(AND($I11="YES",K$2=$H11),3,IF($F11=1,4,IF(K$2<=$G11+($H11-$G11+1)*$F11-1,1,2))),"") | L11: =IF(AND(L$2>=$G11,L$2<=$H11),IF(AND($I11="YES",L$2=$H11),3,IF($F11=1,4,IF(L$2<=$G11+($H11-$G11+1)*$F11-1,1,2))),"") | M11: =IF(AND(M$2>=$G11,M$2<=$H11),IF(AND($I11="YES",M$2=$H11),3,IF($F11=1,4,IF(M$2<=$G11+($H11-$G11+1)*$F11-1,1,2))),"") | N11: =IF(AND(N$2>=$G11,N$2<=$H11),IF(AND($I11="YES",N$2=$H11),3,IF($F11=1,4,IF(N$2<=$G11+($H11-$G11+1)*$F11-1,1,2))),"") | O11: =IF(AND(O$2>=$G11,O$2<=$H11),IF(AND($I11="YES",O$2=$H11),3,IF($F11=1,4,IF(O$2<=$G11+($H11-$G11+1)*$F11-1,1,2))),"") | P11: =IF(AND(P$2>=$G11,P$2<=$H11),IF(AND($I11="YES",P$2=$H11),3,IF($F11=1,4,IF(P$2<=$G11+($H11-$G11+1)*$F11-1,1,2))),"") | Q11: =IF(AND(Q$2>=$G11,Q$2<=$H11),IF(AND($I11="YES",Q$2=$H11),3,IF($F11=1,4,IF(Q$2<=$G11+($H11-$G11+1)*$F11-1,1,2))),"") | ... AQ11: =IF(AND(AQ$2>=$G11,AQ$2<=$H11),IF(AND($I11="YES",AQ$2=$H11),3,IF($F11=1,4,IF(AQ$2<=$G11+($H11-$G11+1)*$F11-1,1,2))),"")
A12: =Tracker!A9 | B12: =Tracker!B9 | C12: =Tracker!C9 | D12: =Tracker!J9 | E12: =Tracker!K9 | F12: =Tracker!L9 | G12: =Tracker!E9 | H12: =Tracker!F9 | I12: =Tracker!M9 | J12: =IF(AND(J$2>=$G12,J$2<=$H12),IF(AND($I12="YES",J$2=$H12),3,IF($F12=1,4,IF(J$2<=$G12+($H12-$G12+1)*$F12-1,1,2))),"") | K12: =IF(AND(K$2>=$G12,K$2<=$H12),IF(AND($I12="YES",K$2=$H12),3,IF($F12=1,4,IF(K$2<=$G12+($H12-$G12+1)*$F12-1,1,2))),"") | L12: =IF(AND(L$2>=$G12,L$2<=$H12),IF(AND($I12="YES",L$2=$H12),3,IF($F12=1,4,IF(L$2<=$G12+($H12-$G12+1)*$F12-1,1,2))),"") | M12: =IF(AND(M$2>=$G12,M$2<=$H12),IF(AND($I12="YES",M$2=$H12),3,IF($F12=1,4,IF(M$2<=$G12+($H12-$G12+1)*$F12-1,1,2))),"") | N12: =IF(AND(N$2>=$G12,N$2<=$H12),IF(AND($I12="YES",N$2=$H12),3,IF($F12=1,4,IF(N$2<=$G12+($H12-$G12+1)*$F12-1,1,2))),"") | O12: =IF(AND(O$2>=$G12,O$2<=$H12),IF(AND($I12="YES",O$2=$H12),3,IF($F12=1,4,IF(O$2<=$G12+($H12-$G12+1)*$F12-1,1,2))),"") | P12: =IF(AND(P$2>=$G12,P$2<=$H12),IF(AND($I12="YES",P$2=$H12),3,IF($F12=1,4,IF(P$2<=$G12+($H12-$G12+1)*$F12-1,1,2))),"") | Q12: =IF(AND(Q$2>=$G12,Q$2<=$H12),IF(AND($I12="YES",Q$2=$H12),3,IF($F12=1,4,IF(Q$2<=$G12+($H12-$G12+1)*$F12-1,1,2))),"") | ... AQ12: =IF(AND(AQ$2>=$G12,AQ$2<=$H12),IF(AND($I12="YES",AQ$2=$H12),3,IF($F12=1,4,IF(AQ$2<=$G12+($H12-$G12+1)*$F12-1,1,2))),"")
A13: =Tracker!A10 | B13: =Tracker!B10 | C13: =Tracker!C10 | D13: =Tracker!J10 | E13: =Tracker!K10 | F13: =Tracker!L10 | G13: =Tracker!E10 | H13: =Tracker!F10 | I13: =Tracker!M10 | J13: =IF(AND(J$2>=$G13,J$2<=$H13),IF(AND($I13="YES",J$2=$H13),3,IF($F13=1,4,IF(J$2<=$G13+($H13-$G13+1)*$F13-1,1,2))),"") | K13: =IF(AND(K$2>=$G13,K$2<=$H13),IF(AND($I13="YES",K$2=$H13),3,IF($F13=1,4,IF(K$2<=$G13+($H13-$G13+1)*$F13-1,1,2))),"") | L13: =IF(AND(L$2>=$G13,L$2<=$H13),IF(AND($I13="YES",L$2=$H13),3,IF($F13=1,4,IF(L$2<=$G13+($H13-$G13+1)*$F13-1,1,2))),"") | M13: =IF(AND(M$2>=$G13,M$2<=$H13),IF(AND($I13="YES",M$2=$H13),3,IF($F13=1,4,IF(M$2<=$G13+($H13-$G13+1)*$F13-1,1,2))),"") | N13: =IF(AND(N$2>=$G13,N$2<=$H13),IF(AND($I13="YES",N$2=$H13),3,IF($F13=1,4,IF(N$2<=$G13+($H13-$G13+1)*$F13-1,1,2))),"") | O13: =IF(AND(O$2>=$G13,O$2<=$H13),IF(AND($I13="YES",O$2=$H13),3,IF($F13=1,4,IF(O$2<=$G13+($H13-$G13+1)*$F13-1,1,2))),"") | P13: =IF(AND(P$2>=$G13,P$2<=$H13),IF(AND($I13="YES",P$2=$H13),3,IF($F13=1,4,IF(P$2<=$G13+($H13-$G13+1)*$F13-1,1,2))),"") | Q13: =IF(AND(Q$2>=$G13,Q$2<=$H13),IF(AND($I13="YES",Q$2=$H13),3,IF($F13=1,4,IF(Q$2<=$G13+($H13-$G13+1)*$F13-1,1,2))),"") | ... AQ13: =IF(AND(AQ$2>=$G13,AQ$2<=$H13),IF(AND($I13="YES",AQ$2=$H13),3,IF($F13=1,4,IF(AQ$2<=$G13+($H13-$G13+1)*$F13-1,1,2))),"")
A14: =Tracker!A11 | B14: =Tracker!B11 | C14: =Tracker!C11 | D14: =Tracker!J11 | E14: =Tracker!K11 | F14: =Tracker!L11 | G14: =Tracker!E11 | H14: =Tracker!F11 | I14: =Tracker!M11 | J14: =IF(AND(J$2>=$G14,J$2<=$H14),IF(AND($I14="YES",J$2=$H14),3,IF($F14=1,4,IF(J$2<=$G14+($H14-$G14+1)*$F14-1,1,2))),"") | K14: =IF(AND(K$2>=$G14,K$2<=$H14),IF(AND($I14="YES",K$2=$H14),3,IF($F14=1,4,IF(K$2<=$G14+($H14-$G14+1)*$F14-1,1,2))),"") | L14: =IF(AND(L$2>=$G14,L$2<=$H14),IF(AND($I14="YES",L$2=$H14),3,IF($F14=1,4,IF(L$2<=$G14+($H14-$G14+1)*$F14-1,1,2))),"") | M14: =IF(AND(M$2>=$G14,M$2<=$H14),IF(AND($I14="YES",M$2=$H14),3,IF($F14=1,4,IF(M$2<=$G14+($H14-$G14+1)*$F14-1,1,2))),"") | N14: =IF(AND(N$2>=$G14,N$2<=$H14),IF(AND($I14="YES",N$2=$H14),3,IF($F14=1,4,IF(N$2<=$G14+($H14-$G14+1)*$F14-1,1,2))),"") | O14: =IF(AND(O$2>=$G14,O$2<=$H14),IF(AND($I14="YES",O$2=$H14),3,IF($F14=1,4,IF(O$2<=$G14+($H14-$G14+1)*$F14-1,1,2))),"") | P14: =IF(AND(P$2>=$G14,P$2<=$H14),IF(AND($I14="YES",P$2=$H14),3,IF($F14=1,4,IF(P$2<=$G14+($H14-$G14+1)*$F14-1,1,2))),"") | Q14: =IF(AND(Q$2>=$G14,Q$2<=$H14),IF(AND($I14="YES",Q$2=$H14),3,IF($F14=1,4,IF(Q$2<=$G14+($H14-$G14+1)*$F14-1,1,2))),"") | ... AQ14: =IF(AND(AQ$2>=$G14,AQ$2<=$H14),IF(AND($I14="YES",AQ$2=$H14),3,IF($F14=1,4,IF(AQ$2<=$G14+($H14-$G14+1)*$F14-1,1,2))),"")
A15: =Tracker!A12 | B15: =Tracker!B12 | C15: =Tracker!C12 | D15: =Tracker!J12 | E15: =Tracker!K12 | F15: =Tracker!L12 | G15: =Tracker!E12 | H15: =Tracker!F12 | I15: =Tracker!M12 | J15: =IF(AND(J$2>=$G15,J$2<=$H15),IF(AND($I15="YES",J$2=$H15),3,IF($F15=1,4,IF(J$2<=$G15+($H15-$G15+1)*$F15-1,1,2))),"") | K15: =IF(AND(K$2>=$G15,K$2<=$H15),IF(AND($I15="YES",K$2=$H15),3,IF($F15=1,4,IF(K$2<=$G15+($H15-$G15+1)*$F15-1,1,2))),"") | L15: =IF(AND(L$2>=$G15,L$2<=$H15),IF(AND($I15="YES",L$2=$H15),3,IF($F15=1,4,IF(L$2<=$G15+($H15-$G15+1)*$F15-1,1,2))),"") | M15: =IF(AND(M$2>=$G15,M$2<=$H15),IF(AND($I15="YES",M$2=$H15),3,IF($F15=1,4,IF(M$2<=$G15+($H15-$G15+1)*$F15-1,1,2))),"") | N15: =IF(AND(N$2>=$G15,N$2<=$H15),IF(AND($I15="YES",N$2=$H15),3,IF($F15=1,4,IF(N$2<=$G15+($H15-$G15+1)*$F15-1,1,2))),"") | O15: =IF(AND(O$2>=$G15,O$2<=$H15),IF(AND($I15="YES",O$2=$H15),3,IF($F15=1,4,IF(O$2<=$G15+($H15-$G15+1)*$F15-1,1,2))),"") | P15: =IF(AND(P$2>=$G15,P$2<=$H15),IF(AND($I15="YES",P$2=$H15),3,IF($F15=1,4,IF(P$2<=$G15+($H15-$G15+1)*$F15-1,1,2))),"") | Q15: =IF(AND(Q$2>=$G15,Q$2<=$H15),IF(AND($I15="YES",Q$2=$H15),3,IF($F15=1,4,IF(Q$2<=$G15+($H15-$G15+1)*$F15-1,1,2))),"") | ... AQ15: =IF(AND(AQ$2>=$G15,AQ$2<=$H15),IF(AND($I15="YES",AQ$2=$H15),3,IF($F15=1,4,IF(AQ$2<=$G15+($H15-$G15+1)*$F15-1,1,2))),"")
A16: =Tracker!A13 | B16: =Tracker!B13 | C16: =Tracker!C13 | D16: =Tracker!J13 | E16: =Tracker!K13 | F16: =Tracker!L13 | G16: =Tracker!E13 | H16: =Tracker!F13 | I16: =Tracker!M13 | J16: =IF(AND(J$2>=$G16,J$2<=$H16),IF(AND($I16="YES",J$2=$H16),3,IF($F16=1,4,IF(J$2<=$G16+($H16-$G16+1)*$F16-1,1,2))),"") | K16: =IF(AND(K$2>=$G16,K$2<=$H16),IF(AND($I16="YES",K$2=$H16),3,IF($F16=1,4,IF(K$2<=$G16+($H16-$G16+1)*$F16-1,1,2))),"") | L16: =IF(AND(L$2>=$G16,L$2<=$H16),IF(AND($I16="YES",L$2=$H16),3,IF($F16=1,4,IF(L$2<=$G16+($H16-$G16+1)*$F16-1,1,2))),"") | M16: =IF(AND(M$2>=$G16,M$2<=$H16),IF(AND($I16="YES",M$2=$H16),3,IF($F16=1,4,IF(M$2<=$G16+($H16-$G16+1)*$F16-1,1,2))),"") | N16: =IF(AND(N$2>=$G16,N$2<=$H16),IF(AND($I16="YES",N$2=$H16),3,IF($F16=1,4,IF(N$2<=$G16+($H16-$G16+1)*$F16-1,1,2))),"") | O16: =IF(AND(O$2>=$G16,O$2<=$H16),IF(AND($I16="YES",O$2=$H16),3,IF($F16=1,4,IF(O$2<=$G16+($H16-$G16+1)*$F16-1,1,2))),"") | P16: =IF(AND(P$2>=$G16,P$2<=$H16),IF(AND($I16="YES",P$2=$H16),3,IF($F16=1,4,IF(P$2<=$G16+($H16-$G16+1)*$F16-1,1,2))),"") | Q16: =IF(AND(Q$2>=$G16,Q$2<=$H16),IF(AND($I16="YES",Q$2=$H16),3,IF($F16=1,4,IF(Q$2<=$G16+($H16-$G16+1)*$F16-1,1,2))),"") | ... AQ16: =IF(AND(AQ$2>=$G16,AQ$2<=$H16),IF(AND($I16="YES",AQ$2=$H16),3,IF($F16=1,4,IF(AQ$2<=$G16+($H16-$G16+1)*$F16-1,1,2))),"")
... A38: =Tracker!A35 | B38: =Tracker!B35 | C38: =Tracker!C35 | D38: =Tracker!J35 | E38: =Tracker!K35 | F38: =Tracker!L35 | G38: =Tracker!E35 | H38: =Tracker!F35 | I38: =Tracker!M35 | J38: =IF(AND(J$2>=$G38,J$2<=$H38),IF(AND($I38="YES",J$2=$H38),3,IF($F38=1,4,IF(J$2<=$G38+($H38-$G38+1)*$F38-1,1,2))),"") | K38: =IF(AND(K$2>=$G38,K$2<=$H38),IF(AND($I38="YES",K$2=$H38),3,IF($F38=1,4,IF(K$2<=$G38+($H38-$G38+1)*$F38-1,1,2))),"") | L38: =IF(AND(L$2>=$G38,L$2<=$H38),IF(AND($I38="YES",L$2=$H38),3,IF($F38=1,4,IF(L$2<=$G38+($H38-$G38+1)*$F38-1,1,2))),"") | M38: =IF(AND(M$2>=$G38,M$2<=$H38),IF(AND($I38="YES",M$2=$H38),3,IF($F38=1,4,IF(M$2<=$G38+($H38-$G38+1)*$F38-1,1,2))),"") | N38: =IF(AND(N$2>=$G38,N$2<=$H38),IF(AND($I38="YES",N$2=$H38),3,IF($F38=1,4,IF(N$2<=$G38+($H38-$G38+1)*$F38-1,1,2))),"") | O38: =IF(AND(O$2>=$G38,O$2<=$H38),IF(AND($I38="YES",O$2=$H38),3,IF($F38=1,4,IF(O$2<=$G38+($H38-$G38+1)*$F38-1,1,2))),"") | P38: =IF(AND(P$2>=$G38,P$2<=$H38),IF(AND($I38="YES",P$2=$H38),3,IF($F38=1,4,IF(P$2<=$G38+($H38-$G38+1)*$F38-1,1,2))),"") | Q38: =IF(AND(Q$2>=$G38,Q$2<=$H38),IF(AND($I38="YES",Q$2=$H38),3,IF($F38=1,4,IF(Q$2<=$G38+($H38-$G38+1)*$F38-1,1,2))),"") | ... AQ38: =IF(AND(AQ$2>=$G38,AQ$2<=$H38),IF(AND($I38="YES",AQ$2=$H38),3,IF($F38=1,4,IF(AQ$2<=$G38+($H38-$G38+1)*$F38-1,1,2))),"")

Sheet Dashboard
A1: Project Dashboard - Governed Multi-Brand Agentic System
A2: Reporting Date (controls Active/Overdue calculations): | B2: 46275 | C2: Project Window: 2026-09-11 to 2026-10-14 (34 days)
A4: KPI | B4: Value | C4: Formula / Notes
A5: Total Tasks | B5: =COUNTA(Tracker!A2:A35) | C5: Count of tasks
A6: Completed Tasks | B6: =COUNTIF(Tracker!K2:K35,"Completed")
A7: In Progress Tasks | B7: =COUNTIF(Tracker!K2:K35,"In Progress")
A8: Not Started Tasks | B8: =COUNTIF(Tracker!K2:K35,"Not Started")
A9: On Hold Tasks | B9: =COUNTIF(Tracker!K2:K35,"On Hold")
A10: Delayed Tasks | B10: =COUNTIF(Tracker!K2:K35,"Delayed")
A11: Overdue (by date) | B11: =COUNTIF(Tracker!R2:R35,"Overdue") | C11: Based on Report Date
A12: Overall Progress (simple avg) | B12: =AVERAGE(Tracker!L2:L35) | C12: Avg of Progress %
A13: Overall Progress (weighted by duration) | B13: =IF(SUM(Tracker!G2:G35)=0,"",SUMPRODUCT(Tracker!G2:G35,Tracker!L2:L35)/SUM(Tracker!G2:G35)) | C13: Weighted
A14: Milestones Completed | B14: =COUNTIF(Milestones!G2:G8,"Yes - Completed")
A15: Milestones Remaining | B15: =7-COUNTIF(Milestones!G2:G8,"Yes - Completed")
A16: Tasks with Conflict | B16: =COUNTIF(Tracker!Q2:Q35,"*⚠*")
A17: Days Remaining | B17: =DATE(2026,10,14)-B2
A19: Tasks by Status | D19: Tasks by Phase / Workstream
A20: Status | B20: Count | D20: Phase | E20: Count | F20: Avg Progress
A21: Not Started | B21: =COUNTIF(Tracker!K2:K35,A21) | D21: Phase 1: Governance, Policy & Canonical State | E21: =COUNTIF(Tracker!B2:B35,D21) | F21: =IF(E21=0,"",AVERAGEIF(Tracker!B2:B35,D21,Tracker!L2:L35))
A22: In Progress | B22: =COUNTIF(Tracker!K2:K35,A22) | D22: Phase 2: Governed Data Plane & Central Storage | E22: =COUNTIF(Tracker!B2:B35,D22) | F22: =IF(E22=0,"",AVERAGEIF(Tracker!B2:B35,D22,Tracker!L2:L35))
A23: Completed | B23: =COUNTIF(Tracker!K2:K35,A23) | D23: Phase 3: Sandbox Isolation & Sub-Agent Readiness | E23: =COUNTIF(Tracker!B2:B35,D23) | F23: =IF(E23=0,"",AVERAGEIF(Tracker!B2:B35,D23,Tracker!L2:L35))
A24: On Hold | B24: =COUNTIF(Tracker!K2:K35,A24) | D24: Phase 4: Domain Intelligence & Asset Synthesis | E24: =COUNTIF(Tracker!B2:B35,D24) | F24: =IF(E24=0,"",AVERAGEIF(Tracker!B2:B35,D24,Tracker!L2:L35))
A25: Delayed | B25: =COUNTIF(Tracker!K2:K35,A25) | D25: Phase 5: Evidence Consolidation & HITL | E25: =COUNTIF(Tracker!B2:B35,D25) | F25: =IF(E25=0,"",AVERAGEIF(Tracker!B2:B35,D25,Tracker!L2:L35))
D26: Phase 6: Outbound Actuation & Go-Live | E26: =COUNTIF(Tracker!B2:B35,D26) | F26: =IF(E26=0,"",AVERAGEIF(Tracker!B2:B35,D26,Tracker!L2:L35))
A27: Upcoming Deadlines (Next 7 days from Report Date) | D27: Phase 7: Telemetry Optimization & Closeout | E27: =COUNTIF(Tracker!B2:B35,D27) | F27: =IF(E27=0,"",AVERAGEIF(Tracker!B2:B35,D27,Tracker!L2:L35))
A28: Task ID | B28: Task Name | C28: End Date | D28: Status | E28: Progress
A29: =IFERROR(FILTER(Tracker!A2:F35,(Tracker!F2:F35>=B2)*(Tracker!F2:F35<=B2+7)),"No deadlines in next 7 days")

Sheet Milestones
A1: Milestone ID | B1: Milestone Name | C1: Milestone Date | D1: Linked Tasks | E1: Status | F1: Avg Progress of Linked Tasks | G1: Completed? | H1: Description
A2: M1 | B2: Governance, Policy & Canonical State Initialization | C2: 46279 | D2: T01, T02, T03, T04 | E2: Complete | F2: =IF(D2="","",AVERAGE(XLOOKUP(TEXTSPLIT(D2,", ",,TRUE),Tracker!$A$2:$A$35,Tracker!$L$2:$L$35))) | G2: =IF(F2=1,"Yes - Completed",IF(F2>0,"Partial","Not Started")) | H2: Governance policies, PAB rules, CTS DAG ready
A3: M2 | B3: Governed Data Plane & Central Storage Integration (Model A) | C3: 46284 | D3: T05, T06, T07, T08, T09, T10 | E3: Complete | F3: =IF(D3="","",AVERAGE(XLOOKUP(TEXTSPLIT(D3,", ",,TRUE),Tracker!$A$2:$A$35,Tracker!$L$2:$L$35))) | G3: =IF(F3=1,"Yes - Completed",IF(F3>0,"Partial","Not Started")) | H3: CDB, CMS, MEM, ART, MCP Gateway, Agentic RAG
A4: M3 | B4: Sandbox Isolation & Specialist Sub-Agent Readiness | C4: 46288 | D4: T11, T12, T13, T14 | E4: Complete | F4: =IF(D4="","",AVERAGE(XLOOKUP(TEXTSPLIT(D4,", ",,TRUE),Tracker!$A$2:$A$35,Tracker!$L$2:$L$35))) | G4: =IF(F4=1,"Yes - Completed",IF(F4>0,"Partial","Not Started")) | H4: agent_sandbox, proxy, audit, sub-agent tools
A5: M4 | B5: Domain Intelligence Ingestion & Asset Synthesis Complete | C5: 46297 | D5: T15, T16, T17, T18, T19, T20, T21 | E5: Complete | F5: =IF(D5="","",AVERAGE(XLOOKUP(TEXTSPLIT(D5,", ",,TRUE),Tracker!$A$2:$A$35,Tracker!$L$2:$L$35))) | G5: =IF(F5=1,"Yes - Completed",IF(F5>0,"Partial","Not Started")) | H5: IE context, W_PROD/VOICE/COMP/STRAT/CREAT/DEV outputs
A6: M5 | B6: HITL Gateway Clearance & Cryptographic Authorization | C6: 46301 | D6: T22, T23, T24 | E6: In Progress | F6: =IF(D6="","",AVERAGE(XLOOKUP(TEXTSPLIT(D6,", ",,TRUE),Tracker!$A$2:$A$35,Tracker!$L$2:$L$35))) | G6: =IF(F6=1,"Yes - Completed",IF(F6>0,"Partial","Not Started")) | H6: Evidence consolidation, action previews, HITL sign-off
A7: M6 | B7: Outbound Actuation, Telemetry & Omnichannel Go-Live | C7: 46305 | D7: T25, T26, T27, T28, T29 | E7: Planned | F7: =IF(D7="","",AVERAGE(XLOOKUP(TEXTSPLIT(D7,", ",,TRUE),Tracker!$A$2:$A$35,Tracker!$L$2:$L$35))) | G7: =IF(F7=1,"Yes - Completed",IF(F7>0,"Partial","Not Started")) | H7: Outbound MCP, Website, Ads, Social, Telemetry hooks
A8: M7 | B8: Closed-Loop Telemetry Optimization & Final Project Closeout | C8: 46309 | D8: T30, T31, T32, T33, T34 | E8: Planned | F8: =IF(D8="","",AVERAGE(XLOOKUP(TEXTSPLIT(D8,", ",,TRUE),Tracker!$A$2:$A$35,Tracker!$L$2:$L$35))) | G8: =IF(F8=1,"Yes - Completed",IF(F8>0,"Partial","Not Started")) | H8: Live ingestion, attribution, memory promotion, audit close

Sheet Resources
A1: Resource Name | B1: Assigned Tasks | C1: Active Tasks | D1: Completed Tasks | E1: Outstanding Tasks | F1: Avg Progress | G1: Workload Flag | H1: Tasks List
A2: Brand Stakeholder / Portfolio Owner | B2: 1 | C2: =COUNTIFS(Tracker!$J$2:$J$35,A2,Tracker!$K$2:$K$35,"In Progress") | D2: =COUNTIFS(Tracker!$J$2:$J$35,A2,Tracker!$K$2:$K$35,"Completed") | E2: =B2-D2 | F2: =IFERROR(AVERAGE(XLOOKUP(TEXTSPLIT(H2,", ",,TRUE),Tracker!$A$2:$A$35,Tracker!$L$2:$L$35)),"") | G2: =IF(B2>3,"⚠ High load",IF(AND(C2>1,E2>2),"⚠ Potential overlap","OK")) | H2: T01
A3: Enterprise Policy Engine | B3: 1 | C3: =COUNTIFS(Tracker!$J$2:$J$35,A3,Tracker!$K$2:$K$35,"In Progress") | D3: =COUNTIFS(Tracker!$J$2:$J$35,A3,Tracker!$K$2:$K$35,"Completed") | E3: =B3-D3 | F3: =IFERROR(AVERAGE(XLOOKUP(TEXTSPLIT(H3,", ",,TRUE),Tracker!$A$2:$A$35,Tracker!$L$2:$L$35)),"") | G3: =IF(B3>3,"⚠ High load",IF(AND(C3>1,E3>2),"⚠ Potential overlap","OK")) | H3: T02
A4: Policy & Authorization Boundary (PAB) | B4: 1 | C4: =COUNTIFS(Tracker!$J$2:$J$35,A4,Tracker!$K$2:$K$35,"In Progress") | D4: =COUNTIFS(Tracker!$J$2:$J$35,A4,Tracker!$K$2:$K$35,"Completed") | E4: =B4-D4 | F4: =IFERROR(AVERAGE(XLOOKUP(TEXTSPLIT(H4,", ",,TRUE),Tracker!$A$2:$A$35,Tracker!$L$2:$L$35)),"") | G4: =IF(B4>3,"⚠ High load",IF(AND(C4>1,E4>2),"⚠ Potential overlap","OK")) | H4: T03
A5: Canonical Task State Machine (CTS) | B5: 1 | C5: =COUNTIFS(Tracker!$J$2:$J$35,A5,Tracker!$K$2:$K$35,"In Progress") | D5: =COUNTIFS(Tracker!$J$2:$J$35,A5,Tracker!$K$2:$K$35,"Completed") | E5: =B5-D5 | F5: =IFERROR(AVERAGE(XLOOKUP(TEXTSPLIT(H5,", ",,TRUE),Tracker!$A$2:$A$35,Tracker!$L$2:$L$35)),"") | G5: =IF(B5>3,"⚠ High load",IF(AND(C5>1,E5>2),"⚠ Potential overlap","OK")) | H5: T04
A6: Central Enterprise Database (CDB) | B6: 1 | C6: =COUNTIFS(Tracker!$J$2:$J$35,A6,Tracker!$K$2:$K$35,"In Progress") | D6: =COUNTIFS(Tracker!$J$2:$J$35,A6,Tracker!$K$2:$K$35,"Completed") | E6: =B6-D6 | F6: =IFERROR(AVERAGE(XLOOKUP(TEXTSPLIT(H6,", ",,TRUE),Tracker!$A$2:$A$35,Tracker!$L$2:$L$35)),"") | G6: =IF(B6>3,"⚠ High load",IF(AND(C6>1,E6>2),"⚠ Potential overlap","OK")) | H6: T05
A7: Headless CMS & Web Store (CMS) | B7: 1 | C7: =COUNTIFS(Tracker!$J$2:$J$35,A7,Tracker!$K$2:$K$35,"In Progress") | D7: =COUNTIFS(Tracker!$J$2:$J$35,A7,Tracker!$K$2:$K$35,"Completed") | E7: =B7-D7 | F7: =IFERROR(AVERAGE(XLOOKUP(TEXTSPLIT(H7,", ",,TRUE),Tracker!$A$2:$A$35,Tracker!$L$2:$L$35)),"") | G7: =IF(B7>3,"⚠ High load",IF(AND(C7>1,E7>2),"⚠ Potential overlap","OK")) | H7: T06
A8: Institutional Memory Store (MEM) | B8: 1 | C8: =COUNTIFS(Tracker!$J$2:$J$35,A8,Tracker!$K$2:$K$35,"In Progress") | D8: =COUNTIFS(Tracker!$J$2:$J$35,A8,Tracker!$K$2:$K$35,"Completed") | E8: =B8-D8 | F8: =IFERROR(AVERAGE(XLOOKUP(TEXTSPLIT(H8,", ",,TRUE),Tracker!$A$2:$A$35,Tracker!$L$2:$L$35)),"") | G8: =IF(B8>3,"⚠ High load",IF(AND(C8>1,E8>2),"⚠ Potential overlap","OK")) | H8: T07
A9: Artifact & Evidence Registry (ART) | B9: 1 | C9: =COUNTIFS(Tracker!$J$2:$J$35,A9,Tracker!$K$2:$K$35,"In Progress") | D9: =COUNTIFS(Tracker!$J$2:$J$35,A9,Tracker!$K$2:$K$35,"Completed") | E9: =B9-D9 | F9: =IFERROR(AVERAGE(XLOOKUP(TEXTSPLIT(H9,", ",,TRUE),Tracker!$A$2:$A$35,Tracker!$L$2:$L$35)),"") | G9: =IF(B9>3,"⚠ High load",IF(AND(C9>1,E9>2),"⚠ Potential overlap","OK")) | H9: T08
A10: Governed MCP Data Boundary | B10: 1 | C10: =COUNTIFS(Tracker!$J$2:$J$35,A10,Tracker!$K$2:$K$35,"In Progress") | D10: =COUNTIFS(Tracker!$J$2:$J$35,A10,Tracker!$K$2:$K$35,"Completed") | E10: =B10-D10 | F10: =IFERROR(AVERAGE(XLOOKUP(TEXTSPLIT(H10,", ",,TRUE),Tracker!$A$2:$A$35,Tracker!$L$2:$L$35)),"") | G10: =IF(B10>3,"⚠ High load",IF(AND(C10>1,E10>2),"⚠ Potential overlap","OK")) | H10: T09
A11: Agentic RAG Controller | B11: 1 | C11: =COUNTIFS(Tracker!$J$2:$J$35,A11,Tracker!$K$2:$K$35,"In Progress") | D11: =COUNTIFS(Tracker!$J$2:$J$35,A11,Tracker!$K$2:$K$35,"Completed") | E11: =B11-D11 | F11: =IFERROR(AVERAGE(XLOOKUP(TEXTSPLIT(H11,", ",,TRUE),Tracker!$A$2:$A$35,Tracker!$L$2:$L$35)),"") | G11: =IF(B11>3,"⚠ High load",IF(AND(C11>1,E11>2),"⚠ Potential overlap","OK")) | H11: T10
A12: Sandbox Controller (agent_sandbox) | B12: 2 | C12: =COUNTIFS(Tracker!$J$2:$J$35,A12,Tracker!$K$2:$K$35,"In Progress") | D12: =COUNTIFS(Tracker!$J$2:$J$35,A12,Tracker!$K$2:$K$35,"Completed") | E12: =B12-D12 | F12: =IFERROR(AVERAGE(XLOOKUP(TEXTSPLIT(H12,", ",,TRUE),Tracker!$A$2:$A$35,Tracker!$L$2:$L$35)),"") | G12: =IF(B12>3,"⚠ High load",IF(AND(C12>1,E12>2),"⚠ Potential overlap","OK")) | H12: T11, T12
A13: Sandbox Controller & W3C PROV Audit | B13: 1 | C13: =COUNTIFS(Tracker!$J$2:$J$35,A13,Tracker!$K$2:$K$35,"In Progress") | D13: =COUNTIFS(Tracker!$J$2:$J$35,A13,Tracker!$K$2:$K$35,"Completed") | E13: =B13-D13 | F13: =IFERROR(AVERAGE(XLOOKUP(TEXTSPLIT(H13,", ",,TRUE),Tracker!$A$2:$A$35,Tracker!$L$2:$L$35)),"") | G13: =IF(B13>3,"⚠ High load",IF(AND(C13>1,E13>2),"⚠ Potential overlap","OK")) | H13: T13
... A32: Intelligence Engine & Brand Owner | B32: 1 | C32: =COUNTIFS(Tracker!$J$2:$J$35,A32,Tracker!$K$2:$K$35,"In Progress") | D32: =COUNTIFS(Tracker!$J$2:$J$35,A32,Tracker!$K$2:$K$35,"Completed") | E32: =B32-D32 | F32: =IFERROR(AVERAGE(XLOOKUP(TEXTSPLIT(H32,", ",,TRUE),Tracker!$A$2:$A$35,Tracker!$L$2:$L$35)),"") | G32: =IF(B32>3,"⚠ High load",IF(AND(C32>1,E32>2),"⚠ Potential overlap","OK")) | H32: T34

Sheet Lists
A1: Status | B1: Priority | C1: DepType | D1: Phase | E1: MilestoneYN | F1: MilestoneID
A2: Not Started | B2: Critical | C2: FS | D2: Phase 1: Governance, Policy & Canonical State | E2: YES | F2: M1
A3: In Progress | B3: High | C3: SS | D3: Phase 2: Governed Data Plane & Central Storage | E3: NO | F3: M2
A4: Completed | B4: Medium | C4: FF | D4: Phase 3: Sandbox Isolation & Sub-Agent Readiness | F4: M3
A5: On Hold | B5: Low | C5: SF | D5: Phase 4: Domain Intelligence & Asset Synthesis | F5: M4
A6: Delayed | D6: Phase 5: Evidence Consolidation & HITL | F6: M5
D7: Phase 6: Outbound Actuation & Go-Live | F7: M6
D8: Phase 7: Telemetry Optimization & Closeout | F8: M7
