Workbook

Sheet Project Tracker
A2: Governed Multi-Brand Agentic System — Master Project Tracker
A3: Fixed Project Window: 2026-09-11 to 2026-10-14 | Access Model: Model A | Execution Boundary: agent_sandbox
A4: Task ID | B4: Phase | C4: Task Name | D4: Description | E4: Start Date | F4: End Date | G4: Duration | H4: Predecessor | I4: Dependency Type | J4: Milestone | K4: Resource / Owner | L4: Priority | M4: Status | N4: Progress % | O4: Schedule Health | P4: Notes
A5: T01 | B5: Phase 1: Governance & Authority | C5: Define enterprise objectives, tenant scopes, and budget boundaries | D5: Establish multi-brand goals, risk boundaries, and financial limits in governance console. | E5: 46276 | F5: 46277 | G5: =IF(OR(E5="",F5=""),0,F5-E5+1) | H5: None | I5: FS | J5: No | K5: Brand Stakeholder / Portfolio Owner | L5: High | M5: Not Started | N5: 0 | O5: =IF(J5="Yes",IF(N5=1,"Completed",IF(TODAY()>F5,"Overdue","Scheduled")),IF(N5=1,"Completed",IF(M5="Delayed","Delayed",IF(M5="On Hold","On Hold",IF(TODAY()>F5,"Overdue",IF(AND(TODAY()>=E5,N5=0),"Behind Schedule","On Track")))))) | P5: Model A baseline; blueprint marked as complete; initialized at 0% for live execution tracking.
A6: T02 | B6: Phase 1: Governance & Authority | C6: Configure machine-readable policy rules, autonomy tiers, and claim limits | D6: Deploy enterprise compliance matrix and statutory guidelines to policy store. | E6: 46276 | F6: 46277 | G6: =IF(OR(E6="",F6=""),0,F6-E6+1) | H6: None | I6: FS | J6: No | K6: Enterprise Policy Engine | L6: High | M6: Not Started | N6: 0 | O6: =IF(J6="Yes",IF(N6=1,"Completed",IF(TODAY()>F6,"Overdue","Scheduled")),IF(N6=1,"Completed",IF(M6="Delayed","Delayed",IF(M6="On Hold","On Hold",IF(TODAY()>F6,"Overdue",IF(AND(TODAY()>=E6,N6=0),"Behind Schedule","On Track")))))) | P6: Defines strict monotonic attenuation constraints for worker tools.
A7: T03 | B7: Phase 1: Governance & Authority | C7: Establish Policy & Authorization Boundary (PAB) evaluation rules | D7: Implement caller token, delegation chain, tenant scope, and attenuation validator. | E7: 46277 | F7: 46279 | G7: =IF(OR(E7="",F7=""),0,F7-E7+1) | H7: T01, T02 | I7: FS | J7: No | K7: Policy & Authorization Boundary (PAB) | L7: High | M7: Not Started | N7: 0 | O7: =IF(J7="Yes",IF(N7=1,"Completed",IF(TODAY()>F7,"Overdue","Scheduled")),IF(N7=1,"Completed",IF(M7="Delayed","Delayed",IF(M7="On Hold","On Hold",IF(TODAY()>F7,"Overdue",IF(AND(TODAY()>=E7,N7=0),"Behind Schedule","On Track")))))) | P7: Same-day handoff from T01/T02 on 2026-09-12 [INFERRED].
A8: T04 | B8: Phase 1: Governance & Authority | C8: Initialize Canonical Task State Machine (CTS) and DAG execution schema | D8: Configure task state transitions, checkpoint barriers, dependency locks, and hold queues. | E8: 46277 | F8: 46279 | G8: =IF(OR(E8="",F8=""),0,F8-E8+1) | H8: T01 | I8: FS | J8: No | K8: Canonical Task State Machine (CTS) | L8: High | M8: Not Started | N8: 0 | O8: =IF(J8="Yes",IF(N8=1,"Completed",IF(TODAY()>F8,"Overdue","Scheduled")),IF(N8=1,"Completed",IF(M8="Delayed","Delayed",IF(M8="On Hold","On Hold",IF(TODAY()>F8,"Overdue",IF(AND(TODAY()>=E8,N8=0),"Behind Schedule","On Track")))))) | P8: Authoritative single-source state ledger for Orchestrator.
A9: M01 | B9: Phase 1: Governance & Authority | C9: Milestone 1: Governance, Policy & Canonical State Initialized | D9: Verification of governance plane, attenuation rules, and state DAG machine. | E9: 46279 | F9: 46279 | G9: =IF(OR(E9="",F9=""),0,F9-E9+1) | H9: T01, T02, T03, T04 | I9: FS | J9: Yes | K9: Intelligence Engine & Owner | L9: High | M9: Not Started | N9: 0 | O9: =IF(J9="Yes",IF(N9=1,"Completed",IF(TODAY()>F9,"Overdue","Scheduled")),IF(N9=1,"Completed",IF(M9="Delayed","Delayed",IF(M9="On Hold","On Hold",IF(TODAY()>F9,"Overdue",IF(AND(TODAY()>=E9,N9=0),"Behind Schedule","On Track")))))) | P9: Explicit checkpoint M1.
A10: T05 | B10: Phase 2: Governed Data Plane | C10: Provision Central Enterprise Database (CDB) relational tables & vector stores | D10: Deploy PostgreSQL, pgvector partitions, tenant schemas, and telemetry tables. | E10: 46279 | F10: 46281 | G10: =IF(OR(E10="",F10=""),0,F10-E10+1) | H10: T04 | I10: FS | J10: No | K10: Central Enterprise Database (CDB) | L10: High | M10: Not Started | N10: 0 | O10: =IF(J10="Yes",IF(N10=1,"Completed",IF(TODAY()>F10,"Overdue","Scheduled")),IF(N10=1,"Completed",IF(M10="Delayed","Delayed",IF(M10="On Hold","On Hold",IF(TODAY()>F10,"Overdue",IF(AND(TODAY()>=E10,N10=0),"Behind Schedule","On Track")))))) | P10: Universal persistence target for all pipeline events.
A11: T06 | B11: Phase 2: Governed Data Plane | C11: Connect Headless CMS content models and staging layout schemas | D11: Establish CMS staged page models, catalog structures, and digital asset repositories. | E11: 46279 | F11: 46281 | G11: =IF(OR(E11="",F11=""),0,F11-E11+1) | H11: T04 | I11: FS | J11: No | K11: Headless CMS & Web Store (CMS) | L11: Medium | M11: Not Started | N11: 0 | O11: =IF(J11="Yes",IF(N11=1,"Completed",IF(TODAY()>F11,"Overdue","Scheduled")),IF(N11=1,"Completed",IF(M11="Delayed","Delayed",IF(M11="On Hold","On Hold",IF(TODAY()>F11,"Overdue",IF(AND(TODAY()>=E11,N11=0),"Behind Schedule","On Track")))))) | P11: System of record for staged storefront layouts and catalog diffs.
A12: T07 | B12: Phase 2: Governed Data Plane | C12: Instantiate Institutional Memory Store (MEM) for brand heuristics & rules | D12: Configure long-term key-value and vector feature store for brand persona memory. | E12: 46279 | F12: 46281 | G12: =IF(OR(E12="",F12=""),0,F12-E12+1) | H12: T04 | I12: FS | J12: No | K12: Institutional Memory Store (MEM) | L12: Medium | M12: Not Started | N12: 0 | O12: =IF(J12="Yes",IF(N12=1,"Completed",IF(TODAY()>F12,"Overdue","Scheduled")),IF(N12=1,"Completed",IF(M12="Delayed","Delayed",IF(M12="On Hold","On Hold",IF(TODAY()>F12,"Overdue",IF(AND(TODAY()>=E12,N12=0),"Behind Schedule","On Track")))))) | P12: Durable store for promoted optimization heuristics.
A13: T08 | B13: Phase 2: Governed Data Plane | C13: Configure Artifact & Evidence Registry (ART) for UUID/hash deliverables | D13: Set up content-addressable storage for code patches, copy packs, and proof dossiers. | E13: 46281 | F13: 46283 | G13: =IF(OR(E13="",F13=""),0,F13-E13+1) | H13: T05 | I13: FS | J13: No | K13: Artifact & Evidence Registry (ART) | L13: Medium | M13: Not Started | N13: 0 | O13: =IF(J13="Yes",IF(N13=1,"Completed",IF(TODAY()>F13,"Overdue","Scheduled")),IF(N13=1,"Completed",IF(M13="Delayed","Delayed",IF(M13="On Hold","On Hold",IF(TODAY()>F13,"Overdue",IF(AND(TODAY()>=E13,N13=0),"Behind Schedule","On Track")))))) | P13: SHA-256 and UUID delivery addressing.
A14: T09 | B14: Phase 2: Governed Data Plane | C14: Deploy Governed MCP Data Boundary CRUD gateways & connection pools | D14: Expose standardized read/write capability facades to storage planes under strict schema validation. | E14: 46281 | F14: 46283 | G14: =IF(OR(E14="",F14=""),0,F14-E14+1) | H14: T05, T06, T07 | I14: FS | J14: No | K14: Governed MCP Data Boundary | L14: High | M14: Not Started | N14: 0 | O14: =IF(J14="Yes",IF(N14=1,"Completed",IF(TODAY()>F14,"Overdue","Scheduled")),IF(N14=1,"Completed",IF(M14="Delayed","Delayed",IF(M14="On Hold","On Hold",IF(TODAY()>F14,"Overdue",IF(AND(TODAY()>=E14,N14=0),"Behind Schedule","On Track")))))) | P14: Exclusively accessible by Agentic RAG Controller.
A15: T10 | B15: Phase 2: Governed Data Plane | C15: Configure Agentic RAG Controller with tenant isolation & freshness gates | D15: Deploy hybrid semantic search, BM25 ranking, provenance tagging, and freshness verifiers. | E15: 46283 | F15: 46284 | G15: =IF(OR(E15="",F15=""),0,F15-E15+1) | H15: T03, T09 | I15: FS | J15: No | K15: Agentic RAG Controller | L15: High | M15: Not Started | N15: 0 | O15: =IF(J15="Yes",IF(N15=1,"Completed",IF(TODAY()>F15,"Overdue","Scheduled")),IF(N15=1,"Completed",IF(M15="Delayed","Delayed",IF(M15="On Hold","On Hold",IF(TODAY()>F15,"Overdue",IF(AND(TODAY()>=E15,N15=0),"Behind Schedule","On Track")))))) | P15: Model A mandate: Exclusively queried by Intelligence Engine.
A16: M02 | B16: Phase 2: Governed Data Plane | C16: Milestone 2: Governed Data Plane & Central Storage Integration (Model A) | D16: Data boundary gateways, RAG controller, and enterprise stores validated. | E16: 46284 | F16: 46284 | G16: =IF(OR(E16="",F16=""),0,F16-E16+1) | H16: T05, T06, T07, T08, T09, T10 | I16: FS | J16: Yes | K16: Intelligence Engine & Agentic RAG | L16: High | M16: Not Started | N16: 0 | O16: =IF(J16="Yes",IF(N16=1,"Completed",IF(TODAY()>F16,"Overdue","Scheduled")),IF(N16=1,"Completed",IF(M16="Delayed","Delayed",IF(M16="On Hold","On Hold",IF(TODAY()>F16,"Overdue",IF(AND(TODAY()>=E16,N16=0),"Behind Schedule","On Track")))))) | P16: Explicit checkpoint M2.
... A45: M07 | B45: Phase 7: Closed-Loop Telemetry | C45: Milestone 7: Closed-Loop Telemetry Optimization & Final Project Closeout | D45: Attribution optimized, memory updated, ledger sealed, and system accepted. | E45: 46309 | F45: 46309 | G45: =IF(OR(E45="",F45=""),0,F45-E45+1) | H45: T30, T31, T32, T33, T34 | I45: FS | J45: Yes | K45: Brand Stakeholder & IE | L45: High | M45: Not Started | N45: 0 | O45: =IF(J45="Yes",IF(N45=1,"Completed",IF(TODAY()>F45,"Overdue","Scheduled")),IF(N45=1,"Completed",IF(M45="Delayed","Delayed",IF(M45="On Hold","On Hold",IF(TODAY()>F45,"Overdue",IF(AND(TODAY()>=E45,N45=0),"Behind Schedule","On Track")))))) | P45: Explicit checkpoint M7 (Project Complete).

Sheet Gantt
A2: Governed Multi-Brand Agentic System — Automated Timeline Visualization
A3: Schedule Duration: 2026-09-11 to 2026-10-14 (34 Calendar Days) | Legend: ■ Done (Blue) | ░ Remaining (Light Blue) | ◆ Milestone (Gold) | G3: September 2026 (Launch & Foundation Plane) | AA3: October 2026 (Actuation & Closed-Loop Telemetry)
A4: Task ID | B4: Task Name | C4: Start Date | D4: End Date | E4: Progress % | F4: Milestone | G4: 11 | H4: 12 | I4: 13 | J4: 14 | K4: 15 | L4: 16 | M4: 17 | N4: 18 | O4: 19 | P4: 20 | Q4: 21 | R4: 22 | S4: 23 | T4: 24 | U4: 25 | V4: 26 | W4: 27 | X4: 28 | Y4: 29 | Z4: 30 | AA4: 1 | AB4: 2 | AC4: 3 | AD4: 4 | AE4: 5 | AF4: 6 | AG4: 7 | AH4: 8 | AI4: 9 | AJ4: 10 | AK4: 11 | AL4: 12 | AM4: 13 | AN4: 14
G5: FR | H5: SA | I5: SU | J5: MO | K5: TU | L5: WE | M5: TH | N5: FR | O5: SA | P5: SU | Q5: MO | R5: TU | S5: WE | T5: TH | U5: FR | V5: SA | W5: SU | X5: MO | Y5: TU | Z5: WE | AA5: TH | AB5: FR | AC5: SA | AD5: SU | AE5: MO | AF5: TU | AG5: WE | AH5: TH | AI5: FR | AJ5: SA | AK5: SU | AL5: MO | AM5: TU | AN5: WE
A6: ='Project Tracker'!A5 | B6: ='Project Tracker'!C5 | C6: ='Project Tracker'!E5 | D6: ='Project Tracker'!F5 | E6: ='Project Tracker'!N5 | F6: ='Project Tracker'!J5 | G6: =IF($F6="Yes",IF(DATE(2026,9,11)=$C6,"◆",""),IF(AND(DATE(2026,9,11)>=$C6,DATE(2026,9,11)<=$D6),IF(DATE(2026,9,11)<$C6+ROUND($E6*($D6-$C6+1),0),"█","░"),"")) | H6: =IF($F6="Yes",IF(DATE(2026,9,12)=$C6,"◆",""),IF(AND(DATE(2026,9,12)>=$C6,DATE(2026,9,12)<=$D6),IF(DATE(2026,9,12)<$C6+ROUND($E6*($D6-$C6+1),0),"█","░"),"")) | I6: =IF($F6="Yes",IF(DATE(2026,9,13)=$C6,"◆",""),IF(AND(DATE(2026,9,13)>=$C6,DATE(2026,9,13)<=$D6),IF(DATE(2026,9,13)<$C6+ROUND($E6*($D6-$C6+1),0),"█","░"),"")) | J6: =IF($F6="Yes",IF(DATE(2026,9,14)=$C6,"◆",""),IF(AND(DATE(2026,9,14)>=$C6,DATE(2026,9,14)<=$D6),IF(DATE(2026,9,14)<$C6+ROUND($E6*($D6-$C6+1),0),"█","░"),"")) | K6: =IF($F6="Yes",IF(DATE(2026,9,15)=$C6,"◆",""),IF(AND(DATE(2026,9,15)>=$C6,DATE(2026,9,15)<=$D6),IF(DATE(2026,9,15)<$C6+ROUND($E6*($D6-$C6+1),0),"█","░"),"")) | L6: =IF($F6="Yes",IF(DATE(2026,9,16)=$C6,"◆",""),IF(AND(DATE(2026,9,16)>=$C6,DATE(2026,9,16)<=$D6),IF(DATE(2026,9,16)<$C6+ROUND($E6*($D6-$C6+1),0),"█","░"),"")) | M6: =IF($F6="Yes",IF(DATE(2026,9,17)=$C6,"◆",""),IF(AND(DATE(2026,9,17)>=$C6,DATE(2026,9,17)<=$D6),IF(DATE(2026,9,17)<$C6+ROUND($E6*($D6-$C6+1),0),"█","░"),"")) | N6: =IF($F6="Yes",IF(DATE(2026,9,18)=$C6,"◆",""),IF(AND(DATE(2026,9,18)>=$C6,DATE(2026,9,18)<=$D6),IF(DATE(2026,9,18)<$C6+ROUND($E6*($D6-$C6+1),0),"█","░"),"")) | O6: =IF($F6="Yes",IF(DATE(2026,9,19)=$C6,"◆",""),IF(AND(DATE(2026,9,19)>=$C6,DATE(2026,9,19)<=$D6),IF(DATE(2026,9,19)<$C6+ROUND($E6*($D6-$C6+1),0),"█","░"),"")) | P6: =IF($F6="Yes",IF(DATE(2026,9,20)=$C6,"◆",""),IF(AND(DATE(2026,9,20)>=$C6,DATE(2026,9,20)<=$D6),IF(DATE(2026,9,20)<$C6+ROUND($E6*($D6-$C6+1),0),"█","░"),"")) | Q6: =IF($F6="Yes",IF(DATE(2026,9,21)=$C6,"◆",""),IF(AND(DATE(2026,9,21)>=$C6,DATE(2026,9,21)<=$D6),IF(DATE(2026,9,21)<$C6+ROUND($E6*($D6-$C6+1),0),"█","░"),"")) | R6: =IF($F6="Yes",IF(DATE(2026,9,22)=$C6,"◆",""),IF(AND(DATE(2026,9,22)>=$C6,DATE(2026,9,22)<=$D6),IF(DATE(2026,9,22)<$C6+ROUND($E6*($D6-$C6+1),0),"█","░"),"")) | S6: =IF($F6="Yes",IF(DATE(2026,9,23)=$C6,"◆",""),IF(AND(DATE(2026,9,23)>=$C6,DATE(2026,9,23)<=$D6),IF(DATE(2026,9,23)<$C6+ROUND($E6*($D6-$C6+1),0),"█","░"),"")) | T6: =IF($F6="Yes",IF(DATE(2026,9,24)=$C6,"◆",""),IF(AND(DATE(2026,9,24)>=$C6,DATE(2026,9,24)<=$D6),IF(DATE(2026,9,24)<$C6+ROUND($E6*($D6-$C6+1),0),"█","░"),"")) | U6: =IF($F6="Yes",IF(DATE(2026,9,25)=$C6,"◆",""),IF(AND(DATE(2026,9,25)>=$C6,DATE(2026,9,25)<=$D6),IF(DATE(2026,9,25)<$C6+ROUND($E6*($D6-$C6+1),0),"█","░"),"")) | V6: =IF($F6="Yes",IF(DATE(2026,9,26)=$C6,"◆",""),IF(AND(DATE(2026,9,26)>=$C6,DATE(2026,9,26)<=$D6),IF(DATE(2026,9,26)<$C6+ROUND($E6*($D6-$C6+1),0),"█","░"),"")) | W6: =IF($F6="Yes",IF(DATE(2026,9,27)=$C6,"◆",""),IF(AND(DATE(2026,9,27)>=$C6,DATE(2026,9,27)<=$D6),IF(DATE(2026,9,27)<$C6+ROUND($E6*($D6-$C6+1),0),"█","░"),"")) | X6: =IF($F6="Yes",IF(DATE(2026,9,28)=$C6,"◆",""),IF(AND(DATE(2026,9,28)>=$C6,DATE(2026,9,28)<=$D6),IF(DATE(2026,9,28)<$C6+ROUND($E6*($D6-$C6+1),0),"█","░"),"")) | Y6: =IF($F6="Yes",IF(DATE(2026,9,29)=$C6,"◆",""),IF(AND(DATE(2026,9,29)>=$C6,DATE(2026,9,29)<=$D6),IF(DATE(2026,9,29)<$C6+ROUND($E6*($D6-$C6+1),0),"█","░"),"")) | Z6: =IF($F6="Yes",IF(DATE(2026,9,30)=$C6,"◆",""),IF(AND(DATE(2026,9,30)>=$C6,DATE(2026,9,30)<=$D6),IF(DATE(2026,9,30)<$C6+ROUND($E6*($D6-$C6+1),0),"█","░"),"")) | AA6: =IF($F6="Yes",IF(DATE(2026,10,1)=$C6,"◆",""),IF(AND(DATE(2026,10,1)>=$C6,DATE(2026,10,1)<=$D6),IF(DATE(2026,10,1)<$C6+ROUND($E6*($D6-$C6+1),0),"█","░"),"")) | AB6: =IF($F6="Yes",IF(DATE(2026,10,2)=$C6,"◆",""),IF(AND(DATE(2026,10,2)>=$C6,DATE(2026,10,2)<=$D6),IF(DATE(2026,10,2)<$C6+ROUND($E6*($D6-$C6+1),0),"█","░"),"")) | AC6: =IF($F6="Yes",IF(DATE(2026,10,3)=$C6,"◆",""),IF(AND(DATE(2026,10,3)>=$C6,DATE(2026,10,3)<=$D6),IF(DATE(2026,10,3)<$C6+ROUND($E6*($D6-$C6+1),0),"█","░"),"")) | AD6: =IF($F6="Yes",IF(DATE(2026,10,4)=$C6,"◆",""),IF(AND(DATE(2026,10,4)>=$C6,DATE(2026,10,4)<=$D6),IF(DATE(2026,10,4)<$C6+ROUND($E6*($D6-$C6+1),0),"█","░"),"")) | AE6: =IF($F6="Yes",IF(DATE(2026,10,5)=$C6,"◆",""),IF(AND(DATE(2026,10,5)>=$C6,DATE(2026,10,5)<=$D6),IF(DATE(2026,10,5)<$C6+ROUND($E6*($D6-$C6+1),0),"█","░"),"")) | AF6: =IF($F6="Yes",IF(DATE(2026,10,6)=$C6,"◆",""),IF(AND(DATE(2026,10,6)>=$C6,DATE(2026,10,6)<=$D6),IF(DATE(2026,10,6)<$C6+ROUND($E6*($D6-$C6+1),0),"█","░"),"")) | AG6: =IF($F6="Yes",IF(DATE(2026,10,7)=$C6,"◆",""),IF(AND(DATE(2026,10,7)>=$C6,DATE(2026,10,7)<=$D6),IF(DATE(2026,10,7)<$C6+ROUND($E6*($D6-$C6+1),0),"█","░"),"")) | AH6: =IF($F6="Yes",IF(DATE(2026,10,8)=$C6,"◆",""),IF(AND(DATE(2026,10,8)>=$C6,DATE(2026,10,8)<=$D6),IF(DATE(2026,10,8)<$C6+ROUND($E6*($D6-$C6+1),0),"█","░"),"")) | AI6: =IF($F6="Yes",IF(DATE(2026,10,9)=$C6,"◆",""),IF(AND(DATE(2026,10,9)>=$C6,DATE(2026,10,9)<=$D6),IF(DATE(2026,10,9)<$C6+ROUND($E6*($D6-$C6+1),0),"█","░"),"")) | AJ6: =IF($F6="Yes",IF(DATE(2026,10,10)=$C6,"◆",""),IF(AND(DATE(2026,10,10)>=$C6,DATE(2026,10,10)<=$D6),IF(DATE(2026,10,10)<$C6+ROUND($E6*($D6-$C6+1),0),"█","░"),"")) | AK6: =IF($F6="Yes",IF(DATE(2026,10,11)=$C6,"◆",""),IF(AND(DATE(2026,10,11)>=$C6,DATE(2026,10,11)<=$D6),IF(DATE(2026,10,11)<$C6+ROUND($E6*($D6-$C6+1),0),"█","░"),"")) | AL6: =IF($F6="Yes",IF(DATE(2026,10,12)=$C6,"◆",""),IF(AND(DATE(2026,10,12)>=$C6,DATE(2026,10,12)<=$D6),IF(DATE(2026,10,12)<$C6+ROUND($E6*($D6-$C6+1),0),"█","░"),"")) | AM6: =IF($F6="Yes",IF(DATE(2026,10,13)=$C6,"◆",""),IF(AND(DATE(2026,10,13)>=$C6,DATE(2026,10,13)<=$D6),IF(DATE(2026,10,13)<$C6+ROUND($E6*($D6-$C6+1),0),"█","░"),"")) | AN6: =IF($F6="Yes",IF(DATE(2026,10,14)=$C6,"◆",""),IF(AND(DATE(2026,10,14)>=$C6,DATE(2026,10,14)<=$D6),IF(DATE(2026,10,14)<$C6+ROUND($E6*($D6-$C6+1),0),"█","░"),""))
A7: ='Project Tracker'!A6 | B7: ='Project Tracker'!C6 | C7: ='Project Tracker'!E6 | D7: ='Project Tracker'!F6 | E7: ='Project Tracker'!N6 | F7: ='Project Tracker'!J6 | G7: =IF($F7="Yes",IF(DATE(2026,9,11)=$C7,"◆",""),IF(AND(DATE(2026,9,11)>=$C7,DATE(2026,9,11)<=$D7),IF(DATE(2026,9,11)<$C7+ROUND($E7*($D7-$C7+1),0),"█","░"),"")) | H7: =IF($F7="Yes",IF(DATE(2026,9,12)=$C7,"◆",""),IF(AND(DATE(2026,9,12)>=$C7,DATE(2026,9,12)<=$D7),IF(DATE(2026,9,12)<$C7+ROUND($E7*($D7-$C7+1),0),"█","░"),"")) | I7: =IF($F7="Yes",IF(DATE(2026,9,13)=$C7,"◆",""),IF(AND(DATE(2026,9,13)>=$C7,DATE(2026,9,13)<=$D7),IF(DATE(2026,9,13)<$C7+ROUND($E7*($D7-$C7+1),0),"█","░"),"")) | J7: =IF($F7="Yes",IF(DATE(2026,9,14)=$C7,"◆",""),IF(AND(DATE(2026,9,14)>=$C7,DATE(2026,9,14)<=$D7),IF(DATE(2026,9,14)<$C7+ROUND($E7*($D7-$C7+1),0),"█","░"),"")) | K7: =IF($F7="Yes",IF(DATE(2026,9,15)=$C7,"◆",""),IF(AND(DATE(2026,9,15)>=$C7,DATE(2026,9,15)<=$D7),IF(DATE(2026,9,15)<$C7+ROUND($E7*($D7-$C7+1),0),"█","░"),"")) | L7: =IF($F7="Yes",IF(DATE(2026,9,16)=$C7,"◆",""),IF(AND(DATE(2026,9,16)>=$C7,DATE(2026,9,16)<=$D7),IF(DATE(2026,9,16)<$C7+ROUND($E7*($D7-$C7+1),0),"█","░"),"")) | M7: =IF($F7="Yes",IF(DATE(2026,9,17)=$C7,"◆",""),IF(AND(DATE(2026,9,17)>=$C7,DATE(2026,9,17)<=$D7),IF(DATE(2026,9,17)<$C7+ROUND($E7*($D7-$C7+1),0),"█","░"),"")) | N7: =IF($F7="Yes",IF(DATE(2026,9,18)=$C7,"◆",""),IF(AND(DATE(2026,9,18)>=$C7,DATE(2026,9,18)<=$D7),IF(DATE(2026,9,18)<$C7+ROUND($E7*($D7-$C7+1),0),"█","░"),"")) | O7: =IF($F7="Yes",IF(DATE(2026,9,19)=$C7,"◆",""),IF(AND(DATE(2026,9,19)>=$C7,DATE(2026,9,19)<=$D7),IF(DATE(2026,9,19)<$C7+ROUND($E7*($D7-$C7+1),0),"█","░"),"")) | P7: =IF($F7="Yes",IF(DATE(2026,9,20)=$C7,"◆",""),IF(AND(DATE(2026,9,20)>=$C7,DATE(2026,9,20)<=$D7),IF(DATE(2026,9,20)<$C7+ROUND($E7*($D7-$C7+1),0),"█","░"),"")) | Q7: =IF($F7="Yes",IF(DATE(2026,9,21)=$C7,"◆",""),IF(AND(DATE(2026,9,21)>=$C7,DATE(2026,9,21)<=$D7),IF(DATE(2026,9,21)<$C7+ROUND($E7*($D7-$C7+1),0),"█","░"),"")) | R7: =IF($F7="Yes",IF(DATE(2026,9,22)=$C7,"◆",""),IF(AND(DATE(2026,9,22)>=$C7,DATE(2026,9,22)<=$D7),IF(DATE(2026,9,22)<$C7+ROUND($E7*($D7-$C7+1),0),"█","░"),"")) | S7: =IF($F7="Yes",IF(DATE(2026,9,23)=$C7,"◆",""),IF(AND(DATE(2026,9,23)>=$C7,DATE(2026,9,23)<=$D7),IF(DATE(2026,9,23)<$C7+ROUND($E7*($D7-$C7+1),0),"█","░"),"")) | T7: =IF($F7="Yes",IF(DATE(2026,9,24)=$C7,"◆",""),IF(AND(DATE(2026,9,24)>=$C7,DATE(2026,9,24)<=$D7),IF(DATE(2026,9,24)<$C7+ROUND($E7*($D7-$C7+1),0),"█","░"),"")) | U7: =IF($F7="Yes",IF(DATE(2026,9,25)=$C7,"◆",""),IF(AND(DATE(2026,9,25)>=$C7,DATE(2026,9,25)<=$D7),IF(DATE(2026,9,25)<$C7+ROUND($E7*($D7-$C7+1),0),"█","░"),"")) | V7: =IF($F7="Yes",IF(DATE(2026,9,26)=$C7,"◆",""),IF(AND(DATE(2026,9,26)>=$C7,DATE(2026,9,26)<=$D7),IF(DATE(2026,9,26)<$C7+ROUND($E7*($D7-$C7+1),0),"█","░"),"")) | W7: =IF($F7="Yes",IF(DATE(2026,9,27)=$C7,"◆",""),IF(AND(DATE(2026,9,27)>=$C7,DATE(2026,9,27)<=$D7),IF(DATE(2026,9,27)<$C7+ROUND($E7*($D7-$C7+1),0),"█","░"),"")) | X7: =IF($F7="Yes",IF(DATE(2026,9,28)=$C7,"◆",""),IF(AND(DATE(2026,9,28)>=$C7,DATE(2026,9,28)<=$D7),IF(DATE(2026,9,28)<$C7+ROUND($E7*($D7-$C7+1),0),"█","░"),"")) | Y7: =IF($F7="Yes",IF(DATE(2026,9,29)=$C7,"◆",""),IF(AND(DATE(2026,9,29)>=$C7,DATE(2026,9,29)<=$D7),IF(DATE(2026,9,29)<$C7+ROUND($E7*($D7-$C7+1),0),"█","░"),"")) | Z7: =IF($F7="Yes",IF(DATE(2026,9,30)=$C7,"◆",""),IF(AND(DATE(2026,9,30)>=$C7,DATE(2026,9,30)<=$D7),IF(DATE(2026,9,30)<$C7+ROUND($E7*($D7-$C7+1),0),"█","░"),"")) | AA7: =IF($F7="Yes",IF(DATE(2026,10,1)=$C7,"◆",""),IF(AND(DATE(2026,10,1)>=$C7,DATE(2026,10,1)<=$D7),IF(DATE(2026,10,1)<$C7+ROUND($E7*($D7-$C7+1),0),"█","░"),"")) | AB7: =IF($F7="Yes",IF(DATE(2026,10,2)=$C7,"◆",""),IF(AND(DATE(2026,10,2)>=$C7,DATE(2026,10,2)<=$D7),IF(DATE(2026,10,2)<$C7+ROUND($E7*($D7-$C7+1),0),"█","░"),"")) | AC7: =IF($F7="Yes",IF(DATE(2026,10,3)=$C7,"◆",""),IF(AND(DATE(2026,10,3)>=$C7,DATE(2026,10,3)<=$D7),IF(DATE(2026,10,3)<$C7+ROUND($E7*($D7-$C7+1),0),"█","░"),"")) | AD7: =IF($F7="Yes",IF(DATE(2026,10,4)=$C7,"◆",""),IF(AND(DATE(2026,10,4)>=$C7,DATE(2026,10,4)<=$D7),IF(DATE(2026,10,4)<$C7+ROUND($E7*($D7-$C7+1),0),"█","░"),"")) | AE7: =IF($F7="Yes",IF(DATE(2026,10,5)=$C7,"◆",""),IF(AND(DATE(2026,10,5)>=$C7,DATE(2026,10,5)<=$D7),IF(DATE(2026,10,5)<$C7+ROUND($E7*($D7-$C7+1),0),"█","░"),"")) | AF7: =IF($F7="Yes",IF(DATE(2026,10,6)=$C7,"◆",""),IF(AND(DATE(2026,10,6)>=$C7,DATE(2026,10,6)<=$D7),IF(DATE(2026,10,6)<$C7+ROUND($E7*($D7-$C7+1),0),"█","░"),"")) | AG7: =IF($F7="Yes",IF(DATE(2026,10,7)=$C7,"◆",""),IF(AND(DATE(2026,10,7)>=$C7,DATE(2026,10,7)<=$D7),IF(DATE(2026,10,7)<$C7+ROUND($E7*($D7-$C7+1),0),"█","░"),"")) | AH7: =IF($F7="Yes",IF(DATE(2026,10,8)=$C7,"◆",""),IF(AND(DATE(2026,10,8)>=$C7,DATE(2026,10,8)<=$D7),IF(DATE(2026,10,8)<$C7+ROUND($E7*($D7-$C7+1),0),"█","░"),"")) | AI7: =IF($F7="Yes",IF(DATE(2026,10,9)=$C7,"◆",""),IF(AND(DATE(2026,10,9)>=$C7,DATE(2026,10,9)<=$D7),IF(DATE(2026,10,9)<$C7+ROUND($E7*($D7-$C7+1),0),"█","░"),"")) | AJ7: =IF($F7="Yes",IF(DATE(2026,10,10)=$C7,"◆",""),IF(AND(DATE(2026,10,10)>=$C7,DATE(2026,10,10)<=$D7),IF(DATE(2026,10,10)<$C7+ROUND($E7*($D7-$C7+1),0),"█","░"),"")) | AK7: =IF($F7="Yes",IF(DATE(2026,10,11)=$C7,"◆",""),IF(AND(DATE(2026,10,11)>=$C7,DATE(2026,10,11)<=$D7),IF(DATE(2026,10,11)<$C7+ROUND($E7*($D7-$C7+1),0),"█","░"),"")) | AL7: =IF($F7="Yes",IF(DATE(2026,10,12)=$C7,"◆",""),IF(AND(DATE(2026,10,12)>=$C7,DATE(2026,10,12)<=$D7),IF(DATE(2026,10,12)<$C7+ROUND($E7*($D7-$C7+1),0),"█","░"),"")) | AM7: =IF($F7="Yes",IF(DATE(2026,10,13)=$C7,"◆",""),IF(AND(DATE(2026,10,13)>=$C7,DATE(2026,10,13)<=$D7),IF(DATE(2026,10,13)<$C7+ROUND($E7*($D7-$C7+1),0),"█","░"),"")) | AN7: =IF($F7="Yes",IF(DATE(2026,10,14)=$C7,"◆",""),IF(AND(DATE(2026,10,14)>=$C7,DATE(2026,10,14)<=$D7),IF(DATE(2026,10,14)<$C7+ROUND($E7*($D7-$C7+1),0),"█","░"),""))
A8: ='Project Tracker'!A7 | B8: ='Project Tracker'!C7 | C8: ='Project Tracker'!E7 | D8: ='Project Tracker'!F7 | E8: ='Project Tracker'!N7 | F8: ='Project Tracker'!J7 | G8: =IF($F8="Yes",IF(DATE(2026,9,11)=$C8,"◆",""),IF(AND(DATE(2026,9,11)>=$C8,DATE(2026,9,11)<=$D8),IF(DATE(2026,9,11)<$C8+ROUND($E8*($D8-$C8+1),0),"█","░"),"")) | H8: =IF($F8="Yes",IF(DATE(2026,9,12)=$C8,"◆",""),IF(AND(DATE(2026,9,12)>=$C8,DATE(2026,9,12)<=$D8),IF(DATE(2026,9,12)<$C8+ROUND($E8*($D8-$C8+1),0),"█","░"),"")) | I8: =IF($F8="Yes",IF(DATE(2026,9,13)=$C8,"◆",""),IF(AND(DATE(2026,9,13)>=$C8,DATE(2026,9,13)<=$D8),IF(DATE(2026,9,13)<$C8+ROUND($E8*($D8-$C8+1),0),"█","░"),"")) | J8: =IF($F8="Yes",IF(DATE(2026,9,14)=$C8,"◆",""),IF(AND(DATE(2026,9,14)>=$C8,DATE(2026,9,14)<=$D8),IF(DATE(2026,9,14)<$C8+ROUND($E8*($D8-$C8+1),0),"█","░"),"")) | K8: =IF($F8="Yes",IF(DATE(2026,9,15)=$C8,"◆",""),IF(AND(DATE(2026,9,15)>=$C8,DATE(2026,9,15)<=$D8),IF(DATE(2026,9,15)<$C8+ROUND($E8*($D8-$C8+1),0),"█","░"),"")) | L8: =IF($F8="Yes",IF(DATE(2026,9,16)=$C8,"◆",""),IF(AND(DATE(2026,9,16)>=$C8,DATE(2026,9,16)<=$D8),IF(DATE(2026,9,16)<$C8+ROUND($E8*($D8-$C8+1),0),"█","░"),"")) | M8: =IF($F8="Yes",IF(DATE(2026,9,17)=$C8,"◆",""),IF(AND(DATE(2026,9,17)>=$C8,DATE(2026,9,17)<=$D8),IF(DATE(2026,9,17)<$C8+ROUND($E8*($D8-$C8+1),0),"█","░"),"")) | N8: =IF($F8="Yes",IF(DATE(2026,9,18)=$C8,"◆",""),IF(AND(DATE(2026,9,18)>=$C8,DATE(2026,9,18)<=$D8),IF(DATE(2026,9,18)<$C8+ROUND($E8*($D8-$C8+1),0),"█","░"),"")) | O8: =IF($F8="Yes",IF(DATE(2026,9,19)=$C8,"◆",""),IF(AND(DATE(2026,9,19)>=$C8,DATE(2026,9,19)<=$D8),IF(DATE(2026,9,19)<$C8+ROUND($E8*($D8-$C8+1),0),"█","░"),"")) | P8: =IF($F8="Yes",IF(DATE(2026,9,20)=$C8,"◆",""),IF(AND(DATE(2026,9,20)>=$C8,DATE(2026,9,20)<=$D8),IF(DATE(2026,9,20)<$C8+ROUND($E8*($D8-$C8+1),0),"█","░"),"")) | Q8: =IF($F8="Yes",IF(DATE(2026,9,21)=$C8,"◆",""),IF(AND(DATE(2026,9,21)>=$C8,DATE(2026,9,21)<=$D8),IF(DATE(2026,9,21)<$C8+ROUND($E8*($D8-$C8+1),0),"█","░"),"")) | R8: =IF($F8="Yes",IF(DATE(2026,9,22)=$C8,"◆",""),IF(AND(DATE(2026,9,22)>=$C8,DATE(2026,9,22)<=$D8),IF(DATE(2026,9,22)<$C8+ROUND($E8*($D8-$C8+1),0),"█","░"),"")) | S8: =IF($F8="Yes",IF(DATE(2026,9,23)=$C8,"◆",""),IF(AND(DATE(2026,9,23)>=$C8,DATE(2026,9,23)<=$D8),IF(DATE(2026,9,23)<$C8+ROUND($E8*($D8-$C8+1),0),"█","░"),"")) | T8: =IF($F8="Yes",IF(DATE(2026,9,24)=$C8,"◆",""),IF(AND(DATE(2026,9,24)>=$C8,DATE(2026,9,24)<=$D8),IF(DATE(2026,9,24)<$C8+ROUND($E8*($D8-$C8+1),0),"█","░"),"")) | U8: =IF($F8="Yes",IF(DATE(2026,9,25)=$C8,"◆",""),IF(AND(DATE(2026,9,25)>=$C8,DATE(2026,9,25)<=$D8),IF(DATE(2026,9,25)<$C8+ROUND($E8*($D8-$C8+1),0),"█","░"),"")) | V8: =IF($F8="Yes",IF(DATE(2026,9,26)=$C8,"◆",""),IF(AND(DATE(2026,9,26)>=$C8,DATE(2026,9,26)<=$D8),IF(DATE(2026,9,26)<$C8+ROUND($E8*($D8-$C8+1),0),"█","░"),"")) | W8: =IF($F8="Yes",IF(DATE(2026,9,27)=$C8,"◆",""),IF(AND(DATE(2026,9,27)>=$C8,DATE(2026,9,27)<=$D8),IF(DATE(2026,9,27)<$C8+ROUND($E8*($D8-$C8+1),0),"█","░"),"")) | X8: =IF($F8="Yes",IF(DATE(2026,9,28)=$C8,"◆",""),IF(AND(DATE(2026,9,28)>=$C8,DATE(2026,9,28)<=$D8),IF(DATE(2026,9,28)<$C8+ROUND($E8*($D8-$C8+1),0),"█","░"),"")) | Y8: =IF($F8="Yes",IF(DATE(2026,9,29)=$C8,"◆",""),IF(AND(DATE(2026,9,29)>=$C8,DATE(2026,9,29)<=$D8),IF(DATE(2026,9,29)<$C8+ROUND($E8*($D8-$C8+1),0),"█","░"),"")) | Z8: =IF($F8="Yes",IF(DATE(2026,9,30)=$C8,"◆",""),IF(AND(DATE(2026,9,30)>=$C8,DATE(2026,9,30)<=$D8),IF(DATE(2026,9,30)<$C8+ROUND($E8*($D8-$C8+1),0),"█","░"),"")) | AA8: =IF($F8="Yes",IF(DATE(2026,10,1)=$C8,"◆",""),IF(AND(DATE(2026,10,1)>=$C8,DATE(2026,10,1)<=$D8),IF(DATE(2026,10,1)<$C8+ROUND($E8*($D8-$C8+1),0),"█","░"),"")) | AB8: =IF($F8="Yes",IF(DATE(2026,10,2)=$C8,"◆",""),IF(AND(DATE(2026,10,2)>=$C8,DATE(2026,10,2)<=$D8),IF(DATE(2026,10,2)<$C8+ROUND($E8*($D8-$C8+1),0),"█","░"),"")) | AC8: =IF($F8="Yes",IF(DATE(2026,10,3)=$C8,"◆",""),IF(AND(DATE(2026,10,3)>=$C8,DATE(2026,10,3)<=$D8),IF(DATE(2026,10,3)<$C8+ROUND($E8*($D8-$C8+1),0),"█","░"),"")) | AD8: =IF($F8="Yes",IF(DATE(2026,10,4)=$C8,"◆",""),IF(AND(DATE(2026,10,4)>=$C8,DATE(2026,10,4)<=$D8),IF(DATE(2026,10,4)<$C8+ROUND($E8*($D8-$C8+1),0),"█","░"),"")) | AE8: =IF($F8="Yes",IF(DATE(2026,10,5)=$C8,"◆",""),IF(AND(DATE(2026,10,5)>=$C8,DATE(2026,10,5)<=$D8),IF(DATE(2026,10,5)<$C8+ROUND($E8*($D8-$C8+1),0),"█","░"),"")) | AF8: =IF($F8="Yes",IF(DATE(2026,10,6)=$C8,"◆",""),IF(AND(DATE(2026,10,6)>=$C8,DATE(2026,10,6)<=$D8),IF(DATE(2026,10,6)<$C8+ROUND($E8*($D8-$C8+1),0),"█","░"),"")) | AG8: =IF($F8="Yes",IF(DATE(2026,10,7)=$C8,"◆",""),IF(AND(DATE(2026,10,7)>=$C8,DATE(2026,10,7)<=$D8),IF(DATE(2026,10,7)<$C8+ROUND($E8*($D8-$C8+1),0),"█","░"),"")) | AH8: =IF($F8="Yes",IF(DATE(2026,10,8)=$C8,"◆",""),IF(AND(DATE(2026,10,8)>=$C8,DATE(2026,10,8)<=$D8),IF(DATE(2026,10,8)<$C8+ROUND($E8*($D8-$C8+1),0),"█","░"),"")) | AI8: =IF($F8="Yes",IF(DATE(2026,10,9)=$C8,"◆",""),IF(AND(DATE(2026,10,9)>=$C8,DATE(2026,10,9)<=$D8),IF(DATE(2026,10,9)<$C8+ROUND($E8*($D8-$C8+1),0),"█","░"),"")) | AJ8: =IF($F8="Yes",IF(DATE(2026,10,10)=$C8,"◆",""),IF(AND(DATE(2026,10,10)>=$C8,DATE(2026,10,10)<=$D8),IF(DATE(2026,10,10)<$C8+ROUND($E8*($D8-$C8+1),0),"█","░"),"")) | AK8: =IF($F8="Yes",IF(DATE(2026,10,11)=$C8,"◆",""),IF(AND(DATE(2026,10,11)>=$C8,DATE(2026,10,11)<=$D8),IF(DATE(2026,10,11)<$C8+ROUND($E8*($D8-$C8+1),0),"█","░"),"")) | AL8: =IF($F8="Yes",IF(DATE(2026,10,12)=$C8,"◆",""),IF(AND(DATE(2026,10,12)>=$C8,DATE(2026,10,12)<=$D8),IF(DATE(2026,10,12)<$C8+ROUND($E8*($D8-$C8+1),0),"█","░"),"")) | AM8: =IF($F8="Yes",IF(DATE(2026,10,13)=$C8,"◆",""),IF(AND(DATE(2026,10,13)>=$C8,DATE(2026,10,13)<=$D8),IF(DATE(2026,10,13)<$C8+ROUND($E8*($D8-$C8+1),0),"█","░"),"")) | AN8: =IF($F8="Yes",IF(DATE(2026,10,14)=$C8,"◆",""),IF(AND(DATE(2026,10,14)>=$C8,DATE(2026,10,14)<=$D8),IF(DATE(2026,10,14)<$C8+ROUND($E8*($D8-$C8+1),0),"█","░"),""))
A9: ='Project Tracker'!A8 | B9: ='Project Tracker'!C8 | C9: ='Project Tracker'!E8 | D9: ='Project Tracker'!F8 | E9: ='Project Tracker'!N8 | F9: ='Project Tracker'!J8 | G9: =IF($F9="Yes",IF(DATE(2026,9,11)=$C9,"◆",""),IF(AND(DATE(2026,9,11)>=$C9,DATE(2026,9,11)<=$D9),IF(DATE(2026,9,11)<$C9+ROUND($E9*($D9-$C9+1),0),"█","░"),"")) | H9: =IF($F9="Yes",IF(DATE(2026,9,12)=$C9,"◆",""),IF(AND(DATE(2026,9,12)>=$C9,DATE(2026,9,12)<=$D9),IF(DATE(2026,9,12)<$C9+ROUND($E9*($D9-$C9+1),0),"█","░"),"")) | I9: =IF($F9="Yes",IF(DATE(2026,9,13)=$C9,"◆",""),IF(AND(DATE(2026,9,13)>=$C9,DATE(2026,9,13)<=$D9),IF(DATE(2026,9,13)<$C9+ROUND($E9*($D9-$C9+1),0),"█","░"),"")) | J9: =IF($F9="Yes",IF(DATE(2026,9,14)=$C9,"◆",""),IF(AND(DATE(2026,9,14)>=$C9,DATE(2026,9,14)<=$D9),IF(DATE(2026,9,14)<$C9+ROUND($E9*($D9-$C9+1),0),"█","░"),"")) | K9: =IF($F9="Yes",IF(DATE(2026,9,15)=$C9,"◆",""),IF(AND(DATE(2026,9,15)>=$C9,DATE(2026,9,15)<=$D9),IF(DATE(2026,9,15)<$C9+ROUND($E9*($D9-$C9+1),0),"█","░"),"")) | L9: =IF($F9="Yes",IF(DATE(2026,9,16)=$C9,"◆",""),IF(AND(DATE(2026,9,16)>=$C9,DATE(2026,9,16)<=$D9),IF(DATE(2026,9,16)<$C9+ROUND($E9*($D9-$C9+1),0),"█","░"),"")) | M9: =IF($F9="Yes",IF(DATE(2026,9,17)=$C9,"◆",""),IF(AND(DATE(2026,9,17)>=$C9,DATE(2026,9,17)<=$D9),IF(DATE(2026,9,17)<$C9+ROUND($E9*($D9-$C9+1),0),"█","░"),"")) | N9: =IF($F9="Yes",IF(DATE(2026,9,18)=$C9,"◆",""),IF(AND(DATE(2026,9,18)>=$C9,DATE(2026,9,18)<=$D9),IF(DATE(2026,9,18)<$C9+ROUND($E9*($D9-$C9+1),0),"█","░"),"")) | O9: =IF($F9="Yes",IF(DATE(2026,9,19)=$C9,"◆",""),IF(AND(DATE(2026,9,19)>=$C9,DATE(2026,9,19)<=$D9),IF(DATE(2026,9,19)<$C9+ROUND($E9*($D9-$C9+1),0),"█","░"),"")) | P9: =IF($F9="Yes",IF(DATE(2026,9,20)=$C9,"◆",""),IF(AND(DATE(2026,9,20)>=$C9,DATE(2026,9,20)<=$D9),IF(DATE(2026,9,20)<$C9+ROUND($E9*($D9-$C9+1),0),"█","░"),"")) | Q9: =IF($F9="Yes",IF(DATE(2026,9,21)=$C9,"◆",""),IF(AND(DATE(2026,9,21)>=$C9,DATE(2026,9,21)<=$D9),IF(DATE(2026,9,21)<$C9+ROUND($E9*($D9-$C9+1),0),"█","░"),"")) | R9: =IF($F9="Yes",IF(DATE(2026,9,22)=$C9,"◆",""),IF(AND(DATE(2026,9,22)>=$C9,DATE(2026,9,22)<=$D9),IF(DATE(2026,9,22)<$C9+ROUND($E9*($D9-$C9+1),0),"█","░"),"")) | S9: =IF($F9="Yes",IF(DATE(2026,9,23)=$C9,"◆",""),IF(AND(DATE(2026,9,23)>=$C9,DATE(2026,9,23)<=$D9),IF(DATE(2026,9,23)<$C9+ROUND($E9*($D9-$C9+1),0),"█","░"),"")) | T9: =IF($F9="Yes",IF(DATE(2026,9,24)=$C9,"◆",""),IF(AND(DATE(2026,9,24)>=$C9,DATE(2026,9,24)<=$D9),IF(DATE(2026,9,24)<$C9+ROUND($E9*($D9-$C9+1),0),"█","░"),"")) | U9: =IF($F9="Yes",IF(DATE(2026,9,25)=$C9,"◆",""),IF(AND(DATE(2026,9,25)>=$C9,DATE(2026,9,25)<=$D9),IF(DATE(2026,9,25)<$C9+ROUND($E9*($D9-$C9+1),0),"█","░"),"")) | V9: =IF($F9="Yes",IF(DATE(2026,9,26)=$C9,"◆",""),IF(AND(DATE(2026,9,26)>=$C9,DATE(2026,9,26)<=$D9),IF(DATE(2026,9,26)<$C9+ROUND($E9*($D9-$C9+1),0),"█","░"),"")) | W9: =IF($F9="Yes",IF(DATE(2026,9,27)=$C9,"◆",""),IF(AND(DATE(2026,9,27)>=$C9,DATE(2026,9,27)<=$D9),IF(DATE(2026,9,27)<$C9+ROUND($E9*($D9-$C9+1),0),"█","░"),"")) | X9: =IF($F9="Yes",IF(DATE(2026,9,28)=$C9,"◆",""),IF(AND(DATE(2026,9,28)>=$C9,DATE(2026,9,28)<=$D9),IF(DATE(2026,9,28)<$C9+ROUND($E9*($D9-$C9+1),0),"█","░"),"")) | Y9: =IF($F9="Yes",IF(DATE(2026,9,29)=$C9,"◆",""),IF(AND(DATE(2026,9,29)>=$C9,DATE(2026,9,29)<=$D9),IF(DATE(2026,9,29)<$C9+ROUND($E9*($D9-$C9+1),0),"█","░"),"")) | Z9: =IF($F9="Yes",IF(DATE(2026,9,30)=$C9,"◆",""),IF(AND(DATE(2026,9,30)>=$C9,DATE(2026,9,30)<=$D9),IF(DATE(2026,9,30)<$C9+ROUND($E9*($D9-$C9+1),0),"█","░"),"")) | AA9: =IF($F9="Yes",IF(DATE(2026,10,1)=$C9,"◆",""),IF(AND(DATE(2026,10,1)>=$C9,DATE(2026,10,1)<=$D9),IF(DATE(2026,10,1)<$C9+ROUND($E9*($D9-$C9+1),0),"█","░"),"")) | AB9: =IF($F9="Yes",IF(DATE(2026,10,2)=$C9,"◆",""),IF(AND(DATE(2026,10,2)>=$C9,DATE(2026,10,2)<=$D9),IF(DATE(2026,10,2)<$C9+ROUND($E9*($D9-$C9+1),0),"█","░"),"")) | AC9: =IF($F9="Yes",IF(DATE(2026,10,3)=$C9,"◆",""),IF(AND(DATE(2026,10,3)>=$C9,DATE(2026,10,3)<=$D9),IF(DATE(2026,10,3)<$C9+ROUND($E9*($D9-$C9+1),0),"█","░"),"")) | AD9: =IF($F9="Yes",IF(DATE(2026,10,4)=$C9,"◆",""),IF(AND(DATE(2026,10,4)>=$C9,DATE(2026,10,4)<=$D9),IF(DATE(2026,10,4)<$C9+ROUND($E9*($D9-$C9+1),0),"█","░"),"")) | AE9: =IF($F9="Yes",IF(DATE(2026,10,5)=$C9,"◆",""),IF(AND(DATE(2026,10,5)>=$C9,DATE(2026,10,5)<=$D9),IF(DATE(2026,10,5)<$C9+ROUND($E9*($D9-$C9+1),0),"█","░"),"")) | AF9: =IF($F9="Yes",IF(DATE(2026,10,6)=$C9,"◆",""),IF(AND(DATE(2026,10,6)>=$C9,DATE(2026,10,6)<=$D9),IF(DATE(2026,10,6)<$C9+ROUND($E9*($D9-$C9+1),0),"█","░"),"")) | AG9: =IF($F9="Yes",IF(DATE(2026,10,7)=$C9,"◆",""),IF(AND(DATE(2026,10,7)>=$C9,DATE(2026,10,7)<=$D9),IF(DATE(2026,10,7)<$C9+ROUND($E9*($D9-$C9+1),0),"█","░"),"")) | AH9: =IF($F9="Yes",IF(DATE(2026,10,8)=$C9,"◆",""),IF(AND(DATE(2026,10,8)>=$C9,DATE(2026,10,8)<=$D9),IF(DATE(2026,10,8)<$C9+ROUND($E9*($D9-$C9+1),0),"█","░"),"")) | AI9: =IF($F9="Yes",IF(DATE(2026,10,9)=$C9,"◆",""),IF(AND(DATE(2026,10,9)>=$C9,DATE(2026,10,9)<=$D9),IF(DATE(2026,10,9)<$C9+ROUND($E9*($D9-$C9+1),0),"█","░"),"")) | AJ9: =IF($F9="Yes",IF(DATE(2026,10,10)=$C9,"◆",""),IF(AND(DATE(2026,10,10)>=$C9,DATE(2026,10,10)<=$D9),IF(DATE(2026,10,10)<$C9+ROUND($E9*($D9-$C9+1),0),"█","░"),"")) | AK9: =IF($F9="Yes",IF(DATE(2026,10,11)=$C9,"◆",""),IF(AND(DATE(2026,10,11)>=$C9,DATE(2026,10,11)<=$D9),IF(DATE(2026,10,11)<$C9+ROUND($E9*($D9-$C9+1),0),"█","░"),"")) | AL9: =IF($F9="Yes",IF(DATE(2026,10,12)=$C9,"◆",""),IF(AND(DATE(2026,10,12)>=$C9,DATE(2026,10,12)<=$D9),IF(DATE(2026,10,12)<$C9+ROUND($E9*($D9-$C9+1),0),"█","░"),"")) | AM9: =IF($F9="Yes",IF(DATE(2026,10,13)=$C9,"◆",""),IF(AND(DATE(2026,10,13)>=$C9,DATE(2026,10,13)<=$D9),IF(DATE(2026,10,13)<$C9+ROUND($E9*($D9-$C9+1),0),"█","░"),"")) | AN9: =IF($F9="Yes",IF(DATE(2026,10,14)=$C9,"◆",""),IF(AND(DATE(2026,10,14)>=$C9,DATE(2026,10,14)<=$D9),IF(DATE(2026,10,14)<$C9+ROUND($E9*($D9-$C9+1),0),"█","░"),""))
A10: ='Project Tracker'!A9 | B10: ='Project Tracker'!C9 | C10: ='Project Tracker'!E9 | D10: ='Project Tracker'!F9 | E10: ='Project Tracker'!N9 | F10: ='Project Tracker'!J9 | G10: =IF($F10="Yes",IF(DATE(2026,9,11)=$C10,"◆",""),IF(AND(DATE(2026,9,11)>=$C10,DATE(2026,9,11)<=$D10),IF(DATE(2026,9,11)<$C10+ROUND($E10*($D10-$C10+1),0),"█","░"),"")) | H10: =IF($F10="Yes",IF(DATE(2026,9,12)=$C10,"◆",""),IF(AND(DATE(2026,9,12)>=$C10,DATE(2026,9,12)<=$D10),IF(DATE(2026,9,12)<$C10+ROUND($E10*($D10-$C10+1),0),"█","░"),"")) | I10: =IF($F10="Yes",IF(DATE(2026,9,13)=$C10,"◆",""),IF(AND(DATE(2026,9,13)>=$C10,DATE(2026,9,13)<=$D10),IF(DATE(2026,9,13)<$C10+ROUND($E10*($D10-$C10+1),0),"█","░"),"")) | J10: =IF($F10="Yes",IF(DATE(2026,9,14)=$C10,"◆",""),IF(AND(DATE(2026,9,14)>=$C10,DATE(2026,9,14)<=$D10),IF(DATE(2026,9,14)<$C10+ROUND($E10*($D10-$C10+1),0),"█","░"),"")) | K10: =IF($F10="Yes",IF(DATE(2026,9,15)=$C10,"◆",""),IF(AND(DATE(2026,9,15)>=$C10,DATE(2026,9,15)<=$D10),IF(DATE(2026,9,15)<$C10+ROUND($E10*($D10-$C10+1),0),"█","░"),"")) | L10: =IF($F10="Yes",IF(DATE(2026,9,16)=$C10,"◆",""),IF(AND(DATE(2026,9,16)>=$C10,DATE(2026,9,16)<=$D10),IF(DATE(2026,9,16)<$C10+ROUND($E10*($D10-$C10+1),0),"█","░"),"")) | M10: =IF($F10="Yes",IF(DATE(2026,9,17)=$C10,"◆",""),IF(AND(DATE(2026,9,17)>=$C10,DATE(2026,9,17)<=$D10),IF(DATE(2026,9,17)<$C10+ROUND($E10*($D10-$C10+1),0),"█","░"),"")) | N10: =IF($F10="Yes",IF(DATE(2026,9,18)=$C10,"◆",""),IF(AND(DATE(2026,9,18)>=$C10,DATE(2026,9,18)<=$D10),IF(DATE(2026,9,18)<$C10+ROUND($E10*($D10-$C10+1),0),"█","░"),"")) | O10: =IF($F10="Yes",IF(DATE(2026,9,19)=$C10,"◆",""),IF(AND(DATE(2026,9,19)>=$C10,DATE(2026,9,19)<=$D10),IF(DATE(2026,9,19)<$C10+ROUND($E10*($D10-$C10+1),0),"█","░"),"")) | P10: =IF($F10="Yes",IF(DATE(2026,9,20)=$C10,"◆",""),IF(AND(DATE(2026,9,20)>=$C10,DATE(2026,9,20)<=$D10),IF(DATE(2026,9,20)<$C10+ROUND($E10*($D10-$C10+1),0),"█","░"),"")) | Q10: =IF($F10="Yes",IF(DATE(2026,9,21)=$C10,"◆",""),IF(AND(DATE(2026,9,21)>=$C10,DATE(2026,9,21)<=$D10),IF(DATE(2026,9,21)<$C10+ROUND($E10*($D10-$C10+1),0),"█","░"),"")) | R10: =IF($F10="Yes",IF(DATE(2026,9,22)=$C10,"◆",""),IF(AND(DATE(2026,9,22)>=$C10,DATE(2026,9,22)<=$D10),IF(DATE(2026,9,22)<$C10+ROUND($E10*($D10-$C10+1),0),"█","░"),"")) | S10: =IF($F10="Yes",IF(DATE(2026,9,23)=$C10,"◆",""),IF(AND(DATE(2026,9,23)>=$C10,DATE(2026,9,23)<=$D10),IF(DATE(2026,9,23)<$C10+ROUND($E10*($D10-$C10+1),0),"█","░"),"")) | T10: =IF($F10="Yes",IF(DATE(2026,9,24)=$C10,"◆",""),IF(AND(DATE(2026,9,24)>=$C10,DATE(2026,9,24)<=$D10),IF(DATE(2026,9,24)<$C10+ROUND($E10*($D10-$C10+1),0),"█","░"),"")) | U10: =IF($F10="Yes",IF(DATE(2026,9,25)=$C10,"◆",""),IF(AND(DATE(2026,9,25)>=$C10,DATE(2026,9,25)<=$D10),IF(DATE(2026,9,25)<$C10+ROUND($E10*($D10-$C10+1),0),"█","░"),"")) | V10: =IF($F10="Yes",IF(DATE(2026,9,26)=$C10,"◆",""),IF(AND(DATE(2026,9,26)>=$C10,DATE(2026,9,26)<=$D10),IF(DATE(2026,9,26)<$C10+ROUND($E10*($D10-$C10+1),0),"█","░"),"")) | W10: =IF($F10="Yes",IF(DATE(2026,9,27)=$C10,"◆",""),IF(AND(DATE(2026,9,27)>=$C10,DATE(2026,9,27)<=$D10),IF(DATE(2026,9,27)<$C10+ROUND($E10*($D10-$C10+1),0),"█","░"),"")) | X10: =IF($F10="Yes",IF(DATE(2026,9,28)=$C10,"◆",""),IF(AND(DATE(2026,9,28)>=$C10,DATE(2026,9,28)<=$D10),IF(DATE(2026,9,28)<$C10+ROUND($E10*($D10-$C10+1),0),"█","░"),"")) | Y10: =IF($F10="Yes",IF(DATE(2026,9,29)=$C10,"◆",""),IF(AND(DATE(2026,9,29)>=$C10,DATE(2026,9,29)<=$D10),IF(DATE(2026,9,29)<$C10+ROUND($E10*($D10-$C10+1),0),"█","░"),"")) | Z10: =IF($F10="Yes",IF(DATE(2026,9,30)=$C10,"◆",""),IF(AND(DATE(2026,9,30)>=$C10,DATE(2026,9,30)<=$D10),IF(DATE(2026,9,30)<$C10+ROUND($E10*($D10-$C10+1),0),"█","░"),"")) | AA10: =IF($F10="Yes",IF(DATE(2026,10,1)=$C10,"◆",""),IF(AND(DATE(2026,10,1)>=$C10,DATE(2026,10,1)<=$D10),IF(DATE(2026,10,1)<$C10+ROUND($E10*($D10-$C10+1),0),"█","░"),"")) | AB10: =IF($F10="Yes",IF(DATE(2026,10,2)=$C10,"◆",""),IF(AND(DATE(2026,10,2)>=$C10,DATE(2026,10,2)<=$D10),IF(DATE(2026,10,2)<$C10+ROUND($E10*($D10-$C10+1),0),"█","░"),"")) | AC10: =IF($F10="Yes",IF(DATE(2026,10,3)=$C10,"◆",""),IF(AND(DATE(2026,10,3)>=$C10,DATE(2026,10,3)<=$D10),IF(DATE(2026,10,3)<$C10+ROUND($E10*($D10-$C10+1),0),"█","░"),"")) | AD10: =IF($F10="Yes",IF(DATE(2026,10,4)=$C10,"◆",""),IF(AND(DATE(2026,10,4)>=$C10,DATE(2026,10,4)<=$D10),IF(DATE(2026,10,4)<$C10+ROUND($E10*($D10-$C10+1),0),"█","░"),"")) | AE10: =IF($F10="Yes",IF(DATE(2026,10,5)=$C10,"◆",""),IF(AND(DATE(2026,10,5)>=$C10,DATE(2026,10,5)<=$D10),IF(DATE(2026,10,5)<$C10+ROUND($E10*($D10-$C10+1),0),"█","░"),"")) | AF10: =IF($F10="Yes",IF(DATE(2026,10,6)=$C10,"◆",""),IF(AND(DATE(2026,10,6)>=$C10,DATE(2026,10,6)<=$D10),IF(DATE(2026,10,6)<$C10+ROUND($E10*($D10-$C10+1),0),"█","░"),"")) | AG10: =IF($F10="Yes",IF(DATE(2026,10,7)=$C10,"◆",""),IF(AND(DATE(2026,10,7)>=$C10,DATE(2026,10,7)<=$D10),IF(DATE(2026,10,7)<$C10+ROUND($E10*($D10-$C10+1),0),"█","░"),"")) | AH10: =IF($F10="Yes",IF(DATE(2026,10,8)=$C10,"◆",""),IF(AND(DATE(2026,10,8)>=$C10,DATE(2026,10,8)<=$D10),IF(DATE(2026,10,8)<$C10+ROUND($E10*($D10-$C10+1),0),"█","░"),"")) | AI10: =IF($F10="Yes",IF(DATE(2026,10,9)=$C10,"◆",""),IF(AND(DATE(2026,10,9)>=$C10,DATE(2026,10,9)<=$D10),IF(DATE(2026,10,9)<$C10+ROUND($E10*($D10-$C10+1),0),"█","░"),"")) | AJ10: =IF($F10="Yes",IF(DATE(2026,10,10)=$C10,"◆",""),IF(AND(DATE(2026,10,10)>=$C10,DATE(2026,10,10)<=$D10),IF(DATE(2026,10,10)<$C10+ROUND($E10*($D10-$C10+1),0),"█","░"),"")) | AK10: =IF($F10="Yes",IF(DATE(2026,10,11)=$C10,"◆",""),IF(AND(DATE(2026,10,11)>=$C10,DATE(2026,10,11)<=$D10),IF(DATE(2026,10,11)<$C10+ROUND($E10*($D10-$C10+1),0),"█","░"),"")) | AL10: =IF($F10="Yes",IF(DATE(2026,10,12)=$C10,"◆",""),IF(AND(DATE(2026,10,12)>=$C10,DATE(2026,10,12)<=$D10),IF(DATE(2026,10,12)<$C10+ROUND($E10*($D10-$C10+1),0),"█","░"),"")) | AM10: =IF($F10="Yes",IF(DATE(2026,10,13)=$C10,"◆",""),IF(AND(DATE(2026,10,13)>=$C10,DATE(2026,10,13)<=$D10),IF(DATE(2026,10,13)<$C10+ROUND($E10*($D10-$C10+1),0),"█","░"),"")) | AN10: =IF($F10="Yes",IF(DATE(2026,10,14)=$C10,"◆",""),IF(AND(DATE(2026,10,14)>=$C10,DATE(2026,10,14)<=$D10),IF(DATE(2026,10,14)<$C10+ROUND($E10*($D10-$C10+1),0),"█","░"),""))
A11: ='Project Tracker'!A10 | B11: ='Project Tracker'!C10 | C11: ='Project Tracker'!E10 | D11: ='Project Tracker'!F10 | E11: ='Project Tracker'!N10 | F11: ='Project Tracker'!J10 | G11: =IF($F11="Yes",IF(DATE(2026,9,11)=$C11,"◆",""),IF(AND(DATE(2026,9,11)>=$C11,DATE(2026,9,11)<=$D11),IF(DATE(2026,9,11)<$C11+ROUND($E11*($D11-$C11+1),0),"█","░"),"")) | H11: =IF($F11="Yes",IF(DATE(2026,9,12)=$C11,"◆",""),IF(AND(DATE(2026,9,12)>=$C11,DATE(2026,9,12)<=$D11),IF(DATE(2026,9,12)<$C11+ROUND($E11*($D11-$C11+1),0),"█","░"),"")) | I11: =IF($F11="Yes",IF(DATE(2026,9,13)=$C11,"◆",""),IF(AND(DATE(2026,9,13)>=$C11,DATE(2026,9,13)<=$D11),IF(DATE(2026,9,13)<$C11+ROUND($E11*($D11-$C11+1),0),"█","░"),"")) | J11: =IF($F11="Yes",IF(DATE(2026,9,14)=$C11,"◆",""),IF(AND(DATE(2026,9,14)>=$C11,DATE(2026,9,14)<=$D11),IF(DATE(2026,9,14)<$C11+ROUND($E11*($D11-$C11+1),0),"█","░"),"")) | K11: =IF($F11="Yes",IF(DATE(2026,9,15)=$C11,"◆",""),IF(AND(DATE(2026,9,15)>=$C11,DATE(2026,9,15)<=$D11),IF(DATE(2026,9,15)<$C11+ROUND($E11*($D11-$C11+1),0),"█","░"),"")) | L11: =IF($F11="Yes",IF(DATE(2026,9,16)=$C11,"◆",""),IF(AND(DATE(2026,9,16)>=$C11,DATE(2026,9,16)<=$D11),IF(DATE(2026,9,16)<$C11+ROUND($E11*($D11-$C11+1),0),"█","░"),"")) | M11: =IF($F11="Yes",IF(DATE(2026,9,17)=$C11,"◆",""),IF(AND(DATE(2026,9,17)>=$C11,DATE(2026,9,17)<=$D11),IF(DATE(2026,9,17)<$C11+ROUND($E11*($D11-$C11+1),0),"█","░"),"")) | N11: =IF($F11="Yes",IF(DATE(2026,9,18)=$C11,"◆",""),IF(AND(DATE(2026,9,18)>=$C11,DATE(2026,9,18)<=$D11),IF(DATE(2026,9,18)<$C11+ROUND($E11*($D11-$C11+1),0),"█","░"),"")) | O11: =IF($F11="Yes",IF(DATE(2026,9,19)=$C11,"◆",""),IF(AND(DATE(2026,9,19)>=$C11,DATE(2026,9,19)<=$D11),IF(DATE(2026,9,19)<$C11+ROUND($E11*($D11-$C11+1),0),"█","░"),"")) | P11: =IF($F11="Yes",IF(DATE(2026,9,20)=$C11,"◆",""),IF(AND(DATE(2026,9,20)>=$C11,DATE(2026,9,20)<=$D11),IF(DATE(2026,9,20)<$C11+ROUND($E11*($D11-$C11+1),0),"█","░"),"")) | Q11: =IF($F11="Yes",IF(DATE(2026,9,21)=$C11,"◆",""),IF(AND(DATE(2026,9,21)>=$C11,DATE(2026,9,21)<=$D11),IF(DATE(2026,9,21)<$C11+ROUND($E11*($D11-$C11+1),0),"█","░"),"")) | R11: =IF($F11="Yes",IF(DATE(2026,9,22)=$C11,"◆",""),IF(AND(DATE(2026,9,22)>=$C11,DATE(2026,9,22)<=$D11),IF(DATE(2026,9,22)<$C11+ROUND($E11*($D11-$C11+1),0),"█","░"),"")) | S11: =IF($F11="Yes",IF(DATE(2026,9,23)=$C11,"◆",""),IF(AND(DATE(2026,9,23)>=$C11,DATE(2026,9,23)<=$D11),IF(DATE(2026,9,23)<$C11+ROUND($E11*($D11-$C11+1),0),"█","░"),"")) | T11: =IF($F11="Yes",IF(DATE(2026,9,24)=$C11,"◆",""),IF(AND(DATE(2026,9,24)>=$C11,DATE(2026,9,24)<=$D11),IF(DATE(2026,9,24)<$C11+ROUND($E11*($D11-$C11+1),0),"█","░"),"")) | U11: =IF($F11="Yes",IF(DATE(2026,9,25)=$C11,"◆",""),IF(AND(DATE(2026,9,25)>=$C11,DATE(2026,9,25)<=$D11),IF(DATE(2026,9,25)<$C11+ROUND($E11*($D11-$C11+1),0),"█","░"),"")) | V11: =IF($F11="Yes",IF(DATE(2026,9,26)=$C11,"◆",""),IF(AND(DATE(2026,9,26)>=$C11,DATE(2026,9,26)<=$D11),IF(DATE(2026,9,26)<$C11+ROUND($E11*($D11-$C11+1),0),"█","░"),"")) | W11: =IF($F11="Yes",IF(DATE(2026,9,27)=$C11,"◆",""),IF(AND(DATE(2026,9,27)>=$C11,DATE(2026,9,27)<=$D11),IF(DATE(2026,9,27)<$C11+ROUND($E11*($D11-$C11+1),0),"█","░"),"")) | X11: =IF($F11="Yes",IF(DATE(2026,9,28)=$C11,"◆",""),IF(AND(DATE(2026,9,28)>=$C11,DATE(2026,9,28)<=$D11),IF(DATE(2026,9,28)<$C11+ROUND($E11*($D11-$C11+1),0),"█","░"),"")) | Y11: =IF($F11="Yes",IF(DATE(2026,9,29)=$C11,"◆",""),IF(AND(DATE(2026,9,29)>=$C11,DATE(2026,9,29)<=$D11),IF(DATE(2026,9,29)<$C11+ROUND($E11*($D11-$C11+1),0),"█","░"),"")) | Z11: =IF($F11="Yes",IF(DATE(2026,9,30)=$C11,"◆",""),IF(AND(DATE(2026,9,30)>=$C11,DATE(2026,9,30)<=$D11),IF(DATE(2026,9,30)<$C11+ROUND($E11*($D11-$C11+1),0),"█","░"),"")) | AA11: =IF($F11="Yes",IF(DATE(2026,10,1)=$C11,"◆",""),IF(AND(DATE(2026,10,1)>=$C11,DATE(2026,10,1)<=$D11),IF(DATE(2026,10,1)<$C11+ROUND($E11*($D11-$C11+1),0),"█","░"),"")) | AB11: =IF($F11="Yes",IF(DATE(2026,10,2)=$C11,"◆",""),IF(AND(DATE(2026,10,2)>=$C11,DATE(2026,10,2)<=$D11),IF(DATE(2026,10,2)<$C11+ROUND($E11*($D11-$C11+1),0),"█","░"),"")) | AC11: =IF($F11="Yes",IF(DATE(2026,10,3)=$C11,"◆",""),IF(AND(DATE(2026,10,3)>=$C11,DATE(2026,10,3)<=$D11),IF(DATE(2026,10,3)<$C11+ROUND($E11*($D11-$C11+1),0),"█","░"),"")) | AD11: =IF($F11="Yes",IF(DATE(2026,10,4)=$C11,"◆",""),IF(AND(DATE(2026,10,4)>=$C11,DATE(2026,10,4)<=$D11),IF(DATE(2026,10,4)<$C11+ROUND($E11*($D11-$C11+1),0),"█","░"),"")) | AE11: =IF($F11="Yes",IF(DATE(2026,10,5)=$C11,"◆",""),IF(AND(DATE(2026,10,5)>=$C11,DATE(2026,10,5)<=$D11),IF(DATE(2026,10,5)<$C11+ROUND($E11*($D11-$C11+1),0),"█","░"),"")) | AF11: =IF($F11="Yes",IF(DATE(2026,10,6)=$C11,"◆",""),IF(AND(DATE(2026,10,6)>=$C11,DATE(2026,10,6)<=$D11),IF(DATE(2026,10,6)<$C11+ROUND($E11*($D11-$C11+1),0),"█","░"),"")) | AG11: =IF($F11="Yes",IF(DATE(2026,10,7)=$C11,"◆",""),IF(AND(DATE(2026,10,7)>=$C11,DATE(2026,10,7)<=$D11),IF(DATE(2026,10,7)<$C11+ROUND($E11*($D11-$C11+1),0),"█","░"),"")) | AH11: =IF($F11="Yes",IF(DATE(2026,10,8)=$C11,"◆",""),IF(AND(DATE(2026,10,8)>=$C11,DATE(2026,10,8)<=$D11),IF(DATE(2026,10,8)<$C11+ROUND($E11*($D11-$C11+1),0),"█","░"),"")) | AI11: =IF($F11="Yes",IF(DATE(2026,10,9)=$C11,"◆",""),IF(AND(DATE(2026,10,9)>=$C11,DATE(2026,10,9)<=$D11),IF(DATE(2026,10,9)<$C11+ROUND($E11*($D11-$C11+1),0),"█","░"),"")) | AJ11: =IF($F11="Yes",IF(DATE(2026,10,10)=$C11,"◆",""),IF(AND(DATE(2026,10,10)>=$C11,DATE(2026,10,10)<=$D11),IF(DATE(2026,10,10)<$C11+ROUND($E11*($D11-$C11+1),0),"█","░"),"")) | AK11: =IF($F11="Yes",IF(DATE(2026,10,11)=$C11,"◆",""),IF(AND(DATE(2026,10,11)>=$C11,DATE(2026,10,11)<=$D11),IF(DATE(2026,10,11)<$C11+ROUND($E11*($D11-$C11+1),0),"█","░"),"")) | AL11: =IF($F11="Yes",IF(DATE(2026,10,12)=$C11,"◆",""),IF(AND(DATE(2026,10,12)>=$C11,DATE(2026,10,12)<=$D11),IF(DATE(2026,10,12)<$C11+ROUND($E11*($D11-$C11+1),0),"█","░"),"")) | AM11: =IF($F11="Yes",IF(DATE(2026,10,13)=$C11,"◆",""),IF(AND(DATE(2026,10,13)>=$C11,DATE(2026,10,13)<=$D11),IF(DATE(2026,10,13)<$C11+ROUND($E11*($D11-$C11+1),0),"█","░"),"")) | AN11: =IF($F11="Yes",IF(DATE(2026,10,14)=$C11,"◆",""),IF(AND(DATE(2026,10,14)>=$C11,DATE(2026,10,14)<=$D11),IF(DATE(2026,10,14)<$C11+ROUND($E11*($D11-$C11+1),0),"█","░"),""))
A12: ='Project Tracker'!A11 | B12: ='Project Tracker'!C11 | C12: ='Project Tracker'!E11 | D12: ='Project Tracker'!F11 | E12: ='Project Tracker'!N11 | F12: ='Project Tracker'!J11 | G12: =IF($F12="Yes",IF(DATE(2026,9,11)=$C12,"◆",""),IF(AND(DATE(2026,9,11)>=$C12,DATE(2026,9,11)<=$D12),IF(DATE(2026,9,11)<$C12+ROUND($E12*($D12-$C12+1),0),"█","░"),"")) | H12: =IF($F12="Yes",IF(DATE(2026,9,12)=$C12,"◆",""),IF(AND(DATE(2026,9,12)>=$C12,DATE(2026,9,12)<=$D12),IF(DATE(2026,9,12)<$C12+ROUND($E12*($D12-$C12+1),0),"█","░"),"")) | I12: =IF($F12="Yes",IF(DATE(2026,9,13)=$C12,"◆",""),IF(AND(DATE(2026,9,13)>=$C12,DATE(2026,9,13)<=$D12),IF(DATE(2026,9,13)<$C12+ROUND($E12*($D12-$C12+1),0),"█","░"),"")) | J12: =IF($F12="Yes",IF(DATE(2026,9,14)=$C12,"◆",""),IF(AND(DATE(2026,9,14)>=$C12,DATE(2026,9,14)<=$D12),IF(DATE(2026,9,14)<$C12+ROUND($E12*($D12-$C12+1),0),"█","░"),"")) | K12: =IF($F12="Yes",IF(DATE(2026,9,15)=$C12,"◆",""),IF(AND(DATE(2026,9,15)>=$C12,DATE(2026,9,15)<=$D12),IF(DATE(2026,9,15)<$C12+ROUND($E12*($D12-$C12+1),0),"█","░"),"")) | L12: =IF($F12="Yes",IF(DATE(2026,9,16)=$C12,"◆",""),IF(AND(DATE(2026,9,16)>=$C12,DATE(2026,9,16)<=$D12),IF(DATE(2026,9,16)<$C12+ROUND($E12*($D12-$C12+1),0),"█","░"),"")) | M12: =IF($F12="Yes",IF(DATE(2026,9,17)=$C12,"◆",""),IF(AND(DATE(2026,9,17)>=$C12,DATE(2026,9,17)<=$D12),IF(DATE(2026,9,17)<$C12+ROUND($E12*($D12-$C12+1),0),"█","░"),"")) | N12: =IF($F12="Yes",IF(DATE(2026,9,18)=$C12,"◆",""),IF(AND(DATE(2026,9,18)>=$C12,DATE(2026,9,18)<=$D12),IF(DATE(2026,9,18)<$C12+ROUND($E12*($D12-$C12+1),0),"█","░"),"")) | O12: =IF($F12="Yes",IF(DATE(2026,9,19)=$C12,"◆",""),IF(AND(DATE(2026,9,19)>=$C12,DATE(2026,9,19)<=$D12),IF(DATE(2026,9,19)<$C12+ROUND($E12*($D12-$C12+1),0),"█","░"),"")) | P12: =IF($F12="Yes",IF(DATE(2026,9,20)=$C12,"◆",""),IF(AND(DATE(2026,9,20)>=$C12,DATE(2026,9,20)<=$D12),IF(DATE(2026,9,20)<$C12+ROUND($E12*($D12-$C12+1),0),"█","░"),"")) | Q12: =IF($F12="Yes",IF(DATE(2026,9,21)=$C12,"◆",""),IF(AND(DATE(2026,9,21)>=$C12,DATE(2026,9,21)<=$D12),IF(DATE(2026,9,21)<$C12+ROUND($E12*($D12-$C12+1),0),"█","░"),"")) | R12: =IF($F12="Yes",IF(DATE(2026,9,22)=$C12,"◆",""),IF(AND(DATE(2026,9,22)>=$C12,DATE(2026,9,22)<=$D12),IF(DATE(2026,9,22)<$C12+ROUND($E12*($D12-$C12+1),0),"█","░"),"")) | S12: =IF($F12="Yes",IF(DATE(2026,9,23)=$C12,"◆",""),IF(AND(DATE(2026,9,23)>=$C12,DATE(2026,9,23)<=$D12),IF(DATE(2026,9,23)<$C12+ROUND($E12*($D12-$C12+1),0),"█","░"),"")) | T12: =IF($F12="Yes",IF(DATE(2026,9,24)=$C12,"◆",""),IF(AND(DATE(2026,9,24)>=$C12,DATE(2026,9,24)<=$D12),IF(DATE(2026,9,24)<$C12+ROUND($E12*($D12-$C12+1),0),"█","░"),"")) | U12: =IF($F12="Yes",IF(DATE(2026,9,25)=$C12,"◆",""),IF(AND(DATE(2026,9,25)>=$C12,DATE(2026,9,25)<=$D12),IF(DATE(2026,9,25)<$C12+ROUND($E12*($D12-$C12+1),0),"█","░"),"")) | V12: =IF($F12="Yes",IF(DATE(2026,9,26)=$C12,"◆",""),IF(AND(DATE(2026,9,26)>=$C12,DATE(2026,9,26)<=$D12),IF(DATE(2026,9,26)<$C12+ROUND($E12*($D12-$C12+1),0),"█","░"),"")) | W12: =IF($F12="Yes",IF(DATE(2026,9,27)=$C12,"◆",""),IF(AND(DATE(2026,9,27)>=$C12,DATE(2026,9,27)<=$D12),IF(DATE(2026,9,27)<$C12+ROUND($E12*($D12-$C12+1),0),"█","░"),"")) | X12: =IF($F12="Yes",IF(DATE(2026,9,28)=$C12,"◆",""),IF(AND(DATE(2026,9,28)>=$C12,DATE(2026,9,28)<=$D12),IF(DATE(2026,9,28)<$C12+ROUND($E12*($D12-$C12+1),0),"█","░"),"")) | Y12: =IF($F12="Yes",IF(DATE(2026,9,29)=$C12,"◆",""),IF(AND(DATE(2026,9,29)>=$C12,DATE(2026,9,29)<=$D12),IF(DATE(2026,9,29)<$C12+ROUND($E12*($D12-$C12+1),0),"█","░"),"")) | Z12: =IF($F12="Yes",IF(DATE(2026,9,30)=$C12,"◆",""),IF(AND(DATE(2026,9,30)>=$C12,DATE(2026,9,30)<=$D12),IF(DATE(2026,9,30)<$C12+ROUND($E12*($D12-$C12+1),0),"█","░"),"")) | AA12: =IF($F12="Yes",IF(DATE(2026,10,1)=$C12,"◆",""),IF(AND(DATE(2026,10,1)>=$C12,DATE(2026,10,1)<=$D12),IF(DATE(2026,10,1)<$C12+ROUND($E12*($D12-$C12+1),0),"█","░"),"")) | AB12: =IF($F12="Yes",IF(DATE(2026,10,2)=$C12,"◆",""),IF(AND(DATE(2026,10,2)>=$C12,DATE(2026,10,2)<=$D12),IF(DATE(2026,10,2)<$C12+ROUND($E12*($D12-$C12+1),0),"█","░"),"")) | AC12: =IF($F12="Yes",IF(DATE(2026,10,3)=$C12,"◆",""),IF(AND(DATE(2026,10,3)>=$C12,DATE(2026,10,3)<=$D12),IF(DATE(2026,10,3)<$C12+ROUND($E12*($D12-$C12+1),0),"█","░"),"")) | AD12: =IF($F12="Yes",IF(DATE(2026,10,4)=$C12,"◆",""),IF(AND(DATE(2026,10,4)>=$C12,DATE(2026,10,4)<=$D12),IF(DATE(2026,10,4)<$C12+ROUND($E12*($D12-$C12+1),0),"█","░"),"")) | AE12: =IF($F12="Yes",IF(DATE(2026,10,5)=$C12,"◆",""),IF(AND(DATE(2026,10,5)>=$C12,DATE(2026,10,5)<=$D12),IF(DATE(2026,10,5)<$C12+ROUND($E12*($D12-$C12+1),0),"█","░"),"")) | AF12: =IF($F12="Yes",IF(DATE(2026,10,6)=$C12,"◆",""),IF(AND(DATE(2026,10,6)>=$C12,DATE(2026,10,6)<=$D12),IF(DATE(2026,10,6)<$C12+ROUND($E12*($D12-$C12+1),0),"█","░"),"")) | AG12: =IF($F12="Yes",IF(DATE(2026,10,7)=$C12,"◆",""),IF(AND(DATE(2026,10,7)>=$C12,DATE(2026,10,7)<=$D12),IF(DATE(2026,10,7)<$C12+ROUND($E12*($D12-$C12+1),0),"█","░"),"")) | AH12: =IF($F12="Yes",IF(DATE(2026,10,8)=$C12,"◆",""),IF(AND(DATE(2026,10,8)>=$C12,DATE(2026,10,8)<=$D12),IF(DATE(2026,10,8)<$C12+ROUND($E12*($D12-$C12+1),0),"█","░"),"")) | AI12: =IF($F12="Yes",IF(DATE(2026,10,9)=$C12,"◆",""),IF(AND(DATE(2026,10,9)>=$C12,DATE(2026,10,9)<=$D12),IF(DATE(2026,10,9)<$C12+ROUND($E12*($D12-$C12+1),0),"█","░"),"")) | AJ12: =IF($F12="Yes",IF(DATE(2026,10,10)=$C12,"◆",""),IF(AND(DATE(2026,10,10)>=$C12,DATE(2026,10,10)<=$D12),IF(DATE(2026,10,10)<$C12+ROUND($E12*($D12-$C12+1),0),"█","░"),"")) | AK12: =IF($F12="Yes",IF(DATE(2026,10,11)=$C12,"◆",""),IF(AND(DATE(2026,10,11)>=$C12,DATE(2026,10,11)<=$D12),IF(DATE(2026,10,11)<$C12+ROUND($E12*($D12-$C12+1),0),"█","░"),"")) | AL12: =IF($F12="Yes",IF(DATE(2026,10,12)=$C12,"◆",""),IF(AND(DATE(2026,10,12)>=$C12,DATE(2026,10,12)<=$D12),IF(DATE(2026,10,12)<$C12+ROUND($E12*($D12-$C12+1),0),"█","░"),"")) | AM12: =IF($F12="Yes",IF(DATE(2026,10,13)=$C12,"◆",""),IF(AND(DATE(2026,10,13)>=$C12,DATE(2026,10,13)<=$D12),IF(DATE(2026,10,13)<$C12+ROUND($E12*($D12-$C12+1),0),"█","░"),"")) | AN12: =IF($F12="Yes",IF(DATE(2026,10,14)=$C12,"◆",""),IF(AND(DATE(2026,10,14)>=$C12,DATE(2026,10,14)<=$D12),IF(DATE(2026,10,14)<$C12+ROUND($E12*($D12-$C12+1),0),"█","░"),""))
A13: ='Project Tracker'!A12 | B13: ='Project Tracker'!C12 | C13: ='Project Tracker'!E12 | D13: ='Project Tracker'!F12 | E13: ='Project Tracker'!N12 | F13: ='Project Tracker'!J12 | G13: =IF($F13="Yes",IF(DATE(2026,9,11)=$C13,"◆",""),IF(AND(DATE(2026,9,11)>=$C13,DATE(2026,9,11)<=$D13),IF(DATE(2026,9,11)<$C13+ROUND($E13*($D13-$C13+1),0),"█","░"),"")) | H13: =IF($F13="Yes",IF(DATE(2026,9,12)=$C13,"◆",""),IF(AND(DATE(2026,9,12)>=$C13,DATE(2026,9,12)<=$D13),IF(DATE(2026,9,12)<$C13+ROUND($E13*($D13-$C13+1),0),"█","░"),"")) | I13: =IF($F13="Yes",IF(DATE(2026,9,13)=$C13,"◆",""),IF(AND(DATE(2026,9,13)>=$C13,DATE(2026,9,13)<=$D13),IF(DATE(2026,9,13)<$C13+ROUND($E13*($D13-$C13+1),0),"█","░"),"")) | J13: =IF($F13="Yes",IF(DATE(2026,9,14)=$C13,"◆",""),IF(AND(DATE(2026,9,14)>=$C13,DATE(2026,9,14)<=$D13),IF(DATE(2026,9,14)<$C13+ROUND($E13*($D13-$C13+1),0),"█","░"),"")) | K13: =IF($F13="Yes",IF(DATE(2026,9,15)=$C13,"◆",""),IF(AND(DATE(2026,9,15)>=$C13,DATE(2026,9,15)<=$D13),IF(DATE(2026,9,15)<$C13+ROUND($E13*($D13-$C13+1),0),"█","░"),"")) | L13: =IF($F13="Yes",IF(DATE(2026,9,16)=$C13,"◆",""),IF(AND(DATE(2026,9,16)>=$C13,DATE(2026,9,16)<=$D13),IF(DATE(2026,9,16)<$C13+ROUND($E13*($D13-$C13+1),0),"█","░"),"")) | M13: =IF($F13="Yes",IF(DATE(2026,9,17)=$C13,"◆",""),IF(AND(DATE(2026,9,17)>=$C13,DATE(2026,9,17)<=$D13),IF(DATE(2026,9,17)<$C13+ROUND($E13*($D13-$C13+1),0),"█","░"),"")) | N13: =IF($F13="Yes",IF(DATE(2026,9,18)=$C13,"◆",""),IF(AND(DATE(2026,9,18)>=$C13,DATE(2026,9,18)<=$D13),IF(DATE(2026,9,18)<$C13+ROUND($E13*($D13-$C13+1),0),"█","░"),"")) | O13: =IF($F13="Yes",IF(DATE(2026,9,19)=$C13,"◆",""),IF(AND(DATE(2026,9,19)>=$C13,DATE(2026,9,19)<=$D13),IF(DATE(2026,9,19)<$C13+ROUND($E13*($D13-$C13+1),0),"█","░"),"")) | P13: =IF($F13="Yes",IF(DATE(2026,9,20)=$C13,"◆",""),IF(AND(DATE(2026,9,20)>=$C13,DATE(2026,9,20)<=$D13),IF(DATE(2026,9,20)<$C13+ROUND($E13*($D13-$C13+1),0),"█","░"),"")) | Q13: =IF($F13="Yes",IF(DATE(2026,9,21)=$C13,"◆",""),IF(AND(DATE(2026,9,21)>=$C13,DATE(2026,9,21)<=$D13),IF(DATE(2026,9,21)<$C13+ROUND($E13*($D13-$C13+1),0),"█","░"),"")) | R13: =IF($F13="Yes",IF(DATE(2026,9,22)=$C13,"◆",""),IF(AND(DATE(2026,9,22)>=$C13,DATE(2026,9,22)<=$D13),IF(DATE(2026,9,22)<$C13+ROUND($E13*($D13-$C13+1),0),"█","░"),"")) | S13: =IF($F13="Yes",IF(DATE(2026,9,23)=$C13,"◆",""),IF(AND(DATE(2026,9,23)>=$C13,DATE(2026,9,23)<=$D13),IF(DATE(2026,9,23)<$C13+ROUND($E13*($D13-$C13+1),0),"█","░"),"")) | T13: =IF($F13="Yes",IF(DATE(2026,9,24)=$C13,"◆",""),IF(AND(DATE(2026,9,24)>=$C13,DATE(2026,9,24)<=$D13),IF(DATE(2026,9,24)<$C13+ROUND($E13*($D13-$C13+1),0),"█","░"),"")) | U13: =IF($F13="Yes",IF(DATE(2026,9,25)=$C13,"◆",""),IF(AND(DATE(2026,9,25)>=$C13,DATE(2026,9,25)<=$D13),IF(DATE(2026,9,25)<$C13+ROUND($E13*($D13-$C13+1),0),"█","░"),"")) | V13: =IF($F13="Yes",IF(DATE(2026,9,26)=$C13,"◆",""),IF(AND(DATE(2026,9,26)>=$C13,DATE(2026,9,26)<=$D13),IF(DATE(2026,9,26)<$C13+ROUND($E13*($D13-$C13+1),0),"█","░"),"")) | W13: =IF($F13="Yes",IF(DATE(2026,9,27)=$C13,"◆",""),IF(AND(DATE(2026,9,27)>=$C13,DATE(2026,9,27)<=$D13),IF(DATE(2026,9,27)<$C13+ROUND($E13*($D13-$C13+1),0),"█","░"),"")) | X13: =IF($F13="Yes",IF(DATE(2026,9,28)=$C13,"◆",""),IF(AND(DATE(2026,9,28)>=$C13,DATE(2026,9,28)<=$D13),IF(DATE(2026,9,28)<$C13+ROUND($E13*($D13-$C13+1),0),"█","░"),"")) | Y13: =IF($F13="Yes",IF(DATE(2026,9,29)=$C13,"◆",""),IF(AND(DATE(2026,9,29)>=$C13,DATE(2026,9,29)<=$D13),IF(DATE(2026,9,29)<$C13+ROUND($E13*($D13-$C13+1),0),"█","░"),"")) | Z13: =IF($F13="Yes",IF(DATE(2026,9,30)=$C13,"◆",""),IF(AND(DATE(2026,9,30)>=$C13,DATE(2026,9,30)<=$D13),IF(DATE(2026,9,30)<$C13+ROUND($E13*($D13-$C13+1),0),"█","░"),"")) | AA13: =IF($F13="Yes",IF(DATE(2026,10,1)=$C13,"◆",""),IF(AND(DATE(2026,10,1)>=$C13,DATE(2026,10,1)<=$D13),IF(DATE(2026,10,1)<$C13+ROUND($E13*($D13-$C13+1),0),"█","░"),"")) | AB13: =IF($F13="Yes",IF(DATE(2026,10,2)=$C13,"◆",""),IF(AND(DATE(2026,10,2)>=$C13,DATE(2026,10,2)<=$D13),IF(DATE(2026,10,2)<$C13+ROUND($E13*($D13-$C13+1),0),"█","░"),"")) | AC13: =IF($F13="Yes",IF(DATE(2026,10,3)=$C13,"◆",""),IF(AND(DATE(2026,10,3)>=$C13,DATE(2026,10,3)<=$D13),IF(DATE(2026,10,3)<$C13+ROUND($E13*($D13-$C13+1),0),"█","░"),"")) | AD13: =IF($F13="Yes",IF(DATE(2026,10,4)=$C13,"◆",""),IF(AND(DATE(2026,10,4)>=$C13,DATE(2026,10,4)<=$D13),IF(DATE(2026,10,4)<$C13+ROUND($E13*($D13-$C13+1),0),"█","░"),"")) | AE13: =IF($F13="Yes",IF(DATE(2026,10,5)=$C13,"◆",""),IF(AND(DATE(2026,10,5)>=$C13,DATE(2026,10,5)<=$D13),IF(DATE(2026,10,5)<$C13+ROUND($E13*($D13-$C13+1),0),"█","░"),"")) | AF13: =IF($F13="Yes",IF(DATE(2026,10,6)=$C13,"◆",""),IF(AND(DATE(2026,10,6)>=$C13,DATE(2026,10,6)<=$D13),IF(DATE(2026,10,6)<$C13+ROUND($E13*($D13-$C13+1),0),"█","░"),"")) | AG13: =IF($F13="Yes",IF(DATE(2026,10,7)=$C13,"◆",""),IF(AND(DATE(2026,10,7)>=$C13,DATE(2026,10,7)<=$D13),IF(DATE(2026,10,7)<$C13+ROUND($E13*($D13-$C13+1),0),"█","░"),"")) | AH13: =IF($F13="Yes",IF(DATE(2026,10,8)=$C13,"◆",""),IF(AND(DATE(2026,10,8)>=$C13,DATE(2026,10,8)<=$D13),IF(DATE(2026,10,8)<$C13+ROUND($E13*($D13-$C13+1),0),"█","░"),"")) | AI13: =IF($F13="Yes",IF(DATE(2026,10,9)=$C13,"◆",""),IF(AND(DATE(2026,10,9)>=$C13,DATE(2026,10,9)<=$D13),IF(DATE(2026,10,9)<$C13+ROUND($E13*($D13-$C13+1),0),"█","░"),"")) | AJ13: =IF($F13="Yes",IF(DATE(2026,10,10)=$C13,"◆",""),IF(AND(DATE(2026,10,10)>=$C13,DATE(2026,10,10)<=$D13),IF(DATE(2026,10,10)<$C13+ROUND($E13*($D13-$C13+1),0),"█","░"),"")) | AK13: =IF($F13="Yes",IF(DATE(2026,10,11)=$C13,"◆",""),IF(AND(DATE(2026,10,11)>=$C13,DATE(2026,10,11)<=$D13),IF(DATE(2026,10,11)<$C13+ROUND($E13*($D13-$C13+1),0),"█","░"),"")) | AL13: =IF($F13="Yes",IF(DATE(2026,10,12)=$C13,"◆",""),IF(AND(DATE(2026,10,12)>=$C13,DATE(2026,10,12)<=$D13),IF(DATE(2026,10,12)<$C13+ROUND($E13*($D13-$C13+1),0),"█","░"),"")) | AM13: =IF($F13="Yes",IF(DATE(2026,10,13)=$C13,"◆",""),IF(AND(DATE(2026,10,13)>=$C13,DATE(2026,10,13)<=$D13),IF(DATE(2026,10,13)<$C13+ROUND($E13*($D13-$C13+1),0),"█","░"),"")) | AN13: =IF($F13="Yes",IF(DATE(2026,10,14)=$C13,"◆",""),IF(AND(DATE(2026,10,14)>=$C13,DATE(2026,10,14)<=$D13),IF(DATE(2026,10,14)<$C13+ROUND($E13*($D13-$C13+1),0),"█","░"),""))
A14: ='Project Tracker'!A13 | B14: ='Project Tracker'!C13 | C14: ='Project Tracker'!E13 | D14: ='Project Tracker'!F13 | E14: ='Project Tracker'!N13 | F14: ='Project Tracker'!J13 | G14: =IF($F14="Yes",IF(DATE(2026,9,11)=$C14,"◆",""),IF(AND(DATE(2026,9,11)>=$C14,DATE(2026,9,11)<=$D14),IF(DATE(2026,9,11)<$C14+ROUND($E14*($D14-$C14+1),0),"█","░"),"")) | H14: =IF($F14="Yes",IF(DATE(2026,9,12)=$C14,"◆",""),IF(AND(DATE(2026,9,12)>=$C14,DATE(2026,9,12)<=$D14),IF(DATE(2026,9,12)<$C14+ROUND($E14*($D14-$C14+1),0),"█","░"),"")) | I14: =IF($F14="Yes",IF(DATE(2026,9,13)=$C14,"◆",""),IF(AND(DATE(2026,9,13)>=$C14,DATE(2026,9,13)<=$D14),IF(DATE(2026,9,13)<$C14+ROUND($E14*($D14-$C14+1),0),"█","░"),"")) | J14: =IF($F14="Yes",IF(DATE(2026,9,14)=$C14,"◆",""),IF(AND(DATE(2026,9,14)>=$C14,DATE(2026,9,14)<=$D14),IF(DATE(2026,9,14)<$C14+ROUND($E14*($D14-$C14+1),0),"█","░"),"")) | K14: =IF($F14="Yes",IF(DATE(2026,9,15)=$C14,"◆",""),IF(AND(DATE(2026,9,15)>=$C14,DATE(2026,9,15)<=$D14),IF(DATE(2026,9,15)<$C14+ROUND($E14*($D14-$C14+1),0),"█","░"),"")) | L14: =IF($F14="Yes",IF(DATE(2026,9,16)=$C14,"◆",""),IF(AND(DATE(2026,9,16)>=$C14,DATE(2026,9,16)<=$D14),IF(DATE(2026,9,16)<$C14+ROUND($E14*($D14-$C14+1),0),"█","░"),"")) | M14: =IF($F14="Yes",IF(DATE(2026,9,17)=$C14,"◆",""),IF(AND(DATE(2026,9,17)>=$C14,DATE(2026,9,17)<=$D14),IF(DATE(2026,9,17)<$C14+ROUND($E14*($D14-$C14+1),0),"█","░"),"")) | N14: =IF($F14="Yes",IF(DATE(2026,9,18)=$C14,"◆",""),IF(AND(DATE(2026,9,18)>=$C14,DATE(2026,9,18)<=$D14),IF(DATE(2026,9,18)<$C14+ROUND($E14*($D14-$C14+1),0),"█","░"),"")) | O14: =IF($F14="Yes",IF(DATE(2026,9,19)=$C14,"◆",""),IF(AND(DATE(2026,9,19)>=$C14,DATE(2026,9,19)<=$D14),IF(DATE(2026,9,19)<$C14+ROUND($E14*($D14-$C14+1),0),"█","░"),"")) | P14: =IF($F14="Yes",IF(DATE(2026,9,20)=$C14,"◆",""),IF(AND(DATE(2026,9,20)>=$C14,DATE(2026,9,20)<=$D14),IF(DATE(2026,9,20)<$C14+ROUND($E14*($D14-$C14+1),0),"█","░"),"")) | Q14: =IF($F14="Yes",IF(DATE(2026,9,21)=$C14,"◆",""),IF(AND(DATE(2026,9,21)>=$C14,DATE(2026,9,21)<=$D14),IF(DATE(2026,9,21)<$C14+ROUND($E14*($D14-$C14+1),0),"█","░"),"")) | R14: =IF($F14="Yes",IF(DATE(2026,9,22)=$C14,"◆",""),IF(AND(DATE(2026,9,22)>=$C14,DATE(2026,9,22)<=$D14),IF(DATE(2026,9,22)<$C14+ROUND($E14*($D14-$C14+1),0),"█","░"),"")) | S14: =IF($F14="Yes",IF(DATE(2026,9,23)=$C14,"◆",""),IF(AND(DATE(2026,9,23)>=$C14,DATE(2026,9,23)<=$D14),IF(DATE(2026,9,23)<$C14+ROUND($E14*($D14-$C14+1),0),"█","░"),"")) | T14: =IF($F14="Yes",IF(DATE(2026,9,24)=$C14,"◆",""),IF(AND(DATE(2026,9,24)>=$C14,DATE(2026,9,24)<=$D14),IF(DATE(2026,9,24)<$C14+ROUND($E14*($D14-$C14+1),0),"█","░"),"")) | U14: =IF($F14="Yes",IF(DATE(2026,9,25)=$C14,"◆",""),IF(AND(DATE(2026,9,25)>=$C14,DATE(2026,9,25)<=$D14),IF(DATE(2026,9,25)<$C14+ROUND($E14*($D14-$C14+1),0),"█","░"),"")) | V14: =IF($F14="Yes",IF(DATE(2026,9,26)=$C14,"◆",""),IF(AND(DATE(2026,9,26)>=$C14,DATE(2026,9,26)<=$D14),IF(DATE(2026,9,26)<$C14+ROUND($E14*($D14-$C14+1),0),"█","░"),"")) | W14: =IF($F14="Yes",IF(DATE(2026,9,27)=$C14,"◆",""),IF(AND(DATE(2026,9,27)>=$C14,DATE(2026,9,27)<=$D14),IF(DATE(2026,9,27)<$C14+ROUND($E14*($D14-$C14+1),0),"█","░"),"")) | X14: =IF($F14="Yes",IF(DATE(2026,9,28)=$C14,"◆",""),IF(AND(DATE(2026,9,28)>=$C14,DATE(2026,9,28)<=$D14),IF(DATE(2026,9,28)<$C14+ROUND($E14*($D14-$C14+1),0),"█","░"),"")) | Y14: =IF($F14="Yes",IF(DATE(2026,9,29)=$C14,"◆",""),IF(AND(DATE(2026,9,29)>=$C14,DATE(2026,9,29)<=$D14),IF(DATE(2026,9,29)<$C14+ROUND($E14*($D14-$C14+1),0),"█","░"),"")) | Z14: =IF($F14="Yes",IF(DATE(2026,9,30)=$C14,"◆",""),IF(AND(DATE(2026,9,30)>=$C14,DATE(2026,9,30)<=$D14),IF(DATE(2026,9,30)<$C14+ROUND($E14*($D14-$C14+1),0),"█","░"),"")) | AA14: =IF($F14="Yes",IF(DATE(2026,10,1)=$C14,"◆",""),IF(AND(DATE(2026,10,1)>=$C14,DATE(2026,10,1)<=$D14),IF(DATE(2026,10,1)<$C14+ROUND($E14*($D14-$C14+1),0),"█","░"),"")) | AB14: =IF($F14="Yes",IF(DATE(2026,10,2)=$C14,"◆",""),IF(AND(DATE(2026,10,2)>=$C14,DATE(2026,10,2)<=$D14),IF(DATE(2026,10,2)<$C14+ROUND($E14*($D14-$C14+1),0),"█","░"),"")) | AC14: =IF($F14="Yes",IF(DATE(2026,10,3)=$C14,"◆",""),IF(AND(DATE(2026,10,3)>=$C14,DATE(2026,10,3)<=$D14),IF(DATE(2026,10,3)<$C14+ROUND($E14*($D14-$C14+1),0),"█","░"),"")) | AD14: =IF($F14="Yes",IF(DATE(2026,10,4)=$C14,"◆",""),IF(AND(DATE(2026,10,4)>=$C14,DATE(2026,10,4)<=$D14),IF(DATE(2026,10,4)<$C14+ROUND($E14*($D14-$C14+1),0),"█","░"),"")) | AE14: =IF($F14="Yes",IF(DATE(2026,10,5)=$C14,"◆",""),IF(AND(DATE(2026,10,5)>=$C14,DATE(2026,10,5)<=$D14),IF(DATE(2026,10,5)<$C14+ROUND($E14*($D14-$C14+1),0),"█","░"),"")) | AF14: =IF($F14="Yes",IF(DATE(2026,10,6)=$C14,"◆",""),IF(AND(DATE(2026,10,6)>=$C14,DATE(2026,10,6)<=$D14),IF(DATE(2026,10,6)<$C14+ROUND($E14*($D14-$C14+1),0),"█","░"),"")) | AG14: =IF($F14="Yes",IF(DATE(2026,10,7)=$C14,"◆",""),IF(AND(DATE(2026,10,7)>=$C14,DATE(2026,10,7)<=$D14),IF(DATE(2026,10,7)<$C14+ROUND($E14*($D14-$C14+1),0),"█","░"),"")) | AH14: =IF($F14="Yes",IF(DATE(2026,10,8)=$C14,"◆",""),IF(AND(DATE(2026,10,8)>=$C14,DATE(2026,10,8)<=$D14),IF(DATE(2026,10,8)<$C14+ROUND($E14*($D14-$C14+1),0),"█","░"),"")) | AI14: =IF($F14="Yes",IF(DATE(2026,10,9)=$C14,"◆",""),IF(AND(DATE(2026,10,9)>=$C14,DATE(2026,10,9)<=$D14),IF(DATE(2026,10,9)<$C14+ROUND($E14*($D14-$C14+1),0),"█","░"),"")) | AJ14: =IF($F14="Yes",IF(DATE(2026,10,10)=$C14,"◆",""),IF(AND(DATE(2026,10,10)>=$C14,DATE(2026,10,10)<=$D14),IF(DATE(2026,10,10)<$C14+ROUND($E14*($D14-$C14+1),0),"█","░"),"")) | AK14: =IF($F14="Yes",IF(DATE(2026,10,11)=$C14,"◆",""),IF(AND(DATE(2026,10,11)>=$C14,DATE(2026,10,11)<=$D14),IF(DATE(2026,10,11)<$C14+ROUND($E14*($D14-$C14+1),0),"█","░"),"")) | AL14: =IF($F14="Yes",IF(DATE(2026,10,12)=$C14,"◆",""),IF(AND(DATE(2026,10,12)>=$C14,DATE(2026,10,12)<=$D14),IF(DATE(2026,10,12)<$C14+ROUND($E14*($D14-$C14+1),0),"█","░"),"")) | AM14: =IF($F14="Yes",IF(DATE(2026,10,13)=$C14,"◆",""),IF(AND(DATE(2026,10,13)>=$C14,DATE(2026,10,13)<=$D14),IF(DATE(2026,10,13)<$C14+ROUND($E14*($D14-$C14+1),0),"█","░"),"")) | AN14: =IF($F14="Yes",IF(DATE(2026,10,14)=$C14,"◆",""),IF(AND(DATE(2026,10,14)>=$C14,DATE(2026,10,14)<=$D14),IF(DATE(2026,10,14)<$C14+ROUND($E14*($D14-$C14+1),0),"█","░"),""))
A15: ='Project Tracker'!A14 | B15: ='Project Tracker'!C14 | C15: ='Project Tracker'!E14 | D15: ='Project Tracker'!F14 | E15: ='Project Tracker'!N14 | F15: ='Project Tracker'!J14 | G15: =IF($F15="Yes",IF(DATE(2026,9,11)=$C15,"◆",""),IF(AND(DATE(2026,9,11)>=$C15,DATE(2026,9,11)<=$D15),IF(DATE(2026,9,11)<$C15+ROUND($E15*($D15-$C15+1),0),"█","░"),"")) | H15: =IF($F15="Yes",IF(DATE(2026,9,12)=$C15,"◆",""),IF(AND(DATE(2026,9,12)>=$C15,DATE(2026,9,12)<=$D15),IF(DATE(2026,9,12)<$C15+ROUND($E15*($D15-$C15+1),0),"█","░"),"")) | I15: =IF($F15="Yes",IF(DATE(2026,9,13)=$C15,"◆",""),IF(AND(DATE(2026,9,13)>=$C15,DATE(2026,9,13)<=$D15),IF(DATE(2026,9,13)<$C15+ROUND($E15*($D15-$C15+1),0),"█","░"),"")) | J15: =IF($F15="Yes",IF(DATE(2026,9,14)=$C15,"◆",""),IF(AND(DATE(2026,9,14)>=$C15,DATE(2026,9,14)<=$D15),IF(DATE(2026,9,14)<$C15+ROUND($E15*($D15-$C15+1),0),"█","░"),"")) | K15: =IF($F15="Yes",IF(DATE(2026,9,15)=$C15,"◆",""),IF(AND(DATE(2026,9,15)>=$C15,DATE(2026,9,15)<=$D15),IF(DATE(2026,9,15)<$C15+ROUND($E15*($D15-$C15+1),0),"█","░"),"")) | L15: =IF($F15="Yes",IF(DATE(2026,9,16)=$C15,"◆",""),IF(AND(DATE(2026,9,16)>=$C15,DATE(2026,9,16)<=$D15),IF(DATE(2026,9,16)<$C15+ROUND($E15*($D15-$C15+1),0),"█","░"),"")) | M15: =IF($F15="Yes",IF(DATE(2026,9,17)=$C15,"◆",""),IF(AND(DATE(2026,9,17)>=$C15,DATE(2026,9,17)<=$D15),IF(DATE(2026,9,17)<$C15+ROUND($E15*($D15-$C15+1),0),"█","░"),"")) | N15: =IF($F15="Yes",IF(DATE(2026,9,18)=$C15,"◆",""),IF(AND(DATE(2026,9,18)>=$C15,DATE(2026,9,18)<=$D15),IF(DATE(2026,9,18)<$C15+ROUND($E15*($D15-$C15+1),0),"█","░"),"")) | O15: =IF($F15="Yes",IF(DATE(2026,9,19)=$C15,"◆",""),IF(AND(DATE(2026,9,19)>=$C15,DATE(2026,9,19)<=$D15),IF(DATE(2026,9,19)<$C15+ROUND($E15*($D15-$C15+1),0),"█","░"),"")) | P15: =IF($F15="Yes",IF(DATE(2026,9,20)=$C15,"◆",""),IF(AND(DATE(2026,9,20)>=$C15,DATE(2026,9,20)<=$D15),IF(DATE(2026,9,20)<$C15+ROUND($E15*($D15-$C15+1),0),"█","░"),"")) | Q15: =IF($F15="Yes",IF(DATE(2026,9,21)=$C15,"◆",""),IF(AND(DATE(2026,9,21)>=$C15,DATE(2026,9,21)<=$D15),IF(DATE(2026,9,21)<$C15+ROUND($E15*($D15-$C15+1),0),"█","░"),"")) | R15: =IF($F15="Yes",IF(DATE(2026,9,22)=$C15,"◆",""),IF(AND(DATE(2026,9,22)>=$C15,DATE(2026,9,22)<=$D15),IF(DATE(2026,9,22)<$C15+ROUND($E15*($D15-$C15+1),0),"█","░"),"")) | S15: =IF($F15="Yes",IF(DATE(2026,9,23)=$C15,"◆",""),IF(AND(DATE(2026,9,23)>=$C15,DATE(2026,9,23)<=$D15),IF(DATE(2026,9,23)<$C15+ROUND($E15*($D15-$C15+1),0),"█","░"),"")) | T15: =IF($F15="Yes",IF(DATE(2026,9,24)=$C15,"◆",""),IF(AND(DATE(2026,9,24)>=$C15,DATE(2026,9,24)<=$D15),IF(DATE(2026,9,24)<$C15+ROUND($E15*($D15-$C15+1),0),"█","░"),"")) | U15: =IF($F15="Yes",IF(DATE(2026,9,25)=$C15,"◆",""),IF(AND(DATE(2026,9,25)>=$C15,DATE(2026,9,25)<=$D15),IF(DATE(2026,9,25)<$C15+ROUND($E15*($D15-$C15+1),0),"█","░"),"")) | V15: =IF($F15="Yes",IF(DATE(2026,9,26)=$C15,"◆",""),IF(AND(DATE(2026,9,26)>=$C15,DATE(2026,9,26)<=$D15),IF(DATE(2026,9,26)<$C15+ROUND($E15*($D15-$C15+1),0),"█","░"),"")) | W15: =IF($F15="Yes",IF(DATE(2026,9,27)=$C15,"◆",""),IF(AND(DATE(2026,9,27)>=$C15,DATE(2026,9,27)<=$D15),IF(DATE(2026,9,27)<$C15+ROUND($E15*($D15-$C15+1),0),"█","░"),"")) | X15: =IF($F15="Yes",IF(DATE(2026,9,28)=$C15,"◆",""),IF(AND(DATE(2026,9,28)>=$C15,DATE(2026,9,28)<=$D15),IF(DATE(2026,9,28)<$C15+ROUND($E15*($D15-$C15+1),0),"█","░"),"")) | Y15: =IF($F15="Yes",IF(DATE(2026,9,29)=$C15,"◆",""),IF(AND(DATE(2026,9,29)>=$C15,DATE(2026,9,29)<=$D15),IF(DATE(2026,9,29)<$C15+ROUND($E15*($D15-$C15+1),0),"█","░"),"")) | Z15: =IF($F15="Yes",IF(DATE(2026,9,30)=$C15,"◆",""),IF(AND(DATE(2026,9,30)>=$C15,DATE(2026,9,30)<=$D15),IF(DATE(2026,9,30)<$C15+ROUND($E15*($D15-$C15+1),0),"█","░"),"")) | AA15: =IF($F15="Yes",IF(DATE(2026,10,1)=$C15,"◆",""),IF(AND(DATE(2026,10,1)>=$C15,DATE(2026,10,1)<=$D15),IF(DATE(2026,10,1)<$C15+ROUND($E15*($D15-$C15+1),0),"█","░"),"")) | AB15: =IF($F15="Yes",IF(DATE(2026,10,2)=$C15,"◆",""),IF(AND(DATE(2026,10,2)>=$C15,DATE(2026,10,2)<=$D15),IF(DATE(2026,10,2)<$C15+ROUND($E15*($D15-$C15+1),0),"█","░"),"")) | AC15: =IF($F15="Yes",IF(DATE(2026,10,3)=$C15,"◆",""),IF(AND(DATE(2026,10,3)>=$C15,DATE(2026,10,3)<=$D15),IF(DATE(2026,10,3)<$C15+ROUND($E15*($D15-$C15+1),0),"█","░"),"")) | AD15: =IF($F15="Yes",IF(DATE(2026,10,4)=$C15,"◆",""),IF(AND(DATE(2026,10,4)>=$C15,DATE(2026,10,4)<=$D15),IF(DATE(2026,10,4)<$C15+ROUND($E15*($D15-$C15+1),0),"█","░"),"")) | AE15: =IF($F15="Yes",IF(DATE(2026,10,5)=$C15,"◆",""),IF(AND(DATE(2026,10,5)>=$C15,DATE(2026,10,5)<=$D15),IF(DATE(2026,10,5)<$C15+ROUND($E15*($D15-$C15+1),0),"█","░"),"")) | AF15: =IF($F15="Yes",IF(DATE(2026,10,6)=$C15,"◆",""),IF(AND(DATE(2026,10,6)>=$C15,DATE(2026,10,6)<=$D15),IF(DATE(2026,10,6)<$C15+ROUND($E15*($D15-$C15+1),0),"█","░"),"")) | AG15: =IF($F15="Yes",IF(DATE(2026,10,7)=$C15,"◆",""),IF(AND(DATE(2026,10,7)>=$C15,DATE(2026,10,7)<=$D15),IF(DATE(2026,10,7)<$C15+ROUND($E15*($D15-$C15+1),0),"█","░"),"")) | AH15: =IF($F15="Yes",IF(DATE(2026,10,8)=$C15,"◆",""),IF(AND(DATE(2026,10,8)>=$C15,DATE(2026,10,8)<=$D15),IF(DATE(2026,10,8)<$C15+ROUND($E15*($D15-$C15+1),0),"█","░"),"")) | AI15: =IF($F15="Yes",IF(DATE(2026,10,9)=$C15,"◆",""),IF(AND(DATE(2026,10,9)>=$C15,DATE(2026,10,9)<=$D15),IF(DATE(2026,10,9)<$C15+ROUND($E15*($D15-$C15+1),0),"█","░"),"")) | AJ15: =IF($F15="Yes",IF(DATE(2026,10,10)=$C15,"◆",""),IF(AND(DATE(2026,10,10)>=$C15,DATE(2026,10,10)<=$D15),IF(DATE(2026,10,10)<$C15+ROUND($E15*($D15-$C15+1),0),"█","░"),"")) | AK15: =IF($F15="Yes",IF(DATE(2026,10,11)=$C15,"◆",""),IF(AND(DATE(2026,10,11)>=$C15,DATE(2026,10,11)<=$D15),IF(DATE(2026,10,11)<$C15+ROUND($E15*($D15-$C15+1),0),"█","░"),"")) | AL15: =IF($F15="Yes",IF(DATE(2026,10,12)=$C15,"◆",""),IF(AND(DATE(2026,10,12)>=$C15,DATE(2026,10,12)<=$D15),IF(DATE(2026,10,12)<$C15+ROUND($E15*($D15-$C15+1),0),"█","░"),"")) | AM15: =IF($F15="Yes",IF(DATE(2026,10,13)=$C15,"◆",""),IF(AND(DATE(2026,10,13)>=$C15,DATE(2026,10,13)<=$D15),IF(DATE(2026,10,13)<$C15+ROUND($E15*($D15-$C15+1),0),"█","░"),"")) | AN15: =IF($F15="Yes",IF(DATE(2026,10,14)=$C15,"◆",""),IF(AND(DATE(2026,10,14)>=$C15,DATE(2026,10,14)<=$D15),IF(DATE(2026,10,14)<$C15+ROUND($E15*($D15-$C15+1),0),"█","░"),""))
A16: ='Project Tracker'!A15 | B16: ='Project Tracker'!C15 | C16: ='Project Tracker'!E15 | D16: ='Project Tracker'!F15 | E16: ='Project Tracker'!N15 | F16: ='Project Tracker'!J15 | G16: =IF($F16="Yes",IF(DATE(2026,9,11)=$C16,"◆",""),IF(AND(DATE(2026,9,11)>=$C16,DATE(2026,9,11)<=$D16),IF(DATE(2026,9,11)<$C16+ROUND($E16*($D16-$C16+1),0),"█","░"),"")) | H16: =IF($F16="Yes",IF(DATE(2026,9,12)=$C16,"◆",""),IF(AND(DATE(2026,9,12)>=$C16,DATE(2026,9,12)<=$D16),IF(DATE(2026,9,12)<$C16+ROUND($E16*($D16-$C16+1),0),"█","░"),"")) | I16: =IF($F16="Yes",IF(DATE(2026,9,13)=$C16,"◆",""),IF(AND(DATE(2026,9,13)>=$C16,DATE(2026,9,13)<=$D16),IF(DATE(2026,9,13)<$C16+ROUND($E16*($D16-$C16+1),0),"█","░"),"")) | J16: =IF($F16="Yes",IF(DATE(2026,9,14)=$C16,"◆",""),IF(AND(DATE(2026,9,14)>=$C16,DATE(2026,9,14)<=$D16),IF(DATE(2026,9,14)<$C16+ROUND($E16*($D16-$C16+1),0),"█","░"),"")) | K16: =IF($F16="Yes",IF(DATE(2026,9,15)=$C16,"◆",""),IF(AND(DATE(2026,9,15)>=$C16,DATE(2026,9,15)<=$D16),IF(DATE(2026,9,15)<$C16+ROUND($E16*($D16-$C16+1),0),"█","░"),"")) | L16: =IF($F16="Yes",IF(DATE(2026,9,16)=$C16,"◆",""),IF(AND(DATE(2026,9,16)>=$C16,DATE(2026,9,16)<=$D16),IF(DATE(2026,9,16)<$C16+ROUND($E16*($D16-$C16+1),0),"█","░"),"")) | M16: =IF($F16="Yes",IF(DATE(2026,9,17)=$C16,"◆",""),IF(AND(DATE(2026,9,17)>=$C16,DATE(2026,9,17)<=$D16),IF(DATE(2026,9,17)<$C16+ROUND($E16*($D16-$C16+1),0),"█","░"),"")) | N16: =IF($F16="Yes",IF(DATE(2026,9,18)=$C16,"◆",""),IF(AND(DATE(2026,9,18)>=$C16,DATE(2026,9,18)<=$D16),IF(DATE(2026,9,18)<$C16+ROUND($E16*($D16-$C16+1),0),"█","░"),"")) | O16: =IF($F16="Yes",IF(DATE(2026,9,19)=$C16,"◆",""),IF(AND(DATE(2026,9,19)>=$C16,DATE(2026,9,19)<=$D16),IF(DATE(2026,9,19)<$C16+ROUND($E16*($D16-$C16+1),0),"█","░"),"")) | P16: =IF($F16="Yes",IF(DATE(2026,9,20)=$C16,"◆",""),IF(AND(DATE(2026,9,20)>=$C16,DATE(2026,9,20)<=$D16),IF(DATE(2026,9,20)<$C16+ROUND($E16*($D16-$C16+1),0),"█","░"),"")) | Q16: =IF($F16="Yes",IF(DATE(2026,9,21)=$C16,"◆",""),IF(AND(DATE(2026,9,21)>=$C16,DATE(2026,9,21)<=$D16),IF(DATE(2026,9,21)<$C16+ROUND($E16*($D16-$C16+1),0),"█","░"),"")) | R16: =IF($F16="Yes",IF(DATE(2026,9,22)=$C16,"◆",""),IF(AND(DATE(2026,9,22)>=$C16,DATE(2026,9,22)<=$D16),IF(DATE(2026,9,22)<$C16+ROUND($E16*($D16-$C16+1),0),"█","░"),"")) | S16: =IF($F16="Yes",IF(DATE(2026,9,23)=$C16,"◆",""),IF(AND(DATE(2026,9,23)>=$C16,DATE(2026,9,23)<=$D16),IF(DATE(2026,9,23)<$C16+ROUND($E16*($D16-$C16+1),0),"█","░"),"")) | T16: =IF($F16="Yes",IF(DATE(2026,9,24)=$C16,"◆",""),IF(AND(DATE(2026,9,24)>=$C16,DATE(2026,9,24)<=$D16),IF(DATE(2026,9,24)<$C16+ROUND($E16*($D16-$C16+1),0),"█","░"),"")) | U16: =IF($F16="Yes",IF(DATE(2026,9,25)=$C16,"◆",""),IF(AND(DATE(2026,9,25)>=$C16,DATE(2026,9,25)<=$D16),IF(DATE(2026,9,25)<$C16+ROUND($E16*($D16-$C16+1),0),"█","░"),"")) | V16: =IF($F16="Yes",IF(DATE(2026,9,26)=$C16,"◆",""),IF(AND(DATE(2026,9,26)>=$C16,DATE(2026,9,26)<=$D16),IF(DATE(2026,9,26)<$C16+ROUND($E16*($D16-$C16+1),0),"█","░"),"")) | W16: =IF($F16="Yes",IF(DATE(2026,9,27)=$C16,"◆",""),IF(AND(DATE(2026,9,27)>=$C16,DATE(2026,9,27)<=$D16),IF(DATE(2026,9,27)<$C16+ROUND($E16*($D16-$C16+1),0),"█","░"),"")) | X16: =IF($F16="Yes",IF(DATE(2026,9,28)=$C16,"◆",""),IF(AND(DATE(2026,9,28)>=$C16,DATE(2026,9,28)<=$D16),IF(DATE(2026,9,28)<$C16+ROUND($E16*($D16-$C16+1),0),"█","░"),"")) | Y16: =IF($F16="Yes",IF(DATE(2026,9,29)=$C16,"◆",""),IF(AND(DATE(2026,9,29)>=$C16,DATE(2026,9,29)<=$D16),IF(DATE(2026,9,29)<$C16+ROUND($E16*($D16-$C16+1),0),"█","░"),"")) | Z16: =IF($F16="Yes",IF(DATE(2026,9,30)=$C16,"◆",""),IF(AND(DATE(2026,9,30)>=$C16,DATE(2026,9,30)<=$D16),IF(DATE(2026,9,30)<$C16+ROUND($E16*($D16-$C16+1),0),"█","░"),"")) | AA16: =IF($F16="Yes",IF(DATE(2026,10,1)=$C16,"◆",""),IF(AND(DATE(2026,10,1)>=$C16,DATE(2026,10,1)<=$D16),IF(DATE(2026,10,1)<$C16+ROUND($E16*($D16-$C16+1),0),"█","░"),"")) | AB16: =IF($F16="Yes",IF(DATE(2026,10,2)=$C16,"◆",""),IF(AND(DATE(2026,10,2)>=$C16,DATE(2026,10,2)<=$D16),IF(DATE(2026,10,2)<$C16+ROUND($E16*($D16-$C16+1),0),"█","░"),"")) | AC16: =IF($F16="Yes",IF(DATE(2026,10,3)=$C16,"◆",""),IF(AND(DATE(2026,10,3)>=$C16,DATE(2026,10,3)<=$D16),IF(DATE(2026,10,3)<$C16+ROUND($E16*($D16-$C16+1),0),"█","░"),"")) | AD16: =IF($F16="Yes",IF(DATE(2026,10,4)=$C16,"◆",""),IF(AND(DATE(2026,10,4)>=$C16,DATE(2026,10,4)<=$D16),IF(DATE(2026,10,4)<$C16+ROUND($E16*($D16-$C16+1),0),"█","░"),"")) | AE16: =IF($F16="Yes",IF(DATE(2026,10,5)=$C16,"◆",""),IF(AND(DATE(2026,10,5)>=$C16,DATE(2026,10,5)<=$D16),IF(DATE(2026,10,5)<$C16+ROUND($E16*($D16-$C16+1),0),"█","░"),"")) | AF16: =IF($F16="Yes",IF(DATE(2026,10,6)=$C16,"◆",""),IF(AND(DATE(2026,10,6)>=$C16,DATE(2026,10,6)<=$D16),IF(DATE(2026,10,6)<$C16+ROUND($E16*($D16-$C16+1),0),"█","░"),"")) | AG16: =IF($F16="Yes",IF(DATE(2026,10,7)=$C16,"◆",""),IF(AND(DATE(2026,10,7)>=$C16,DATE(2026,10,7)<=$D16),IF(DATE(2026,10,7)<$C16+ROUND($E16*($D16-$C16+1),0),"█","░"),"")) | AH16: =IF($F16="Yes",IF(DATE(2026,10,8)=$C16,"◆",""),IF(AND(DATE(2026,10,8)>=$C16,DATE(2026,10,8)<=$D16),IF(DATE(2026,10,8)<$C16+ROUND($E16*($D16-$C16+1),0),"█","░"),"")) | AI16: =IF($F16="Yes",IF(DATE(2026,10,9)=$C16,"◆",""),IF(AND(DATE(2026,10,9)>=$C16,DATE(2026,10,9)<=$D16),IF(DATE(2026,10,9)<$C16+ROUND($E16*($D16-$C16+1),0),"█","░"),"")) | AJ16: =IF($F16="Yes",IF(DATE(2026,10,10)=$C16,"◆",""),IF(AND(DATE(2026,10,10)>=$C16,DATE(2026,10,10)<=$D16),IF(DATE(2026,10,10)<$C16+ROUND($E16*($D16-$C16+1),0),"█","░"),"")) | AK16: =IF($F16="Yes",IF(DATE(2026,10,11)=$C16,"◆",""),IF(AND(DATE(2026,10,11)>=$C16,DATE(2026,10,11)<=$D16),IF(DATE(2026,10,11)<$C16+ROUND($E16*($D16-$C16+1),0),"█","░"),"")) | AL16: =IF($F16="Yes",IF(DATE(2026,10,12)=$C16,"◆",""),IF(AND(DATE(2026,10,12)>=$C16,DATE(2026,10,12)<=$D16),IF(DATE(2026,10,12)<$C16+ROUND($E16*($D16-$C16+1),0),"█","░"),"")) | AM16: =IF($F16="Yes",IF(DATE(2026,10,13)=$C16,"◆",""),IF(AND(DATE(2026,10,13)>=$C16,DATE(2026,10,13)<=$D16),IF(DATE(2026,10,13)<$C16+ROUND($E16*($D16-$C16+1),0),"█","░"),"")) | AN16: =IF($F16="Yes",IF(DATE(2026,10,14)=$C16,"◆",""),IF(AND(DATE(2026,10,14)>=$C16,DATE(2026,10,14)<=$D16),IF(DATE(2026,10,14)<$C16+ROUND($E16*($D16-$C16+1),0),"█","░"),""))
A17: ='Project Tracker'!A16 | B17: ='Project Tracker'!C16 | C17: ='Project Tracker'!E16 | D17: ='Project Tracker'!F16 | E17: ='Project Tracker'!N16 | F17: ='Project Tracker'!J16 | G17: =IF($F17="Yes",IF(DATE(2026,9,11)=$C17,"◆",""),IF(AND(DATE(2026,9,11)>=$C17,DATE(2026,9,11)<=$D17),IF(DATE(2026,9,11)<$C17+ROUND($E17*($D17-$C17+1),0),"█","░"),"")) | H17: =IF($F17="Yes",IF(DATE(2026,9,12)=$C17,"◆",""),IF(AND(DATE(2026,9,12)>=$C17,DATE(2026,9,12)<=$D17),IF(DATE(2026,9,12)<$C17+ROUND($E17*($D17-$C17+1),0),"█","░"),"")) | I17: =IF($F17="Yes",IF(DATE(2026,9,13)=$C17,"◆",""),IF(AND(DATE(2026,9,13)>=$C17,DATE(2026,9,13)<=$D17),IF(DATE(2026,9,13)<$C17+ROUND($E17*($D17-$C17+1),0),"█","░"),"")) | J17: =IF($F17="Yes",IF(DATE(2026,9,14)=$C17,"◆",""),IF(AND(DATE(2026,9,14)>=$C17,DATE(2026,9,14)<=$D17),IF(DATE(2026,9,14)<$C17+ROUND($E17*($D17-$C17+1),0),"█","░"),"")) | K17: =IF($F17="Yes",IF(DATE(2026,9,15)=$C17,"◆",""),IF(AND(DATE(2026,9,15)>=$C17,DATE(2026,9,15)<=$D17),IF(DATE(2026,9,15)<$C17+ROUND($E17*($D17-$C17+1),0),"█","░"),"")) | L17: =IF($F17="Yes",IF(DATE(2026,9,16)=$C17,"◆",""),IF(AND(DATE(2026,9,16)>=$C17,DATE(2026,9,16)<=$D17),IF(DATE(2026,9,16)<$C17+ROUND($E17*($D17-$C17+1),0),"█","░"),"")) | M17: =IF($F17="Yes",IF(DATE(2026,9,17)=$C17,"◆",""),IF(AND(DATE(2026,9,17)>=$C17,DATE(2026,9,17)<=$D17),IF(DATE(2026,9,17)<$C17+ROUND($E17*($D17-$C17+1),0),"█","░"),"")) | N17: =IF($F17="Yes",IF(DATE(2026,9,18)=$C17,"◆",""),IF(AND(DATE(2026,9,18)>=$C17,DATE(2026,9,18)<=$D17),IF(DATE(2026,9,18)<$C17+ROUND($E17*($D17-$C17+1),0),"█","░"),"")) | O17: =IF($F17="Yes",IF(DATE(2026,9,19)=$C17,"◆",""),IF(AND(DATE(2026,9,19)>=$C17,DATE(2026,9,19)<=$D17),IF(DATE(2026,9,19)<$C17+ROUND($E17*($D17-$C17+1),0),"█","░"),"")) | P17: =IF($F17="Yes",IF(DATE(2026,9,20)=$C17,"◆",""),IF(AND(DATE(2026,9,20)>=$C17,DATE(2026,9,20)<=$D17),IF(DATE(2026,9,20)<$C17+ROUND($E17*($D17-$C17+1),0),"█","░"),"")) | Q17: =IF($F17="Yes",IF(DATE(2026,9,21)=$C17,"◆",""),IF(AND(DATE(2026,9,21)>=$C17,DATE(2026,9,21)<=$D17),IF(DATE(2026,9,21)<$C17+ROUND($E17*($D17-$C17+1),0),"█","░"),"")) | R17: =IF($F17="Yes",IF(DATE(2026,9,22)=$C17,"◆",""),IF(AND(DATE(2026,9,22)>=$C17,DATE(2026,9,22)<=$D17),IF(DATE(2026,9,22)<$C17+ROUND($E17*($D17-$C17+1),0),"█","░"),"")) | S17: =IF($F17="Yes",IF(DATE(2026,9,23)=$C17,"◆",""),IF(AND(DATE(2026,9,23)>=$C17,DATE(2026,9,23)<=$D17),IF(DATE(2026,9,23)<$C17+ROUND($E17*($D17-$C17+1),0),"█","░"),"")) | T17: =IF($F17="Yes",IF(DATE(2026,9,24)=$C17,"◆",""),IF(AND(DATE(2026,9,24)>=$C17,DATE(2026,9,24)<=$D17),IF(DATE(2026,9,24)<$C17+ROUND($E17*($D17-$C17+1),0),"█","░"),"")) | U17: =IF($F17="Yes",IF(DATE(2026,9,25)=$C17,"◆",""),IF(AND(DATE(2026,9,25)>=$C17,DATE(2026,9,25)<=$D17),IF(DATE(2026,9,25)<$C17+ROUND($E17*($D17-$C17+1),0),"█","░"),"")) | V17: =IF($F17="Yes",IF(DATE(2026,9,26)=$C17,"◆",""),IF(AND(DATE(2026,9,26)>=$C17,DATE(2026,9,26)<=$D17),IF(DATE(2026,9,26)<$C17+ROUND($E17*($D17-$C17+1),0),"█","░"),"")) | W17: =IF($F17="Yes",IF(DATE(2026,9,27)=$C17,"◆",""),IF(AND(DATE(2026,9,27)>=$C17,DATE(2026,9,27)<=$D17),IF(DATE(2026,9,27)<$C17+ROUND($E17*($D17-$C17+1),0),"█","░"),"")) | X17: =IF($F17="Yes",IF(DATE(2026,9,28)=$C17,"◆",""),IF(AND(DATE(2026,9,28)>=$C17,DATE(2026,9,28)<=$D17),IF(DATE(2026,9,28)<$C17+ROUND($E17*($D17-$C17+1),0),"█","░"),"")) | Y17: =IF($F17="Yes",IF(DATE(2026,9,29)=$C17,"◆",""),IF(AND(DATE(2026,9,29)>=$C17,DATE(2026,9,29)<=$D17),IF(DATE(2026,9,29)<$C17+ROUND($E17*($D17-$C17+1),0),"█","░"),"")) | Z17: =IF($F17="Yes",IF(DATE(2026,9,30)=$C17,"◆",""),IF(AND(DATE(2026,9,30)>=$C17,DATE(2026,9,30)<=$D17),IF(DATE(2026,9,30)<$C17+ROUND($E17*($D17-$C17+1),0),"█","░"),"")) | AA17: =IF($F17="Yes",IF(DATE(2026,10,1)=$C17,"◆",""),IF(AND(DATE(2026,10,1)>=$C17,DATE(2026,10,1)<=$D17),IF(DATE(2026,10,1)<$C17+ROUND($E17*($D17-$C17+1),0),"█","░"),"")) | AB17: =IF($F17="Yes",IF(DATE(2026,10,2)=$C17,"◆",""),IF(AND(DATE(2026,10,2)>=$C17,DATE(2026,10,2)<=$D17),IF(DATE(2026,10,2)<$C17+ROUND($E17*($D17-$C17+1),0),"█","░"),"")) | AC17: =IF($F17="Yes",IF(DATE(2026,10,3)=$C17,"◆",""),IF(AND(DATE(2026,10,3)>=$C17,DATE(2026,10,3)<=$D17),IF(DATE(2026,10,3)<$C17+ROUND($E17*($D17-$C17+1),0),"█","░"),"")) | AD17: =IF($F17="Yes",IF(DATE(2026,10,4)=$C17,"◆",""),IF(AND(DATE(2026,10,4)>=$C17,DATE(2026,10,4)<=$D17),IF(DATE(2026,10,4)<$C17+ROUND($E17*($D17-$C17+1),0),"█","░"),"")) | AE17: =IF($F17="Yes",IF(DATE(2026,10,5)=$C17,"◆",""),IF(AND(DATE(2026,10,5)>=$C17,DATE(2026,10,5)<=$D17),IF(DATE(2026,10,5)<$C17+ROUND($E17*($D17-$C17+1),0),"█","░"),"")) | AF17: =IF($F17="Yes",IF(DATE(2026,10,6)=$C17,"◆",""),IF(AND(DATE(2026,10,6)>=$C17,DATE(2026,10,6)<=$D17),IF(DATE(2026,10,6)<$C17+ROUND($E17*($D17-$C17+1),0),"█","░"),"")) | AG17: =IF($F17="Yes",IF(DATE(2026,10,7)=$C17,"◆",""),IF(AND(DATE(2026,10,7)>=$C17,DATE(2026,10,7)<=$D17),IF(DATE(2026,10,7)<$C17+ROUND($E17*($D17-$C17+1),0),"█","░"),"")) | AH17: =IF($F17="Yes",IF(DATE(2026,10,8)=$C17,"◆",""),IF(AND(DATE(2026,10,8)>=$C17,DATE(2026,10,8)<=$D17),IF(DATE(2026,10,8)<$C17+ROUND($E17*($D17-$C17+1),0),"█","░"),"")) | AI17: =IF($F17="Yes",IF(DATE(2026,10,9)=$C17,"◆",""),IF(AND(DATE(2026,10,9)>=$C17,DATE(2026,10,9)<=$D17),IF(DATE(2026,10,9)<$C17+ROUND($E17*($D17-$C17+1),0),"█","░"),"")) | AJ17: =IF($F17="Yes",IF(DATE(2026,10,10)=$C17,"◆",""),IF(AND(DATE(2026,10,10)>=$C17,DATE(2026,10,10)<=$D17),IF(DATE(2026,10,10)<$C17+ROUND($E17*($D17-$C17+1),0),"█","░"),"")) | AK17: =IF($F17="Yes",IF(DATE(2026,10,11)=$C17,"◆",""),IF(AND(DATE(2026,10,11)>=$C17,DATE(2026,10,11)<=$D17),IF(DATE(2026,10,11)<$C17+ROUND($E17*($D17-$C17+1),0),"█","░"),"")) | AL17: =IF($F17="Yes",IF(DATE(2026,10,12)=$C17,"◆",""),IF(AND(DATE(2026,10,12)>=$C17,DATE(2026,10,12)<=$D17),IF(DATE(2026,10,12)<$C17+ROUND($E17*($D17-$C17+1),0),"█","░"),"")) | AM17: =IF($F17="Yes",IF(DATE(2026,10,13)=$C17,"◆",""),IF(AND(DATE(2026,10,13)>=$C17,DATE(2026,10,13)<=$D17),IF(DATE(2026,10,13)<$C17+ROUND($E17*($D17-$C17+1),0),"█","░"),"")) | AN17: =IF($F17="Yes",IF(DATE(2026,10,14)=$C17,"◆",""),IF(AND(DATE(2026,10,14)>=$C17,DATE(2026,10,14)<=$D17),IF(DATE(2026,10,14)<$C17+ROUND($E17*($D17-$C17+1),0),"█","░"),""))
... A46: ='Project Tracker'!A45 | B46: ='Project Tracker'!C45 | C46: ='Project Tracker'!E45 | D46: ='Project Tracker'!F45 | E46: ='Project Tracker'!N45 | F46: ='Project Tracker'!J45 | G46: =IF($F46="Yes",IF(DATE(2026,9,11)=$C46,"◆",""),IF(AND(DATE(2026,9,11)>=$C46,DATE(2026,9,11)<=$D46),IF(DATE(2026,9,11)<$C46+ROUND($E46*($D46-$C46+1),0),"█","░"),"")) | H46: =IF($F46="Yes",IF(DATE(2026,9,12)=$C46,"◆",""),IF(AND(DATE(2026,9,12)>=$C46,DATE(2026,9,12)<=$D46),IF(DATE(2026,9,12)<$C46+ROUND($E46*($D46-$C46+1),0),"█","░"),"")) | I46: =IF($F46="Yes",IF(DATE(2026,9,13)=$C46,"◆",""),IF(AND(DATE(2026,9,13)>=$C46,DATE(2026,9,13)<=$D46),IF(DATE(2026,9,13)<$C46+ROUND($E46*($D46-$C46+1),0),"█","░"),"")) | J46: =IF($F46="Yes",IF(DATE(2026,9,14)=$C46,"◆",""),IF(AND(DATE(2026,9,14)>=$C46,DATE(2026,9,14)<=$D46),IF(DATE(2026,9,14)<$C46+ROUND($E46*($D46-$C46+1),0),"█","░"),"")) | K46: =IF($F46="Yes",IF(DATE(2026,9,15)=$C46,"◆",""),IF(AND(DATE(2026,9,15)>=$C46,DATE(2026,9,15)<=$D46),IF(DATE(2026,9,15)<$C46+ROUND($E46*($D46-$C46+1),0),"█","░"),"")) | L46: =IF($F46="Yes",IF(DATE(2026,9,16)=$C46,"◆",""),IF(AND(DATE(2026,9,16)>=$C46,DATE(2026,9,16)<=$D46),IF(DATE(2026,9,16)<$C46+ROUND($E46*($D46-$C46+1),0),"█","░"),"")) | M46: =IF($F46="Yes",IF(DATE(2026,9,17)=$C46,"◆",""),IF(AND(DATE(2026,9,17)>=$C46,DATE(2026,9,17)<=$D46),IF(DATE(2026,9,17)<$C46+ROUND($E46*($D46-$C46+1),0),"█","░"),"")) | N46: =IF($F46="Yes",IF(DATE(2026,9,18)=$C46,"◆",""),IF(AND(DATE(2026,9,18)>=$C46,DATE(2026,9,18)<=$D46),IF(DATE(2026,9,18)<$C46+ROUND($E46*($D46-$C46+1),0),"█","░"),"")) | O46: =IF($F46="Yes",IF(DATE(2026,9,19)=$C46,"◆",""),IF(AND(DATE(2026,9,19)>=$C46,DATE(2026,9,19)<=$D46),IF(DATE(2026,9,19)<$C46+ROUND($E46*($D46-$C46+1),0),"█","░"),"")) | P46: =IF($F46="Yes",IF(DATE(2026,9,20)=$C46,"◆",""),IF(AND(DATE(2026,9,20)>=$C46,DATE(2026,9,20)<=$D46),IF(DATE(2026,9,20)<$C46+ROUND($E46*($D46-$C46+1),0),"█","░"),"")) | Q46: =IF($F46="Yes",IF(DATE(2026,9,21)=$C46,"◆",""),IF(AND(DATE(2026,9,21)>=$C46,DATE(2026,9,21)<=$D46),IF(DATE(2026,9,21)<$C46+ROUND($E46*($D46-$C46+1),0),"█","░"),"")) | R46: =IF($F46="Yes",IF(DATE(2026,9,22)=$C46,"◆",""),IF(AND(DATE(2026,9,22)>=$C46,DATE(2026,9,22)<=$D46),IF(DATE(2026,9,22)<$C46+ROUND($E46*($D46-$C46+1),0),"█","░"),"")) | S46: =IF($F46="Yes",IF(DATE(2026,9,23)=$C46,"◆",""),IF(AND(DATE(2026,9,23)>=$C46,DATE(2026,9,23)<=$D46),IF(DATE(2026,9,23)<$C46+ROUND($E46*($D46-$C46+1),0),"█","░"),"")) | T46: =IF($F46="Yes",IF(DATE(2026,9,24)=$C46,"◆",""),IF(AND(DATE(2026,9,24)>=$C46,DATE(2026,9,24)<=$D46),IF(DATE(2026,9,24)<$C46+ROUND($E46*($D46-$C46+1),0),"█","░"),"")) | U46: =IF($F46="Yes",IF(DATE(2026,9,25)=$C46,"◆",""),IF(AND(DATE(2026,9,25)>=$C46,DATE(2026,9,25)<=$D46),IF(DATE(2026,9,25)<$C46+ROUND($E46*($D46-$C46+1),0),"█","░"),"")) | V46: =IF($F46="Yes",IF(DATE(2026,9,26)=$C46,"◆",""),IF(AND(DATE(2026,9,26)>=$C46,DATE(2026,9,26)<=$D46),IF(DATE(2026,9,26)<$C46+ROUND($E46*($D46-$C46+1),0),"█","░"),"")) | W46: =IF($F46="Yes",IF(DATE(2026,9,27)=$C46,"◆",""),IF(AND(DATE(2026,9,27)>=$C46,DATE(2026,9,27)<=$D46),IF(DATE(2026,9,27)<$C46+ROUND($E46*($D46-$C46+1),0),"█","░"),"")) | X46: =IF($F46="Yes",IF(DATE(2026,9,28)=$C46,"◆",""),IF(AND(DATE(2026,9,28)>=$C46,DATE(2026,9,28)<=$D46),IF(DATE(2026,9,28)<$C46+ROUND($E46*($D46-$C46+1),0),"█","░"),"")) | Y46: =IF($F46="Yes",IF(DATE(2026,9,29)=$C46,"◆",""),IF(AND(DATE(2026,9,29)>=$C46,DATE(2026,9,29)<=$D46),IF(DATE(2026,9,29)<$C46+ROUND($E46*($D46-$C46+1),0),"█","░"),"")) | Z46: =IF($F46="Yes",IF(DATE(2026,9,30)=$C46,"◆",""),IF(AND(DATE(2026,9,30)>=$C46,DATE(2026,9,30)<=$D46),IF(DATE(2026,9,30)<$C46+ROUND($E46*($D46-$C46+1),0),"█","░"),"")) | AA46: =IF($F46="Yes",IF(DATE(2026,10,1)=$C46,"◆",""),IF(AND(DATE(2026,10,1)>=$C46,DATE(2026,10,1)<=$D46),IF(DATE(2026,10,1)<$C46+ROUND($E46*($D46-$C46+1),0),"█","░"),"")) | AB46: =IF($F46="Yes",IF(DATE(2026,10,2)=$C46,"◆",""),IF(AND(DATE(2026,10,2)>=$C46,DATE(2026,10,2)<=$D46),IF(DATE(2026,10,2)<$C46+ROUND($E46*($D46-$C46+1),0),"█","░"),"")) | AC46: =IF($F46="Yes",IF(DATE(2026,10,3)=$C46,"◆",""),IF(AND(DATE(2026,10,3)>=$C46,DATE(2026,10,3)<=$D46),IF(DATE(2026,10,3)<$C46+ROUND($E46*($D46-$C46+1),0),"█","░"),"")) | AD46: =IF($F46="Yes",IF(DATE(2026,10,4)=$C46,"◆",""),IF(AND(DATE(2026,10,4)>=$C46,DATE(2026,10,4)<=$D46),IF(DATE(2026,10,4)<$C46+ROUND($E46*($D46-$C46+1),0),"█","░"),"")) | AE46: =IF($F46="Yes",IF(DATE(2026,10,5)=$C46,"◆",""),IF(AND(DATE(2026,10,5)>=$C46,DATE(2026,10,5)<=$D46),IF(DATE(2026,10,5)<$C46+ROUND($E46*($D46-$C46+1),0),"█","░"),"")) | AF46: =IF($F46="Yes",IF(DATE(2026,10,6)=$C46,"◆",""),IF(AND(DATE(2026,10,6)>=$C46,DATE(2026,10,6)<=$D46),IF(DATE(2026,10,6)<$C46+ROUND($E46*($D46-$C46+1),0),"█","░"),"")) | AG46: =IF($F46="Yes",IF(DATE(2026,10,7)=$C46,"◆",""),IF(AND(DATE(2026,10,7)>=$C46,DATE(2026,10,7)<=$D46),IF(DATE(2026,10,7)<$C46+ROUND($E46*($D46-$C46+1),0),"█","░"),"")) | AH46: =IF($F46="Yes",IF(DATE(2026,10,8)=$C46,"◆",""),IF(AND(DATE(2026,10,8)>=$C46,DATE(2026,10,8)<=$D46),IF(DATE(2026,10,8)<$C46+ROUND($E46*($D46-$C46+1),0),"█","░"),"")) | AI46: =IF($F46="Yes",IF(DATE(2026,10,9)=$C46,"◆",""),IF(AND(DATE(2026,10,9)>=$C46,DATE(2026,10,9)<=$D46),IF(DATE(2026,10,9)<$C46+ROUND($E46*($D46-$C46+1),0),"█","░"),"")) | AJ46: =IF($F46="Yes",IF(DATE(2026,10,10)=$C46,"◆",""),IF(AND(DATE(2026,10,10)>=$C46,DATE(2026,10,10)<=$D46),IF(DATE(2026,10,10)<$C46+ROUND($E46*($D46-$C46+1),0),"█","░"),"")) | AK46: =IF($F46="Yes",IF(DATE(2026,10,11)=$C46,"◆",""),IF(AND(DATE(2026,10,11)>=$C46,DATE(2026,10,11)<=$D46),IF(DATE(2026,10,11)<$C46+ROUND($E46*($D46-$C46+1),0),"█","░"),"")) | AL46: =IF($F46="Yes",IF(DATE(2026,10,12)=$C46,"◆",""),IF(AND(DATE(2026,10,12)>=$C46,DATE(2026,10,12)<=$D46),IF(DATE(2026,10,12)<$C46+ROUND($E46*($D46-$C46+1),0),"█","░"),"")) | AM46: =IF($F46="Yes",IF(DATE(2026,10,13)=$C46,"◆",""),IF(AND(DATE(2026,10,13)>=$C46,DATE(2026,10,13)<=$D46),IF(DATE(2026,10,13)<$C46+ROUND($E46*($D46-$C46+1),0),"█","░"),"")) | AN46: =IF($F46="Yes",IF(DATE(2026,10,14)=$C46,"◆",""),IF(AND(DATE(2026,10,14)>=$C46,DATE(2026,10,14)<=$D46),IF(DATE(2026,10,14)<$C46+ROUND($E46*($D46-$C46+1),0),"█","░"),""))

Sheet Dashboard
B2: Governed Multi-Brand Agentic System — Executive Program Dashboard
B3: Live Project Window: 2026-09-11 to 2026-10-14 | All Metrics Update Dynamically via Structured Formulas
B5: TOTAL TASKS | D5: COMPLETED TASKS | F5: IN-PROGRESS TASKS | H5: NOT STARTED | J5: OVERALL PROGRESS
B6: =COUNTIF('Project Tracker'!J5:J45, "No") | D6: =COUNTIFS('Project Tracker'!J5:J45, "No", 'Project Tracker'!M5:M45, "Completed") | F6: =COUNTIFS('Project Tracker'!J5:J45, "No", 'Project Tracker'!M5:M45, "In Progress") | H6: =COUNTIFS('Project Tracker'!J5:J45, "No", 'Project Tracker'!M5:M45, "Not Started") | J6: =AVERAGEIFS('Project Tracker'!N5:N45, 'Project Tracker'!J5:J45, "No")
B8: TOTAL MILESTONES | D8: CLEARED MILESTONES | F8: REMAINING MILESTONES | H8: PROJECT WINDOW | J8: DAYS REMAINING
B9: =COUNTIF('Project Tracker'!J5:J45, "Yes") | D9: =COUNTIFS('Project Tracker'!J5:J45, "Yes", 'Project Tracker'!M5:M45, "Completed") | F9: =COUNTIFS('Project Tracker'!J5:J45, "Yes", 'Project Tracker'!M5:M45, "<>Completed") | H9: =MAX(0, DATE(2026,10,14) - DATE(2026,9,11) + 1) | J9: =MAX(0, DATE(2026,10,14) - TODAY())
B12: Workstream Status Breakdown | F12: Phase Execution & Governance Health
B13: Status | C13: Task Count | D13: % of Total | F13: Phase / Workstream | G13: Tasks | H13: Avg Progress
B14: Not Started | C14: =COUNTIFS('Project Tracker'!$J$5:$J$45, "No", 'Project Tracker'!$M$5:$M$45, "Not Started") | D14: =IF($B$5=0,0,C14/$B$5) | F14: Phase 1: Governance & Authority | G14: =COUNTIFS('Project Tracker'!$B$5:$B$45, "Phase 1*", 'Project Tracker'!$J$5:$J$45, "No") | H14: =IFERROR(AVERAGEIFS('Project Tracker'!$N$5:$N$45, 'Project Tracker'!$B$5:$B$45, "Phase 1*", 'Project Tracker'!$J$5:$J$45, "No"), 0)
B15: In Progress | C15: =COUNTIFS('Project Tracker'!$J$5:$J$45, "No", 'Project Tracker'!$M$5:$M$45, "In Progress") | D15: =IF($B$5=0,0,C15/$B$5) | F15: Phase 2: Governed Data Plane | G15: =COUNTIFS('Project Tracker'!$B$5:$B$45, "Phase 2*", 'Project Tracker'!$J$5:$J$45, "No") | H15: =IFERROR(AVERAGEIFS('Project Tracker'!$N$5:$N$45, 'Project Tracker'!$B$5:$B$45, "Phase 2*", 'Project Tracker'!$J$5:$J$45, "No"), 0)
B16: Completed | C16: =COUNTIFS('Project Tracker'!$J$5:$J$45, "No", 'Project Tracker'!$M$5:$M$45, "Completed") | D16: =IF($B$5=0,0,C16/$B$5) | F16: Phase 3: Sandbox Isolation | G16: =COUNTIFS('Project Tracker'!$B$5:$B$45, "Phase 3*", 'Project Tracker'!$J$5:$J$45, "No") | H16: =IFERROR(AVERAGEIFS('Project Tracker'!$N$5:$N$45, 'Project Tracker'!$B$5:$B$45, "Phase 3*", 'Project Tracker'!$J$5:$J$45, "No"), 0)
B17: On Hold | C17: =COUNTIFS('Project Tracker'!$J$5:$J$45, "No", 'Project Tracker'!$M$5:$M$45, "On Hold") | D17: =IF($B$5=0,0,C17/$B$5) | F17: Phase 4: Domain Intelligence | G17: =COUNTIFS('Project Tracker'!$B$5:$B$45, "Phase 4*", 'Project Tracker'!$J$5:$J$45, "No") | H17: =IFERROR(AVERAGEIFS('Project Tracker'!$N$5:$N$45, 'Project Tracker'!$B$5:$B$45, "Phase 4*", 'Project Tracker'!$J$5:$J$45, "No"), 0)
B18: Delayed | C18: =COUNTIFS('Project Tracker'!$J$5:$J$45, "No", 'Project Tracker'!$M$5:$M$45, "Delayed") | D18: =IF($B$5=0,0,C18/$B$5) | F18: Phase 5: Synthesis & HITL Gate | G18: =COUNTIFS('Project Tracker'!$B$5:$B$45, "Phase 5*", 'Project Tracker'!$J$5:$J$45, "No") | H18: =IFERROR(AVERAGEIFS('Project Tracker'!$N$5:$N$45, 'Project Tracker'!$B$5:$B$45, "Phase 5*", 'Project Tracker'!$J$5:$J$45, "No"), 0)
F19: Phase 6: Outbound Actuation | G19: =COUNTIFS('Project Tracker'!$B$5:$B$45, "Phase 6*", 'Project Tracker'!$J$5:$J$45, "No") | H19: =IFERROR(AVERAGEIFS('Project Tracker'!$N$5:$N$45, 'Project Tracker'!$B$5:$B$45, "Phase 6*", 'Project Tracker'!$J$5:$J$45, "No"), 0)
F20: Phase 7: Closed-Loop Telemetry | G20: =COUNTIFS('Project Tracker'!$B$5:$B$45, "Phase 7*", 'Project Tracker'!$J$5:$J$45, "No") | H20: =IFERROR(AVERAGEIFS('Project Tracker'!$N$5:$N$45, 'Project Tracker'!$B$5:$B$45, "Phase 7*", 'Project Tracker'!$J$5:$J$45, "No"), 0)
B21: Key Program Milestones & Status
B22: Milestone ID | C22: Checkpoint Name | D22: Scheduled Date | E22: Status | F22: Health
B23: ='Project Tracker'!A9 | C23: ='Project Tracker'!C9 | D23: ='Project Tracker'!E9 | E23: ='Project Tracker'!M9 | F23: ='Project Tracker'!O9
B24: ='Project Tracker'!A16 | C24: ='Project Tracker'!C16 | D24: ='Project Tracker'!E16 | E24: ='Project Tracker'!M16 | F24: ='Project Tracker'!O16
B25: ='Project Tracker'!A21 | C25: ='Project Tracker'!C21 | D25: ='Project Tracker'!E21 | E25: ='Project Tracker'!M21 | F25: ='Project Tracker'!O21
B26: ='Project Tracker'!A29 | C26: ='Project Tracker'!C29 | D26: ='Project Tracker'!E29 | E26: ='Project Tracker'!M29 | F26: ='Project Tracker'!O29
B27: ='Project Tracker'!A33 | C27: ='Project Tracker'!C33 | D27: ='Project Tracker'!E33 | E27: ='Project Tracker'!M33 | F27: ='Project Tracker'!O33
B28: ='Project Tracker'!A39 | C28: ='Project Tracker'!C39 | D28: ='Project Tracker'!E39 | E28: ='Project Tracker'!M39 | F28: ='Project Tracker'!O39
B29: ='Project Tracker'!A45 | C29: ='Project Tracker'!C45 | D29: ='Project Tracker'!E45 | E29: ='Project Tracker'!M45 | F29: ='Project Tracker'!O45

Sheet Resources
A2: Governed Multi-Brand Agentic System — Resource Matrix & Utilization
A3: Aggregates workload across human owners, control nodes, worker agents, and sandbox components
A4: Resource Name | B4: Total Assigned Tasks | C4: Completed | D4: In Progress | E4: Remaining | F4: Average Progress | G4: Operational Role & Allocation Notes
A5: Brand Stakeholder / Portfolio Owner | B5: =COUNTIFS('Project Tracker'!$K$5:$K$45, "*" & A5 & "*", 'Project Tracker'!$J$5:$J$45, "No") | C5: =COUNTIFS('Project Tracker'!$K$5:$K$45, "*" & A5 & "*", 'Project Tracker'!$M$5:$M$45, "Completed", 'Project Tracker'!$J$5:$J$45, "No") | D5: =COUNTIFS('Project Tracker'!$K$5:$K$45, "*" & A5 & "*", 'Project Tracker'!$M$5:$M$45, "In Progress", 'Project Tracker'!$J$5:$J$45, "No") | E5: =COUNTIFS('Project Tracker'!$K$5:$K$45, "*" & A5 & "*", 'Project Tracker'!$M$5:$M$45, "<>Completed", 'Project Tracker'!$J$5:$J$45, "No") | F5: =IFERROR(AVERAGEIFS('Project Tracker'!$N$5:$N$45, 'Project Tracker'!$K$5:$K$45, "*" & A5 & "*", 'Project Tracker'!$J$5:$J$45, "No"), 0) | G5: Governance authority; strategic directive inputs at project launch and acceptance sign-off at project close.
A6: Enterprise Policy Engine | B6: =COUNTIFS('Project Tracker'!$K$5:$K$45, "*" & A6 & "*", 'Project Tracker'!$J$5:$J$45, "No") | C6: =COUNTIFS('Project Tracker'!$K$5:$K$45, "*" & A6 & "*", 'Project Tracker'!$M$5:$M$45, "Completed", 'Project Tracker'!$J$5:$J$45, "No") | D6: =COUNTIFS('Project Tracker'!$K$5:$K$45, "*" & A6 & "*", 'Project Tracker'!$M$5:$M$45, "In Progress", 'Project Tracker'!$J$5:$J$45, "No") | E6: =COUNTIFS('Project Tracker'!$K$5:$K$45, "*" & A6 & "*", 'Project Tracker'!$M$5:$M$45, "<>Completed", 'Project Tracker'!$J$5:$J$45, "No") | F6: =IFERROR(AVERAGEIFS('Project Tracker'!$N$5:$N$45, 'Project Tracker'!$K$5:$K$45, "*" & A6 & "*", 'Project Tracker'!$J$5:$J$45, "No"), 0) | G6: Automated compliance engine; versioned policy envelope publication and tenant claim boundary enforcement.
A7: Policy & Authorization Boundary (PAB) | B7: =COUNTIFS('Project Tracker'!$K$5:$K$45, "*" & A7 & "*", 'Project Tracker'!$J$5:$J$45, "No") | C7: =COUNTIFS('Project Tracker'!$K$5:$K$45, "*" & A7 & "*", 'Project Tracker'!$M$5:$M$45, "Completed", 'Project Tracker'!$J$5:$J$45, "No") | D7: =COUNTIFS('Project Tracker'!$K$5:$K$45, "*" & A7 & "*", 'Project Tracker'!$M$5:$M$45, "In Progress", 'Project Tracker'!$J$5:$J$45, "No") | E7: =COUNTIFS('Project Tracker'!$K$5:$K$45, "*" & A7 & "*", 'Project Tracker'!$M$5:$M$45, "<>Completed", 'Project Tracker'!$J$5:$J$45, "No") | F7: =IFERROR(AVERAGEIFS('Project Tracker'!$N$5:$N$45, 'Project Tracker'!$K$5:$K$45, "*" & A7 & "*", 'Project Tracker'!$J$5:$J$45, "No"), 0) | G7: Security proxy; caller ID evaluation, monotonic attenuation verification, and cryptographic delegation checks.
A8: Canonical Task State Machine (CTS) | B8: =COUNTIFS('Project Tracker'!$K$5:$K$45, "*" & A8 & "*", 'Project Tracker'!$J$5:$J$45, "No") | C8: =COUNTIFS('Project Tracker'!$K$5:$K$45, "*" & A8 & "*", 'Project Tracker'!$M$5:$M$45, "Completed", 'Project Tracker'!$J$5:$J$45, "No") | D8: =COUNTIFS('Project Tracker'!$K$5:$K$45, "*" & A8 & "*", 'Project Tracker'!$M$5:$M$45, "In Progress", 'Project Tracker'!$J$5:$J$45, "No") | E8: =COUNTIFS('Project Tracker'!$K$5:$K$45, "*" & A8 & "*", 'Project Tracker'!$M$5:$M$45, "<>Completed", 'Project Tracker'!$J$5:$J$45, "No") | F8: =IFERROR(AVERAGEIFS('Project Tracker'!$N$5:$N$45, 'Project Tracker'!$K$5:$K$45, "*" & A8 & "*", 'Project Tracker'!$J$5:$J$45, "No"), 0) | G8: Control state engine; maintains task DAG transitions, hold gates, and dependency locks.
A9: Central Enterprise Database (CDB) | B9: =COUNTIFS('Project Tracker'!$K$5:$K$45, "*" & A9 & "*", 'Project Tracker'!$J$5:$J$45, "No") | C9: =COUNTIFS('Project Tracker'!$K$5:$K$45, "*" & A9 & "*", 'Project Tracker'!$M$5:$M$45, "Completed", 'Project Tracker'!$J$5:$J$45, "No") | D9: =COUNTIFS('Project Tracker'!$K$5:$K$45, "*" & A9 & "*", 'Project Tracker'!$M$5:$M$45, "In Progress", 'Project Tracker'!$J$5:$J$45, "No") | E9: =COUNTIFS('Project Tracker'!$K$5:$K$45, "*" & A9 & "*", 'Project Tracker'!$M$5:$M$45, "<>Completed", 'Project Tracker'!$J$5:$J$45, "No") | F9: =IFERROR(AVERAGEIFS('Project Tracker'!$N$5:$N$45, 'Project Tracker'!$K$5:$K$45, "*" & A9 & "*", 'Project Tracker'!$J$5:$J$45, "No"), 0) | G9: Persistent system of record; relational tables, vector spaces, and timeseries telemetry ingestion.
A10: Headless CMS & Web Store (CMS) | B10: =COUNTIFS('Project Tracker'!$K$5:$K$45, "*" & A10 & "*", 'Project Tracker'!$J$5:$J$45, "No") | C10: =COUNTIFS('Project Tracker'!$K$5:$K$45, "*" & A10 & "*", 'Project Tracker'!$M$5:$M$45, "Completed", 'Project Tracker'!$J$5:$J$45, "No") | D10: =COUNTIFS('Project Tracker'!$K$5:$K$45, "*" & A10 & "*", 'Project Tracker'!$M$5:$M$45, "In Progress", 'Project Tracker'!$J$5:$J$45, "No") | E10: =COUNTIFS('Project Tracker'!$K$5:$K$45, "*" & A10 & "*", 'Project Tracker'!$M$5:$M$45, "<>Completed", 'Project Tracker'!$J$5:$J$45, "No") | F10: =IFERROR(AVERAGEIFS('Project Tracker'!$N$5:$N$45, 'Project Tracker'!$K$5:$K$45, "*" & A10 & "*", 'Project Tracker'!$J$5:$J$45, "No"), 0) | G10: Content store; staged page layout schemas, catalog diffs, and production frontend models.
A11: Institutional Memory Store (MEM) | B11: =COUNTIFS('Project Tracker'!$K$5:$K$45, "*" & A11 & "*", 'Project Tracker'!$J$5:$J$45, "No") | C11: =COUNTIFS('Project Tracker'!$K$5:$K$45, "*" & A11 & "*", 'Project Tracker'!$M$5:$M$45, "Completed", 'Project Tracker'!$J$5:$J$45, "No") | D11: =COUNTIFS('Project Tracker'!$K$5:$K$45, "*" & A11 & "*", 'Project Tracker'!$M$5:$M$45, "In Progress", 'Project Tracker'!$J$5:$J$45, "No") | E11: =COUNTIFS('Project Tracker'!$K$5:$K$45, "*" & A11 & "*", 'Project Tracker'!$M$5:$M$45, "<>Completed", 'Project Tracker'!$J$5:$J$45, "No") | F11: =IFERROR(AVERAGEIFS('Project Tracker'!$N$5:$N$45, 'Project Tracker'!$K$5:$K$45, "*" & A11 & "*", 'Project Tracker'!$J$5:$J$45, "No"), 0) | G11: Institutional knowledge base; promoted heuristics, brand persona parameters, and optimization weights.
A12: Artifact & Evidence Registry (ART) | B12: =COUNTIFS('Project Tracker'!$K$5:$K$45, "*" & A12 & "*", 'Project Tracker'!$J$5:$J$45, "No") | C12: =COUNTIFS('Project Tracker'!$K$5:$K$45, "*" & A12 & "*", 'Project Tracker'!$M$5:$M$45, "Completed", 'Project Tracker'!$J$5:$J$45, "No") | D12: =COUNTIFS('Project Tracker'!$K$5:$K$45, "*" & A12 & "*", 'Project Tracker'!$M$5:$M$45, "In Progress", 'Project Tracker'!$J$5:$J$45, "No") | E12: =COUNTIFS('Project Tracker'!$K$5:$K$45, "*" & A12 & "*", 'Project Tracker'!$M$5:$M$45, "<>Completed", 'Project Tracker'!$J$5:$J$45, "No") | F12: =IFERROR(AVERAGEIFS('Project Tracker'!$N$5:$N$45, 'Project Tracker'!$K$5:$K$45, "*" & A12 & "*", 'Project Tracker'!$J$5:$J$45, "No"), 0) | G12: Content-addressable storage; UUID and SHA-256 versioned diffs, proof dossiers, and asset packs.
A13: Governed MCP Data Boundary | B13: =COUNTIFS('Project Tracker'!$K$5:$K$45, "*" & A13 & "*", 'Project Tracker'!$J$5:$J$45, "No") | C13: =COUNTIFS('Project Tracker'!$K$5:$K$45, "*" & A13 & "*", 'Project Tracker'!$M$5:$M$45, "Completed", 'Project Tracker'!$J$5:$J$45, "No") | D13: =COUNTIFS('Project Tracker'!$K$5:$K$45, "*" & A13 & "*", 'Project Tracker'!$M$5:$M$45, "In Progress", 'Project Tracker'!$J$5:$J$45, "No") | E13: =COUNTIFS('Project Tracker'!$K$5:$K$45, "*" & A13 & "*", 'Project Tracker'!$M$5:$M$45, "<>Completed", 'Project Tracker'!$J$5:$J$45, "No") | F13: =IFERROR(AVERAGEIFS('Project Tracker'!$N$5:$N$45, 'Project Tracker'!$K$5:$K$45, "*" & A13 & "*", 'Project Tracker'!$J$5:$J$45, "No"), 0) | G13: Protocol capability gateway; CRUD adapters and schema-validated access to enterprise storage.
A14: Agentic RAG Controller | B14: =COUNTIFS('Project Tracker'!$K$5:$K$45, "*" & A14 & "*", 'Project Tracker'!$J$5:$J$45, "No") | C14: =COUNTIFS('Project Tracker'!$K$5:$K$45, "*" & A14 & "*", 'Project Tracker'!$M$5:$M$45, "Completed", 'Project Tracker'!$J$5:$J$45, "No") | D14: =COUNTIFS('Project Tracker'!$K$5:$K$45, "*" & A14 & "*", 'Project Tracker'!$M$5:$M$45, "In Progress", 'Project Tracker'!$J$5:$J$45, "No") | E14: =COUNTIFS('Project Tracker'!$K$5:$K$45, "*" & A14 & "*", 'Project Tracker'!$M$5:$M$45, "<>Completed", 'Project Tracker'!$J$5:$J$45, "No") | F14: =IFERROR(AVERAGEIFS('Project Tracker'!$N$5:$N$45, 'Project Tracker'!$K$5:$K$45, "*" & A14 & "*", 'Project Tracker'!$J$5:$J$45, "No"), 0) | G14: Exclusive Model A data retrieval broker for the Intelligence Engine; semantic search & freshness checks.
A15: Sandbox Controller (agent_sandbox) | B15: =COUNTIFS('Project Tracker'!$K$5:$K$45, "*" & A15 & "*", 'Project Tracker'!$J$5:$J$45, "No") | C15: =COUNTIFS('Project Tracker'!$K$5:$K$45, "*" & A15 & "*", 'Project Tracker'!$M$5:$M$45, "Completed", 'Project Tracker'!$J$5:$J$45, "No") | D15: =COUNTIFS('Project Tracker'!$K$5:$K$45, "*" & A15 & "*", 'Project Tracker'!$M$5:$M$45, "In Progress", 'Project Tracker'!$J$5:$J$45, "No") | E15: =COUNTIFS('Project Tracker'!$K$5:$K$45, "*" & A15 & "*", 'Project Tracker'!$M$5:$M$45, "<>Completed", 'Project Tracker'!$J$5:$J$45, "No") | F15: =IFERROR(AVERAGEIFS('Project Tracker'!$N$5:$N$45, 'Project Tracker'!$K$5:$K$45, "*" & A15 & "*", 'Project Tracker'!$J$5:$J$45, "No"), 0) | G15: Micro-virtualization boundary; cgroups memory limits, seccomp profiles, and strict egress proxying.
A16: Specialist Sub-Agents (L4_SUBS) | B16: =COUNTIFS('Project Tracker'!$K$5:$K$45, "*" & A16 & "*", 'Project Tracker'!$J$5:$J$45, "No") | C16: =COUNTIFS('Project Tracker'!$K$5:$K$45, "*" & A16 & "*", 'Project Tracker'!$M$5:$M$45, "Completed", 'Project Tracker'!$J$5:$J$45, "No") | D16: =COUNTIFS('Project Tracker'!$K$5:$K$45, "*" & A16 & "*", 'Project Tracker'!$M$5:$M$45, "In Progress", 'Project Tracker'!$J$5:$J$45, "No") | E16: =COUNTIFS('Project Tracker'!$K$5:$K$45, "*" & A16 & "*", 'Project Tracker'!$M$5:$M$45, "<>Completed", 'Project Tracker'!$J$5:$J$45, "No") | F16: =IFERROR(AVERAGEIFS('Project Tracker'!$N$5:$N$45, 'Project Tracker'!$K$5:$K$45, "*" & A16 & "*", 'Project Tracker'!$J$5:$J$45, "No"), 0) | G16: Ephemeral micro-tools (S_CODE, S_ALLOC, S_COPY, S_VAL, S_SCRAPE, S_PARSE, S_ATTR) executed in sandbox.
... A28: W3C PROV Immutable Ledger | B28: =COUNTIFS('Project Tracker'!$K$5:$K$45, "*" & A28 & "*", 'Project Tracker'!$J$5:$J$45, "No") | C28: =COUNTIFS('Project Tracker'!$K$5:$K$45, "*" & A28 & "*", 'Project Tracker'!$M$5:$M$45, "Completed", 'Project Tracker'!$J$5:$J$45, "No") | D28: =COUNTIFS('Project Tracker'!$K$5:$K$45, "*" & A28 & "*", 'Project Tracker'!$M$5:$M$45, "In Progress", 'Project Tracker'!$J$5:$J$45, "No") | E28: =COUNTIFS('Project Tracker'!$K$5:$K$45, "*" & A28 & "*", 'Project Tracker'!$M$5:$M$45, "<>Completed", 'Project Tracker'!$J$5:$J$45, "No") | F28: =IFERROR(AVERAGEIFS('Project Tracker'!$N$5:$N$45, 'Project Tracker'!$K$5:$K$45, "*" & A28 & "*", 'Project Tracker'!$J$5:$J$45, "No"), 0) | G28: Tamper-evident audit store; W3C PROV entity-activity-agent relationships and execution lineage.

Sheet Assumptions & Gaps
A2: Governed Multi-Brand Agentic System — Architectural Assumptions & Gaps
A3: Formal reconciliation audit categorized by standard governance labels
A4: Classification Label | B4: Source Field / Item | C4: Identified Condition / Architectural Context | D4: Resolution Implemented in Workbook | E4: User / Stakeholder Action Needed
A5: [CONFLICT] | B5: System Architecture Flowcharts | C5: Comparison between Final-Level Full Architecture.md and flowchart.drawio.html. | D5: Zero architectural conflicts identified. The Draw.io XML contains the identical Mermaid syntax and layer groupings. | E5: None. System topology is 100% verified and structurally consistent.
A6: [INFERRED] | B6: Task Calendar Scheduling | C6: Architectural specifications define DAG flow and component interactions without explicit calendar dates. | D6: Inferred continuous dates across the fixed 34-day project window (2026-09-11 to 2026-10-14) respecting all DAG dependencies. | E6: Review inferred task sequencing; adjust individual Start/End dates if team availability shifts.
A7: [INFERRED] | B7: Baseline Progress Protocol | C7: Blueprint indicates foundational specifications are established, but operational project requires live tracking. | D7: All tasks initialized at 0% with 'Not Started' status to allow live tracking from day one; baseline readiness documented in notes. | E7: Update Progress % in Project Tracker as implementation milestones are executed.
A8: [INFERRED] | B8: Finish-to-Start Same-Day Handoffs | C8: Successive tasks share boundary dates (e.g., T01/T02 finish on Sept 12 while T03/T04 start on Sept 12). | D8: Treated as valid same-day handoffs where predecessor deliverables unblock successor initialization within the same working day. | E8: Confirm operational teams are prepared for intra-day handoffs at Phase transition points.
A9: [MISSING] | B9: External Platform Credentials | C9: API keys, OAuth tokens, and staging credentials for Meta Ads, Google Ads, TikTok, and CMS production are omitted. | D9: Assumed that credentials will be injected via enterprise secret management vaults into Outbound MCP Boundary during T25. | E9: Security team must provision cryptographic secrets and audience tokens in key vaults prior to Phase 6.
A10: [MISSING] | B10: Exact Financial Spend Caps | C10: Data flow diagrams reference spend limits and media budgets conceptually without discrete currency numbers. | D10: Structured action preview generator (T23) is designed to ingest exact budget envelopes defined by Brand Owner in T01. | E10: Brand Portfolio Owner must supply numerical budget ceilings during Task T01 kickoff.
A11: [OUTSIDE WINDOW] | B11: Project Window Conformance | C11: Verification of all 34 tasks and 7 milestones against fixed window (2026-09-11 to 2026-10-14). | D11: Zero tasks scheduled outside the allowed project window. Earliest start is Sept 11, 2026; latest end is Oct 14, 2026. | E11: None. Schedule conforms strictly to the 34-calendar-day mandate.
A12: [DEPENDENCY ISSUE] | B12: DAG Integrity Verification | C12: Audit of direct predecessor and successor relationships across the multi-tier engine hierarchy. | D12: Zero dependency cycles or orphan nodes exist. Authority monotonically decreases down the delegation tree. | E12: Maintain Model A broker exclusivity when modifying task dependencies.

Sheet Instructions
A2: Governed Multi-Brand Agentic System — Standard Operating Instructions
A3: Operational guide for editing, updating progress, maintaining dependencies, and tracking schedules
A4: Instruction Topic | B4: Standard Operating Protocol | C4: Impact on Formulas & Sheets | D4: Best Practice Guidance
A5: 1. Where to Edit Tasks | B5: Edit tasks strictly in Sheet 1 ('Project Tracker'). Columns A through F, H, I, J, K, L, M, N, and P accept user inputs. | C5: Changes automatically propagate to Sheet 2 ('Gantt'), Sheet 3 ('Dashboard'), and Sheet 4 ('Resources'). | D5: Never type over calculated columns (Column G: Duration, Column O: Schedule Health).
A6: 2. How to Change Dates | B6: Enter dates in 'YYYY-MM-DD' format in Start Date (Col E) and End Date (Col F). | C6: Duration automatically recalculates via formula (=[@End]-[@Start]+1). Gantt timeline bars adjust length. | D6: Ensure Start Date <= End Date. Stay within project bounds (2026-09-11 to 2026-10-14).
A7: 3. How to Update Progress % | B7: Type a percentage (e.g., 50%) or decimal (e.g., 0.50) into Progress % (Col N). Cell is validated for 0.0 to 1.0. | C7: Gantt fills the completed duration bar with dark blue blocks ('█') based on the percentage entered. | D7: When progress reaches 100%, update Status to 'Completed' to sync health indicators.
A8: 4. How to Change Status | B8: Select Status from the Data Validation dropdown in Col M (Not Started, In Progress, Completed, On Hold, Delayed). | C8: Reconciles with Schedule Health (Col O) and updates Dashboard KPI cards and status breakdown table. | D8: If a task is blocked, mark as 'On Hold' or 'Delayed' rather than artificially changing dates.
A9: 5. How to Assign Resources | B9: Select or enter the responsible entity in Col K. Use approved roster names to ensure proper resource aggregation. | C9: Updates assigned task counts, completion rates, and average progress in Sheet 4 ('Resources'). | D9: For joint ownership, enter comma-separated entities (e.g., 'Intelligence Engine & Brand Owner').
A10: 6. Adding or Modifying Dependencies | B10: Update Predecessor IDs in Col H (e.g., 'T01, T02') and select Dependency Type in Col I (FS, SS, FF, SF). | C10: Maintains the Directed Acyclic Graph (DAG). Does not alter dates automatically but guides schedule integrity. | D10: Successor start dates should never precede the completion date of their finish-to-start predecessors.
A11: 7. Adding a New Task Safely | B11: Right-click inside 'ProjectTrackerTable' above row 45 and select Insert > Table Rows Above. | C11: Formulas in Duration and Schedule Health, as well as Data Validation rules, expand automatically. | D11: Assign a unique Task ID (e.g., T35). Update Gantt row links to maintain alignment.
A12: 8. Milestone Markers | B12: Set Milestone to 'Yes' in Col J. Set Start Date equal to End Date (e.g., 2026-09-14). | C12: Gantt renders a gold diamond symbol ('◆') instead of a duration bar; row highlights yellow. | D12: Milestones are tracked separately in Dashboard KPI cards and Milestone clearance schedules.
A13: 9. Dynamic Gantt Behavior | B13: Sheet 2 ('Gantt') is 100% formula-driven from 'Project Tracker' across 34 continuous calendar days. | C13: No manual coloring needed. Completed portions show as '█' (solid blue), remaining as '░' (light blue). | D13: Weekend days (Sat/Sun) feature dedicated shading in timeline header rows 4 and 5.
A14: 10. Dashboard Health Indicators | B14: Sheet 3 ('Dashboard') aggregates all active task data using COUNTIFS and AVERAGEIFS. | C14: Health shows 'On Track' (normal), 'Behind Schedule' (start elapsed with 0%), 'Overdue' (end elapsed), or 'Complete'. | D14: Review the 'Key Program Milestones' table on the Dashboard weekly to ensure delivery on schedule.
